Workbook
Name ValidWorkPackageNames: 'WORK PACKAGES'!$D$2:$D$100
Name ValidWorkPackageIDs: 'WORK PACKAGES'!$A$2:$A$100

Sheet DASHBOARD
A1: PROJECT PROGRESS DASHBOARD
A2: Work Package ID | B2: Package Code | C2: Priority Level | D2: Critical Path? | E2: Eng Completion | F2: Program Completion | G2: Conduit & Wire Pulls | H2: Devices Installed | I2: PreComm Completed | J2: BLOCKED - Eng Info | K2: BLOCKED - Vendor Info | L2: BLOCKED - Cond & Wire | M2: BLOCKED - Devices | N2: BLOCKED - PreComm | O2: Active Change Orders? | P2: Internal Gates Complete? | Q2: Open Punchlist Items | R2: Open RFIs | S2: Open Issues | T2: Weekly Notes | U2: Engineering Scope / Scope of Work
B3: =IF($A3="","",IFERROR(IF(INDEX('WORK PACKAGES'!$B$2:$B$100,MATCH($A3,'WORK PACKAGES'!$A$2:$A$100,0))="","",INDEX('WORK PACKAGES'!$B$2:$B$100,MATCH($A3,'WORK PACKAGES'!$A$2:$A$100,0))),"")) | C3: =IF($A3="","",IFERROR(IF(INDEX('WORK PACKAGES'!$E$2:$E$100,MATCH($A3,'WORK PACKAGES'!$A$2:$A$100,0))="","",INDEX('WORK PACKAGES'!$E$2:$E$100,MATCH($A3,'WORK PACKAGES'!$A$2:$A$100,0))),"")) | E3: =IF($A3="","",IFERROR(IF(INDEX('WP PROGRESS'!$F$2:$F$100,MATCH($A3,'WP PROGRESS'!$A$2:$A$100,0))="","",INDEX('WP PROGRESS'!$F$2:$F$100,MATCH($A3,'WP PROGRESS'!$A$2:$A$100,0))),"")) | F3: =IF($A3="","",IFERROR(IF(INDEX('WP PROGRESS'!$G$2:$G$100,MATCH($A3,'WP PROGRESS'!$A$2:$A$100,0))="","",INDEX('WP PROGRESS'!$G$2:$G$100,MATCH($A3,'WP PROGRESS'!$A$2:$A$100,0))),"")) | G3: =IF($A3="","",IFERROR(IF(INDEX('WP PROGRESS'!$H$2:$H$100,MATCH($A3,'WP PROGRESS'!$A$2:$A$100,0))="","",INDEX('WP PROGRESS'!$H$2:$H$100,MATCH($A3,'WP PROGRESS'!$A$2:$A$100,0))),"")) | H3: =IF($A3="","",IFERROR(IF(INDEX('WP PROGRESS'!$I$2:$I$100,MATCH($A3,'WP PROGRESS'!$A$2:$A$100,0))="","",INDEX('WP PROGRESS'!$I$2:$I$100,MATCH($A3,'WP PROGRESS'!$A$2:$A$100,0))),"")) | I3: =IF($A3="","",IFERROR(IF(INDEX('WP PROGRESS'!$K$2:$K$100,MATCH($A3,'WP PROGRESS'!$A$2:$A$100,0))="","",INDEX('WP PROGRESS'!$K$2:$K$100,MATCH($A3,'WP PROGRESS'!$A$2:$A$100,0))),"")) | P3: =IF($A3="","",IFERROR(IF(INDEX('WP PROGRESS'!$V$2:$V$100,MATCH($A3,'WP PROGRESS'!$A$2:$A$100,0))="","",INDEX('WP PROGRESS'!$V$2:$V$100,MATCH($A3,'WP PROGRESS'!$A$2:$A$100,0))),"")) | Q3: =IF($A3="","",IFERROR(IF(INDEX('WP PROGRESS'!$E$2:$E$100,MATCH($A3,'WP PROGRESS'!$A$2:$A$100,0))="","",INDEX('WP PROGRESS'!$E$2:$E$100,MATCH($A3,'WP PROGRESS'!$A$2:$A$100,0))),"")) | R3: =IF($A3="","",IFERROR(IF(INDEX('WP PROGRESS'!$Z$2:$Z$100,MATCH($A3,'WP PROGRESS'!$A$2:$A$100,0))="","",INDEX('WP PROGRESS'!$Z$2:$Z$100,MATCH($A3,'WP PROGRESS'!$A$2:$A$100,0))),"")) | S3: =IF($A3="","",COUNTIFS(ISSUES!$P$5:$P$200,"*"&$A3&"*",ISSUES!$H$5:$H$200,"<>Closed",ISSUES!$H$5:$H$200,"<>Resolved",ISSUES!$H$5:$H$200,"<>Cancelled",ISSUES!$H$5:$H$200,"<>",ISSUES!$A$5:$A$200,"<>")) | U3: =IF($A3="","",IFERROR(IF(INDEX('WORK PACKAGES'!$G$2:$G$100,MATCH($A3,'WORK PACKAGES'!$A$2:$A$100,0))="","",INDEX('WORK PACKAGES'!$G$2:$G$100,MATCH($A3,'WORK PACKAGES'!$A$2:$A$100,0))),""))
B4: =IF($A4="","",IFERROR(IF(INDEX('WORK PACKAGES'!$B$2:$B$100,MATCH($A4,'WORK PACKAGES'!$A$2:$A$100,0))="","",INDEX('WORK PACKAGES'!$B$2:$B$100,MATCH($A4,'WORK PACKAGES'!$A$2:$A$100,0))),"")) | C4: =IF($A4="","",IFERROR(IF(INDEX('WORK PACKAGES'!$E$2:$E$100,MATCH($A4,'WORK PACKAGES'!$A$2:$A$100,0))="","",INDEX('WORK PACKAGES'!$E$2:$E$100,MATCH($A4,'WORK PACKAGES'!$A$2:$A$100,0))),"")) | E4: =IF($A4="","",IFERROR(IF(INDEX('WP PROGRESS'!$F$2:$F$100,MATCH($A4,'WP PROGRESS'!$A$2:$A$100,0))="","",INDEX('WP PROGRESS'!$F$2:$F$100,MATCH($A4,'WP PROGRESS'!$A$2:$A$100,0))),"")) | F4: =IF($A4="","",IFERROR(IF(INDEX('WP PROGRESS'!$G$2:$G$100,MATCH($A4,'WP PROGRESS'!$A$2:$A$100,0))="","",INDEX('WP PROGRESS'!$G$2:$G$100,MATCH($A4,'WP PROGRESS'!$A$2:$A$100,0))),"")) | G4: =IF($A4="","",IFERROR(IF(INDEX('WP PROGRESS'!$H$2:$H$100,MATCH($A4,'WP PROGRESS'!$A$2:$A$100,0))="","",INDEX('WP PROGRESS'!$H$2:$H$100,MATCH($A4,'WP PROGRESS'!$A$2:$A$100,0))),"")) | H4: =IF($A4="","",IFERROR(IF(INDEX('WP PROGRESS'!$I$2:$I$100,MATCH($A4,'WP PROGRESS'!$A$2:$A$100,0))="","",INDEX('WP PROGRESS'!$I$2:$I$100,MATCH($A4,'WP PROGRESS'!$A$2:$A$100,0))),"")) | I4: =IF($A4="","",IFERROR(IF(INDEX('WP PROGRESS'!$K$2:$K$100,MATCH($A4,'WP PROGRESS'!$A$2:$A$100,0))="","",INDEX('WP PROGRESS'!$K$2:$K$100,MATCH($A4,'WP PROGRESS'!$A$2:$A$100,0))),"")) | P4: =IF($A4="","",IFERROR(IF(INDEX('WP PROGRESS'!$V$2:$V$100,MATCH($A4,'WP PROGRESS'!$A$2:$A$100,0))="","",INDEX('WP PROGRESS'!$V$2:$V$100,MATCH($A4,'WP PROGRESS'!$A$2:$A$100,0))),"")) | Q4: =IF($A4="","",IFERROR(IF(INDEX('WP PROGRESS'!$E$2:$E$100,MATCH($A4,'WP PROGRESS'!$A$2:$A$100,0))="","",INDEX('WP PROGRESS'!$E$2:$E$100,MATCH($A4,'WP PROGRESS'!$A$2:$A$100,0))),"")) | R4: =IF($A4="","",IFERROR(IF(INDEX('WP PROGRESS'!$Z$2:$Z$100,MATCH($A4,'WP PROGRESS'!$A$2:$A$100,0))="","",INDEX('WP PROGRESS'!$Z$2:$Z$100,MATCH($A4,'WP PROGRESS'!$A$2:$A$100,0))),"")) | S4: =IF($A4="","",COUNTIFS(ISSUES!$P$5:$P$200,"*"&$A4&"*",ISSUES!$H$5:$H$200,"<>Closed",ISSUES!$H$5:$H$200,"<>Resolved",ISSUES!$H$5:$H$200,"<>Cancelled",ISSUES!$H$5:$H$200,"<>",ISSUES!$A$5:$A$200,"<>")) | U4: =IF($A4="","",IFERROR(IF(INDEX('WORK PACKAGES'!$G$2:$G$100,MATCH($A4,'WORK PACKAGES'!$A$2:$A$100,0))="","",INDEX('WORK PACKAGES'!$G$2:$G$100,MATCH($A4,'WORK PACKAGES'!$A$2:$A$100,0))),""))
B5: =IF($A5="","",IFERROR(IF(INDEX('WORK PACKAGES'!$B$2:$B$100,MATCH($A5,'WORK PACKAGES'!$A$2:$A$100,0))="","",INDEX('WORK PACKAGES'!$B$2:$B$100,MATCH($A5,'WORK PACKAGES'!$A$2:$A$100,0))),"")) | C5: =IF($A5="","",IFERROR(IF(INDEX('WORK PACKAGES'!$E$2:$E$100,MATCH($A5,'WORK PACKAGES'!$A$2:$A$100,0))="","",INDEX('WORK PACKAGES'!$E$2:$E$100,MATCH($A5,'WORK PACKAGES'!$A$2:$A$100,0))),"")) | E5: =IF($A5="","",IFERROR(IF(INDEX('WP PROGRESS'!$F$2:$F$100,MATCH($A5,'WP PROGRESS'!$A$2:$A$100,0))="","",INDEX('WP PROGRESS'!$F$2:$F$100,MATCH($A5,'WP PROGRESS'!$A$2:$A$100,0))),"")) | F5: =IF($A5="","",IFERROR(IF(INDEX('WP PROGRESS'!$G$2:$G$100,MATCH($A5,'WP PROGRESS'!$A$2:$A$100,0))="","",INDEX('WP PROGRESS'!$G$2:$G$100,MATCH($A5,'WP PROGRESS'!$A$2:$A$100,0))),"")) | G5: =IF($A5="","",IFERROR(IF(INDEX('WP PROGRESS'!$H$2:$H$100,MATCH($A5,'WP PROGRESS'!$A$2:$A$100,0))="","",INDEX('WP PROGRESS'!$H$2:$H$100,MATCH($A5,'WP PROGRESS'!$A$2:$A$100,0))),"")) | H5: =IF($A5="","",IFERROR(IF(INDEX('WP PROGRESS'!$I$2:$I$100,MATCH($A5,'WP PROGRESS'!$A$2:$A$100,0))="","",INDEX('WP PROGRESS'!$I$2:$I$100,MATCH($A5,'WP PROGRESS'!$A$2:$A$100,0))),"")) | I5: =IF($A5="","",IFERROR(IF(INDEX('WP PROGRESS'!$K$2:$K$100,MATCH($A5,'WP PROGRESS'!$A$2:$A$100,0))="","",INDEX('WP PROGRESS'!$K$2:$K$100,MATCH($A5,'WP PROGRESS'!$A$2:$A$100,0))),"")) | P5: =IF($A5="","",IFERROR(IF(INDEX('WP PROGRESS'!$V$2:$V$100,MATCH($A5,'WP PROGRESS'!$A$2:$A$100,0))="","",INDEX('WP PROGRESS'!$V$2:$V$100,MATCH($A5,'WP PROGRESS'!$A$2:$A$100,0))),"")) | Q5: =IF($A5="","",IFERROR(IF(INDEX('WP PROGRESS'!$E$2:$E$100,MATCH($A5,'WP PROGRESS'!$A$2:$A$100,0))="","",INDEX('WP PROGRESS'!$E$2:$E$100,MATCH($A5,'WP PROGRESS'!$A$2:$A$100,0))),"")) | R5: =IF($A5="","",IFERROR(IF(INDEX('WP PROGRESS'!$Z$2:$Z$100,MATCH($A5,'WP PROGRESS'!$A$2:$A$100,0))="","",INDEX('WP PROGRESS'!$Z$2:$Z$100,MATCH($A5,'WP PROGRESS'!$A$2:$A$100,0))),"")) | S5: =IF($A5="","",COUNTIFS(ISSUES!$P$5:$P$200,"*"&$A5&"*",ISSUES!$H$5:$H$200,"<>Closed",ISSUES!$H$5:$H$200,"<>Resolved",ISSUES!$H$5:$H$200,"<>Cancelled",ISSUES!$H$5:$H$200,"<>",ISSUES!$A$5:$A$200,"<>")) | U5: =IF($A5="","",IFERROR(IF(INDEX('WORK PACKAGES'!$G$2:$G$100,MATCH($A5,'WORK PACKAGES'!$A$2:$A$100,0))="","",INDEX('WORK PACKAGES'!$G$2:$G$100,MATCH($A5,'WORK PACKAGES'!$A$2:$A$100,0))),""))
B6: =IF($A6="","",IFERROR(IF(INDEX('WORK PACKAGES'!$B$2:$B$100,MATCH($A6,'WORK PACKAGES'!$A$2:$A$100,0))="","",INDEX('WORK PACKAGES'!$B$2:$B$100,MATCH($A6,'WORK PACKAGES'!$A$2:$A$100,0))),"")) | C6: =IF($A6="","",IFERROR(IF(INDEX('WORK PACKAGES'!$E$2:$E$100,MATCH($A6,'WORK PACKAGES'!$A$2:$A$100,0))="","",INDEX('WORK PACKAGES'!$E$2:$E$100,MATCH($A6,'WORK PACKAGES'!$A$2:$A$100,0))),"")) | E6: =IF($A6="","",IFERROR(IF(INDEX('WP PROGRESS'!$F$2:$F$100,MATCH($A6,'WP PROGRESS'!$A$2:$A$100,0))="","",INDEX('WP PROGRESS'!$F$2:$F$100,MATCH($A6,'WP PROGRESS'!$A$2:$A$100,0))),"")) | F6: =IF($A6="","",IFERROR(IF(INDEX('WP PROGRESS'!$G$2:$G$100,MATCH($A6,'WP PROGRESS'!$A$2:$A$100,0))="","",INDEX('WP PROGRESS'!$G$2:$G$100,MATCH($A6,'WP PROGRESS'!$A$2:$A$100,0))),"")) | G6: =IF($A6="","",IFERROR(IF(INDEX('WP PROGRESS'!$H$2:$H$100,MATCH($A6,'WP PROGRESS'!$A$2:$A$100,0))="","",INDEX('WP PROGRESS'!$H$2:$H$100,MATCH($A6,'WP PROGRESS'!$A$2:$A$100,0))),"")) | H6: =IF($A6="","",IFERROR(IF(INDEX('WP PROGRESS'!$I$2:$I$100,MATCH($A6,'WP PROGRESS'!$A$2:$A$100,0))="","",INDEX('WP PROGRESS'!$I$2:$I$100,MATCH($A6,'WP PROGRESS'!$A$2:$A$100,0))),"")) | I6: =IF($A6="","",IFERROR(IF(INDEX('WP PROGRESS'!$K$2:$K$100,MATCH($A6,'WP PROGRESS'!$A$2:$A$100,0))="","",INDEX('WP PROGRESS'!$K$2:$K$100,MATCH($A6,'WP PROGRESS'!$A$2:$A$100,0))),"")) | P6: =IF($A6="","",IFERROR(IF(INDEX('WP PROGRESS'!$V$2:$V$100,MATCH($A6,'WP PROGRESS'!$A$2:$A$100,0))="","",INDEX('WP PROGRESS'!$V$2:$V$100,MATCH($A6,'WP PROGRESS'!$A$2:$A$100,0))),"")) | Q6: =IF($A6="","",IFERROR(IF(INDEX('WP PROGRESS'!$E$2:$E$100,MATCH($A6,'WP PROGRESS'!$A$2:$A$100,0))="","",INDEX('WP PROGRESS'!$E$2:$E$100,MATCH($A6,'WP PROGRESS'!$A$2:$A$100,0))),"")) | R6: =IF($A6="","",IFERROR(IF(INDEX('WP PROGRESS'!$Z$2:$Z$100,MATCH($A6,'WP PROGRESS'!$A$2:$A$100,0))="","",INDEX('WP PROGRESS'!$Z$2:$Z$100,MATCH($A6,'WP PROGRESS'!$A$2:$A$100,0))),"")) | S6: =IF($A6="","",COUNTIFS(ISSUES!$P$5:$P$200,"*"&$A6&"*",ISSUES!$H$5:$H$200,"<>Closed",ISSUES!$H$5:$H$200,"<>Resolved",ISSUES!$H$5:$H$200,"<>Cancelled",ISSUES!$H$5:$H$200,"<>",ISSUES!$A$5:$A$200,"<>")) | U6: =IF($A6="","",IFERROR(IF(INDEX('WORK PACKAGES'!$G$2:$G$100,MATCH($A6,'WORK PACKAGES'!$A$2:$A$100,0))="","",INDEX('WORK PACKAGES'!$G$2:$G$100,MATCH($A6,'WORK PACKAGES'!$A$2:$A$100,0))),""))
B7: =IF($A7="","",IFERROR(IF(INDEX('WORK PACKAGES'!$B$2:$B$100,MATCH($A7,'WORK PACKAGES'!$A$2:$A$100,0))="","",INDEX('WORK PACKAGES'!$B$2:$B$100,MATCH($A7,'WORK PACKAGES'!$A$2:$A$100,0))),"")) | C7: =IF($A7="","",IFERROR(IF(INDEX('WORK PACKAGES'!$E$2:$E$100,MATCH($A7,'WORK PACKAGES'!$A$2:$A$100,0))="","",INDEX('WORK PACKAGES'!$E$2:$E$100,MATCH($A7,'WORK PACKAGES'!$A$2:$A$100,0))),"")) | E7: =IF($A7="","",IFERROR(IF(INDEX('WP PROGRESS'!$F$2:$F$100,MATCH($A7,'WP PROGRESS'!$A$2:$A$100,0))="","",INDEX('WP PROGRESS'!$F$2:$F$100,MATCH($A7,'WP PROGRESS'!$A$2:$A$100,0))),"")) | F7: =IF($A7="","",IFERROR(IF(INDEX('WP PROGRESS'!$G$2:$G$100,MATCH($A7,'WP PROGRESS'!$A$2:$A$100,0))="","",INDEX('WP PROGRESS'!$G$2:$G$100,MATCH($A7,'WP PROGRESS'!$A$2:$A$100,0))),"")) | G7: =IF($A7="","",IFERROR(IF(INDEX('WP PROGRESS'!$H$2:$H$100,MATCH($A7,'WP PROGRESS'!$A$2:$A$100,0))="","",INDEX('WP PROGRESS'!$H$2:$H$100,MATCH($A7,'WP PROGRESS'!$A$2:$A$100,0))),"")) | H7: =IF($A7="","",IFERROR(IF(INDEX('WP PROGRESS'!$I$2:$I$100,MATCH($A7,'WP PROGRESS'!$A$2:$A$100,0))="","",INDEX('WP PROGRESS'!$I$2:$I$100,MATCH($A7,'WP PROGRESS'!$A$2:$A$100,0))),"")) | I7: =IF($A7="","",IFERROR(IF(INDEX('WP PROGRESS'!$K$2:$K$100,MATCH($A7,'WP PROGRESS'!$A$2:$A$100,0))="","",INDEX('WP PROGRESS'!$K$2:$K$100,MATCH($A7,'WP PROGRESS'!$A$2:$A$100,0))),"")) | P7: =IF($A7="","",IFERROR(IF(INDEX('WP PROGRESS'!$V$2:$V$100,MATCH($A7,'WP PROGRESS'!$A$2:$A$100,0))="","",INDEX('WP PROGRESS'!$V$2:$V$100,MATCH($A7,'WP PROGRESS'!$A$2:$A$100,0))),"")) | Q7: =IF($A7="","",IFERROR(IF(INDEX('WP PROGRESS'!$E$2:$E$100,MATCH($A7,'WP PROGRESS'!$A$2:$A$100,0))="","",INDEX('WP PROGRESS'!$E$2:$E$100,MATCH($A7,'WP PROGRESS'!$A$2:$A$100,0))),"")) | R7: =IF($A7="","",IFERROR(IF(INDEX('WP PROGRESS'!$Z$2:$Z$100,MATCH($A7,'WP PROGRESS'!$A$2:$A$100,0))="","",INDEX('WP PROGRESS'!$Z$2:$Z$100,MATCH($A7,'WP PROGRESS'!$A$2:$A$100,0))),"")) | S7: =IF($A7="","",COUNTIFS(ISSUES!$P$5:$P$200,"*"&$A7&"*",ISSUES!$H$5:$H$200,"<>Closed",ISSUES!$H$5:$H$200,"<>Resolved",ISSUES!$H$5:$H$200,"<>Cancelled",ISSUES!$H$5:$H$200,"<>",ISSUES!$A$5:$A$200,"<>")) | U7: =IF($A7="","",IFERROR(IF(INDEX('WORK PACKAGES'!$G$2:$G$100,MATCH($A7,'WORK PACKAGES'!$A$2:$A$100,0))="","",INDEX('WORK PACKAGES'!$G$2:$G$100,MATCH($A7,'WORK PACKAGES'!$A$2:$A$100,0))),""))
B8: =IF($A8="","",IFERROR(IF(INDEX('WORK PACKAGES'!$B$2:$B$100,MATCH($A8,'WORK PACKAGES'!$A$2:$A$100,0))="","",INDEX('WORK PACKAGES'!$B$2:$B$100,MATCH($A8,'WORK PACKAGES'!$A$2:$A$100,0))),"")) | C8: =IF($A8="","",IFERROR(IF(INDEX('WORK PACKAGES'!$E$2:$E$100,MATCH($A8,'WORK PACKAGES'!$A$2:$A$100,0))="","",INDEX('WORK PACKAGES'!$E$2:$E$100,MATCH($A8,'WORK PACKAGES'!$A$2:$A$100,0))),"")) | E8: =IF($A8="","",IFERROR(IF(INDEX('WP PROGRESS'!$F$2:$F$100,MATCH($A8,'WP PROGRESS'!$A$2:$A$100,0))="","",INDEX('WP PROGRESS'!$F$2:$F$100,MATCH($A8,'WP PROGRESS'!$A$2:$A$100,0))),"")) | F8: =IF($A8="","",IFERROR(IF(INDEX('WP PROGRESS'!$G$2:$G$100,MATCH($A8,'WP PROGRESS'!$A$2:$A$100,0))="","",INDEX('WP PROGRESS'!$G$2:$G$100,MATCH($A8,'WP PROGRESS'!$A$2:$A$100,0))),"")) | G8: =IF($A8="","",IFERROR(IF(INDEX('WP PROGRESS'!$H$2:$H$100,MATCH($A8,'WP PROGRESS'!$A$2:$A$100,0))="","",INDEX('WP PROGRESS'!$H$2:$H$100,MATCH($A8,'WP PROGRESS'!$A$2:$A$100,0))),"")) | H8: =IF($A8="","",IFERROR(IF(INDEX('WP PROGRESS'!$I$2:$I$100,MATCH($A8,'WP PROGRESS'!$A$2:$A$100,0))="","",INDEX('WP PROGRESS'!$I$2:$I$100,MATCH($A8,'WP PROGRESS'!$A$2:$A$100,0))),"")) | I8: =IF($A8="","",IFERROR(IF(INDEX('WP PROGRESS'!$K$2:$K$100,MATCH($A8,'WP PROGRESS'!$A$2:$A$100,0))="","",INDEX('WP PROGRESS'!$K$2:$K$100,MATCH($A8,'WP PROGRESS'!$A$2:$A$100,0))),"")) | P8: =IF($A8="","",IFERROR(IF(INDEX('WP PROGRESS'!$V$2:$V$100,MATCH($A8,'WP PROGRESS'!$A$2:$A$100,0))="","",INDEX('WP PROGRESS'!$V$2:$V$100,MATCH($A8,'WP PROGRESS'!$A$2:$A$100,0))),"")) | Q8: =IF($A8="","",IFERROR(IF(INDEX('WP PROGRESS'!$E$2:$E$100,MATCH($A8,'WP PROGRESS'!$A$2:$A$100,0))="","",INDEX('WP PROGRESS'!$E$2:$E$100,MATCH($A8,'WP PROGRESS'!$A$2:$A$100,0))),"")) | R8: =IF($A8="","",IFERROR(IF(INDEX('WP PROGRESS'!$Z$2:$Z$100,MATCH($A8,'WP PROGRESS'!$A$2:$A$100,0))="","",INDEX('WP PROGRESS'!$Z$2:$Z$100,MATCH($A8,'WP PROGRESS'!$A$2:$A$100,0))),"")) | S8: =IF($A8="","",COUNTIFS(ISSUES!$P$5:$P$200,"*"&$A8&"*",ISSUES!$H$5:$H$200,"<>Closed",ISSUES!$H$5:$H$200,"<>Resolved",ISSUES!$H$5:$H$200,"<>Cancelled",ISSUES!$H$5:$H$200,"<>",ISSUES!$A$5:$A$200,"<>")) | U8: =IF($A8="","",IFERROR(IF(INDEX('WORK PACKAGES'!$G$2:$G$100,MATCH($A8,'WORK PACKAGES'!$A$2:$A$100,0))="","",INDEX('WORK PACKAGES'!$G$2:$G$100,MATCH($A8,'WORK PACKAGES'!$A$2:$A$100,0))),""))
B9: =IF($A9="","",IFERROR(IF(INDEX('WORK PACKAGES'!$B$2:$B$100,MATCH($A9,'WORK PACKAGES'!$A$2:$A$100,0))="","",INDEX('WORK PACKAGES'!$B$2:$B$100,MATCH($A9,'WORK PACKAGES'!$A$2:$A$100,0))),"")) | C9: =IF($A9="","",IFERROR(IF(INDEX('WORK PACKAGES'!$E$2:$E$100,MATCH($A9,'WORK PACKAGES'!$A$2:$A$100,0))="","",INDEX('WORK PACKAGES'!$E$2:$E$100,MATCH($A9,'WORK PACKAGES'!$A$2:$A$100,0))),"")) | E9: =IF($A9="","",IFERROR(IF(INDEX('WP PROGRESS'!$F$2:$F$100,MATCH($A9,'WP PROGRESS'!$A$2:$A$100,0))="","",INDEX('WP PROGRESS'!$F$2:$F$100,MATCH($A9,'WP PROGRESS'!$A$2:$A$100,0))),"")) | F9: =IF($A9="","",IFERROR(IF(INDEX('WP PROGRESS'!$G$2:$G$100,MATCH($A9,'WP PROGRESS'!$A$2:$A$100,0))="","",INDEX('WP PROGRESS'!$G$2:$G$100,MATCH($A9,'WP PROGRESS'!$A$2:$A$100,0))),"")) | G9: =IF($A9="","",IFERROR(IF(INDEX('WP PROGRESS'!$H$2:$H$100,MATCH($A9,'WP PROGRESS'!$A$2:$A$100,0))="","",INDEX('WP PROGRESS'!$H$2:$H$100,MATCH($A9,'WP PROGRESS'!$A$2:$A$100,0))),"")) | H9: =IF($A9="","",IFERROR(IF(INDEX('WP PROGRESS'!$I$2:$I$100,MATCH($A9,'WP PROGRESS'!$A$2:$A$100,0))="","",INDEX('WP PROGRESS'!$I$2:$I$100,MATCH($A9,'WP PROGRESS'!$A$2:$A$100,0))),"")) | I9: =IF($A9="","",IFERROR(IF(INDEX('WP PROGRESS'!$K$2:$K$100,MATCH($A9,'WP PROGRESS'!$A$2:$A$100,0))="","",INDEX('WP PROGRESS'!$K$2:$K$100,MATCH($A9,'WP PROGRESS'!$A$2:$A$100,0))),"")) | P9: =IF($A9="","",IFERROR(IF(INDEX('WP PROGRESS'!$V$2:$V$100,MATCH($A9,'WP PROGRESS'!$A$2:$A$100,0))="","",INDEX('WP PROGRESS'!$V$2:$V$100,MATCH($A9,'WP PROGRESS'!$A$2:$A$100,0))),"")) | Q9: =IF($A9="","",IFERROR(IF(INDEX('WP PROGRESS'!$E$2:$E$100,MATCH($A9,'WP PROGRESS'!$A$2:$A$100,0))="","",INDEX('WP PROGRESS'!$E$2:$E$100,MATCH($A9,'WP PROGRESS'!$A$2:$A$100,0))),"")) | R9: =IF($A9="","",IFERROR(IF(INDEX('WP PROGRESS'!$Z$2:$Z$100,MATCH($A9,'WP PROGRESS'!$A$2:$A$100,0))="","",INDEX('WP PROGRESS'!$Z$2:$Z$100,MATCH($A9,'WP PROGRESS'!$A$2:$A$100,0))),"")) | S9: =IF($A9="","",COUNTIFS(ISSUES!$P$5:$P$200,"*"&$A9&"*",ISSUES!$H$5:$H$200,"<>Closed",ISSUES!$H$5:$H$200,"<>Resolved",ISSUES!$H$5:$H$200,"<>Cancelled",ISSUES!$H$5:$H$200,"<>",ISSUES!$A$5:$A$200,"<>")) | U9: =IF($A9="","",IFERROR(IF(INDEX('WORK PACKAGES'!$G$2:$G$100,MATCH($A9,'WORK PACKAGES'!$A$2:$A$100,0))="","",INDEX('WORK PACKAGES'!$G$2:$G$100,MATCH($A9,'WORK PACKAGES'!$A$2:$A$100,0))),""))
B10: =IF($A10="","",IFERROR(IF(INDEX('WORK PACKAGES'!$B$2:$B$100,MATCH($A10,'WORK PACKAGES'!$A$2:$A$100,0))="","",INDEX('WORK PACKAGES'!$B$2:$B$100,MATCH($A10,'WORK PACKAGES'!$A$2:$A$100,0))),"")) | C10: =IF($A10="","",IFERROR(IF(INDEX('WORK PACKAGES'!$E$2:$E$100,MATCH($A10,'WORK PACKAGES'!$A$2:$A$100,0))="","",INDEX('WORK PACKAGES'!$E$2:$E$100,MATCH($A10,'WORK PACKAGES'!$A$2:$A$100,0))),"")) | E10: =IF($A10="","",IFERROR(IF(INDEX('WP PROGRESS'!$F$2:$F$100,MATCH($A10,'WP PROGRESS'!$A$2:$A$100,0))="","",INDEX('WP PROGRESS'!$F$2:$F$100,MATCH($A10,'WP PROGRESS'!$A$2:$A$100,0))),"")) | F10: =IF($A10="","",IFERROR(IF(INDEX('WP PROGRESS'!$G$2:$G$100,MATCH($A10,'WP PROGRESS'!$A$2:$A$100,0))="","",INDEX('WP PROGRESS'!$G$2:$G$100,MATCH($A10,'WP PROGRESS'!$A$2:$A$100,0))),"")) | G10: =IF($A10="","",IFERROR(IF(INDEX('WP PROGRESS'!$H$2:$H$100,MATCH($A10,'WP PROGRESS'!$A$2:$A$100,0))="","",INDEX('WP PROGRESS'!$H$2:$H$100,MATCH($A10,'WP PROGRESS'!$A$2:$A$100,0))),"")) | H10: =IF($A10="","",IFERROR(IF(INDEX('WP PROGRESS'!$I$2:$I$100,MATCH($A10,'WP PROGRESS'!$A$2:$A$100,0))="","",INDEX('WP PROGRESS'!$I$2:$I$100,MATCH($A10,'WP PROGRESS'!$A$2:$A$100,0))),"")) | I10: =IF($A10="","",IFERROR(IF(INDEX('WP PROGRESS'!$K$2:$K$100,MATCH($A10,'WP PROGRESS'!$A$2:$A$100,0))="","",INDEX('WP PROGRESS'!$K$2:$K$100,MATCH($A10,'WP PROGRESS'!$A$2:$A$100,0))),"")) | P10: =IF($A10="","",IFERROR(IF(INDEX('WP PROGRESS'!$V$2:$V$100,MATCH($A10,'WP PROGRESS'!$A$2:$A$100,0))="","",INDEX('WP PROGRESS'!$V$2:$V$100,MATCH($A10,'WP PROGRESS'!$A$2:$A$100,0))),"")) | Q10: =IF($A10="","",IFERROR(IF(INDEX('WP PROGRESS'!$E$2:$E$100,MATCH($A10,'WP PROGRESS'!$A$2:$A$100,0))="","",INDEX('WP PROGRESS'!$E$2:$E$100,MATCH($A10,'WP PROGRESS'!$A$2:$A$100,0))),"")) | R10: =IF($A10="","",IFERROR(IF(INDEX('WP PROGRESS'!$Z$2:$Z$100,MATCH($A10,'WP PROGRESS'!$A$2:$A$100,0))="","",INDEX('WP PROGRESS'!$Z$2:$Z$100,MATCH($A10,'WP PROGRESS'!$A$2:$A$100,0))),"")) | S10: =IF($A10="","",COUNTIFS(ISSUES!$P$5:$P$200,"*"&$A10&"*",ISSUES!$H$5:$H$200,"<>Closed",ISSUES!$H$5:$H$200,"<>Resolved",ISSUES!$H$5:$H$200,"<>Cancelled",ISSUES!$H$5:$H$200,"<>",ISSUES!$A$5:$A$200,"<>")) | U10: =IF($A10="","",IFERROR(IF(INDEX('WORK PACKAGES'!$G$2:$G$100,MATCH($A10,'WORK PACKAGES'!$A$2:$A$100,0))="","",INDEX('WORK PACKAGES'!$G$2:$G$100,MATCH($A10,'WORK PACKAGES'!$A$2:$A$100,0))),""))
B11: =IF($A11="","",IFERROR(IF(INDEX('WORK PACKAGES'!$B$2:$B$100,MATCH($A11,'WORK PACKAGES'!$A$2:$A$100,0))="","",INDEX('WORK PACKAGES'!$B$2:$B$100,MATCH($A11,'WORK PACKAGES'!$A$2:$A$100,0))),"")) | C11: =IF($A11="","",IFERROR(IF(INDEX('WORK PACKAGES'!$E$2:$E$100,MATCH($A11,'WORK PACKAGES'!$A$2:$A$100,0))="","",INDEX('WORK PACKAGES'!$E$2:$E$100,MATCH($A11,'WORK PACKAGES'!$A$2:$A$100,0))),"")) | E11: =IF($A11="","",IFERROR(IF(INDEX('WP PROGRESS'!$F$2:$F$100,MATCH($A11,'WP PROGRESS'!$A$2:$A$100,0))="","",INDEX('WP PROGRESS'!$F$2:$F$100,MATCH($A11,'WP PROGRESS'!$A$2:$A$100,0))),"")) | F11: =IF($A11="","",IFERROR(IF(INDEX('WP PROGRESS'!$G$2:$G$100,MATCH($A11,'WP PROGRESS'!$A$2:$A$100,0))="","",INDEX('WP PROGRESS'!$G$2:$G$100,MATCH($A11,'WP PROGRESS'!$A$2:$A$100,0))),"")) | G11: =IF($A11="","",IFERROR(IF(INDEX('WP PROGRESS'!$H$2:$H$100,MATCH($A11,'WP PROGRESS'!$A$2:$A$100,0))="","",INDEX('WP PROGRESS'!$H$2:$H$100,MATCH($A11,'WP PROGRESS'!$A$2:$A$100,0))),"")) | H11: =IF($A11="","",IFERROR(IF(INDEX('WP PROGRESS'!$I$2:$I$100,MATCH($A11,'WP PROGRESS'!$A$2:$A$100,0))="","",INDEX('WP PROGRESS'!$I$2:$I$100,MATCH($A11,'WP PROGRESS'!$A$2:$A$100,0))),"")) | I11: =IF($A11="","",IFERROR(IF(INDEX('WP PROGRESS'!$K$2:$K$100,MATCH($A11,'WP PROGRESS'!$A$2:$A$100,0))="","",INDEX('WP PROGRESS'!$K$2:$K$100,MATCH($A11,'WP PROGRESS'!$A$2:$A$100,0))),"")) | P11: =IF($A11="","",IFERROR(IF(INDEX('WP PROGRESS'!$V$2:$V$100,MATCH($A11,'WP PROGRESS'!$A$2:$A$100,0))="","",INDEX('WP PROGRESS'!$V$2:$V$100,MATCH($A11,'WP PROGRESS'!$A$2:$A$100,0))),"")) | Q11: =IF($A11="","",IFERROR(IF(INDEX('WP PROGRESS'!$E$2:$E$100,MATCH($A11,'WP PROGRESS'!$A$2:$A$100,0))="","",INDEX('WP PROGRESS'!$E$2:$E$100,MATCH($A11,'WP PROGRESS'!$A$2:$A$100,0))),"")) | R11: =IF($A11="","",IFERROR(IF(INDEX('WP PROGRESS'!$Z$2:$Z$100,MATCH($A11,'WP PROGRESS'!$A$2:$A$100,0))="","",INDEX('WP PROGRESS'!$Z$2:$Z$100,MATCH($A11,'WP PROGRESS'!$A$2:$A$100,0))),"")) | S11: =IF($A11="","",COUNTIFS(ISSUES!$P$5:$P$200,"*"&$A11&"*",ISSUES!$H$5:$H$200,"<>Closed",ISSUES!$H$5:$H$200,"<>Resolved",ISSUES!$H$5:$H$200,"<>Cancelled",ISSUES!$H$5:$H$200,"<>",ISSUES!$A$5:$A$200,"<>")) | U11: =IF($A11="","",IFERROR(IF(INDEX('WORK PACKAGES'!$G$2:$G$100,MATCH($A11,'WORK PACKAGES'!$A$2:$A$100,0))="","",INDEX('WORK PACKAGES'!$G$2:$G$100,MATCH($A11,'WORK PACKAGES'!$A$2:$A$100,0))),""))
B12: =IF($A12="","",IFERROR(IF(INDEX('WORK PACKAGES'!$B$2:$B$100,MATCH($A12,'WORK PACKAGES'!$A$2:$A$100,0))="","",INDEX('WORK PACKAGES'!$B$2:$B$100,MATCH($A12,'WORK PACKAGES'!$A$2:$A$100,0))),"")) | C12: =IF($A12="","",IFERROR(IF(INDEX('WORK PACKAGES'!$E$2:$E$100,MATCH($A12,'WORK PACKAGES'!$A$2:$A$100,0))="","",INDEX('WORK PACKAGES'!$E$2:$E$100,MATCH($A12,'WORK PACKAGES'!$A$2:$A$100,0))),"")) | E12: =IF($A12="","",IFERROR(IF(INDEX('WP PROGRESS'!$F$2:$F$100,MATCH($A12,'WP PROGRESS'!$A$2:$A$100,0))="","",INDEX('WP PROGRESS'!$F$2:$F$100,MATCH($A12,'WP PROGRESS'!$A$2:$A$100,0))),"")) | F12: =IF($A12="","",IFERROR(IF(INDEX('WP PROGRESS'!$G$2:$G$100,MATCH($A12,'WP PROGRESS'!$A$2:$A$100,0))="","",INDEX('WP PROGRESS'!$G$2:$G$100,MATCH($A12,'WP PROGRESS'!$A$2:$A$100,0))),"")) | G12: =IF($A12="","",IFERROR(IF(INDEX('WP PROGRESS'!$H$2:$H$100,MATCH($A12,'WP PROGRESS'!$A$2:$A$100,0))="","",INDEX('WP PROGRESS'!$H$2:$H$100,MATCH($A12,'WP PROGRESS'!$A$2:$A$100,0))),"")) | H12: =IF($A12="","",IFERROR(IF(INDEX('WP PROGRESS'!$I$2:$I$100,MATCH($A12,'WP PROGRESS'!$A$2:$A$100,0))="","",INDEX('WP PROGRESS'!$I$2:$I$100,MATCH($A12,'WP PROGRESS'!$A$2:$A$100,0))),"")) | I12: =IF($A12="","",IFERROR(IF(INDEX('WP PROGRESS'!$K$2:$K$100,MATCH($A12,'WP PROGRESS'!$A$2:$A$100,0))="","",INDEX('WP PROGRESS'!$K$2:$K$100,MATCH($A12,'WP PROGRESS'!$A$2:$A$100,0))),"")) | P12: =IF($A12="","",IFERROR(IF(INDEX('WP PROGRESS'!$V$2:$V$100,MATCH($A12,'WP PROGRESS'!$A$2:$A$100,0))="","",INDEX('WP PROGRESS'!$V$2:$V$100,MATCH($A12,'WP PROGRESS'!$A$2:$A$100,0))),"")) | Q12: =IF($A12="","",IFERROR(IF(INDEX('WP PROGRESS'!$E$2:$E$100,MATCH($A12,'WP PROGRESS'!$A$2:$A$100,0))="","",INDEX('WP PROGRESS'!$E$2:$E$100,MATCH($A12,'WP PROGRESS'!$A$2:$A$100,0))),"")) | R12: =IF($A12="","",IFERROR(IF(INDEX('WP PROGRESS'!$Z$2:$Z$100,MATCH($A12,'WP PROGRESS'!$A$2:$A$100,0))="","",INDEX('WP PROGRESS'!$Z$2:$Z$100,MATCH($A12,'WP PROGRESS'!$A$2:$A$100,0))),"")) | S12: =IF($A12="","",COUNTIFS(ISSUES!$P$5:$P$200,"*"&$A12&"*",ISSUES!$H$5:$H$200,"<>Closed",ISSUES!$H$5:$H$200,"<>Resolved",ISSUES!$H$5:$H$200,"<>Cancelled",ISSUES!$H$5:$H$200,"<>",ISSUES!$A$5:$A$200,"<>")) | U12: =IF($A12="","",IFERROR(IF(INDEX('WORK PACKAGES'!$G$2:$G$100,MATCH($A12,'WORK PACKAGES'!$A$2:$A$100,0))="","",INDEX('WORK PACKAGES'!$G$2:$G$100,MATCH($A12,'WORK PACKAGES'!$A$2:$A$100,0))),""))
B13: =IF($A13="","",IFERROR(IF(INDEX('WORK PACKAGES'!$B$2:$B$100,MATCH($A13,'WORK PACKAGES'!$A$2:$A$100,0))="","",INDEX('WORK PACKAGES'!$B$2:$B$100,MATCH($A13,'WORK PACKAGES'!$A$2:$A$100,0))),"")) | C13: =IF($A13="","",IFERROR(IF(INDEX('WORK PACKAGES'!$E$2:$E$100,MATCH($A13,'WORK PACKAGES'!$A$2:$A$100,0))="","",INDEX('WORK PACKAGES'!$E$2:$E$100,MATCH($A13,'WORK PACKAGES'!$A$2:$A$100,0))),"")) | E13: =IF($A13="","",IFERROR(IF(INDEX('WP PROGRESS'!$F$2:$F$100,MATCH($A13,'WP PROGRESS'!$A$2:$A$100,0))="","",INDEX('WP PROGRESS'!$F$2:$F$100,MATCH($A13,'WP PROGRESS'!$A$2:$A$100,0))),"")) | F13: =IF($A13="","",IFERROR(IF(INDEX('WP PROGRESS'!$G$2:$G$100,MATCH($A13,'WP PROGRESS'!$A$2:$A$100,0))="","",INDEX('WP PROGRESS'!$G$2:$G$100,MATCH($A13,'WP PROGRESS'!$A$2:$A$100,0))),"")) | G13: =IF($A13="","",IFERROR(IF(INDEX('WP PROGRESS'!$H$2:$H$100,MATCH($A13,'WP PROGRESS'!$A$2:$A$100,0))="","",INDEX('WP PROGRESS'!$H$2:$H$100,MATCH($A13,'WP PROGRESS'!$A$2:$A$100,0))),"")) | H13: =IF($A13="","",IFERROR(IF(INDEX('WP PROGRESS'!$I$2:$I$100,MATCH($A13,'WP PROGRESS'!$A$2:$A$100,0))="","",INDEX('WP PROGRESS'!$I$2:$I$100,MATCH($A13,'WP PROGRESS'!$A$2:$A$100,0))),"")) | I13: =IF($A13="","",IFERROR(IF(INDEX('WP PROGRESS'!$K$2:$K$100,MATCH($A13,'WP PROGRESS'!$A$2:$A$100,0))="","",INDEX('WP PROGRESS'!$K$2:$K$100,MATCH($A13,'WP PROGRESS'!$A$2:$A$100,0))),"")) | P13: =IF($A13="","",IFERROR(IF(INDEX('WP PROGRESS'!$V$2:$V$100,MATCH($A13,'WP PROGRESS'!$A$2:$A$100,0))="","",INDEX('WP PROGRESS'!$V$2:$V$100,MATCH($A13,'WP PROGRESS'!$A$2:$A$100,0))),"")) | Q13: =IF($A13="","",IFERROR(IF(INDEX('WP PROGRESS'!$E$2:$E$100,MATCH($A13,'WP PROGRESS'!$A$2:$A$100,0))="","",INDEX('WP PROGRESS'!$E$2:$E$100,MATCH($A13,'WP PROGRESS'!$A$2:$A$100,0))),"")) | R13: =IF($A13="","",IFERROR(IF(INDEX('WP PROGRESS'!$Z$2:$Z$100,MATCH($A13,'WP PROGRESS'!$A$2:$A$100,0))="","",INDEX('WP PROGRESS'!$Z$2:$Z$100,MATCH($A13,'WP PROGRESS'!$A$2:$A$100,0))),"")) | S13: =IF($A13="","",COUNTIFS(ISSUES!$P$5:$P$200,"*"&$A13&"*",ISSUES!$H$5:$H$200,"<>Closed",ISSUES!$H$5:$H$200,"<>Resolved",ISSUES!$H$5:$H$200,"<>Cancelled",ISSUES!$H$5:$H$200,"<>",ISSUES!$A$5:$A$200,"<>")) | U13: =IF($A13="","",IFERROR(IF(INDEX('WORK PACKAGES'!$G$2:$G$100,MATCH($A13,'WORK PACKAGES'!$A$2:$A$100,0))="","",INDEX('WORK PACKAGES'!$G$2:$G$100,MATCH($A13,'WORK PACKAGES'!$A$2:$A$100,0))),""))
B14: =IF($A14="","",IFERROR(IF(INDEX('WORK PACKAGES'!$B$2:$B$100,MATCH($A14,'WORK PACKAGES'!$A$2:$A$100,0))="","",INDEX('WORK PACKAGES'!$B$2:$B$100,MATCH($A14,'WORK PACKAGES'!$A$2:$A$100,0))),"")) | C14: =IF($A14="","",IFERROR(IF(INDEX('WORK PACKAGES'!$E$2:$E$100,MATCH($A14,'WORK PACKAGES'!$A$2:$A$100,0))="","",INDEX('WORK PACKAGES'!$E$2:$E$100,MATCH($A14,'WORK PACKAGES'!$A$2:$A$100,0))),"")) | E14: =IF($A14="","",IFERROR(IF(INDEX('WP PROGRESS'!$F$2:$F$100,MATCH($A14,'WP PROGRESS'!$A$2:$A$100,0))="","",INDEX('WP PROGRESS'!$F$2:$F$100,MATCH($A14,'WP PROGRESS'!$A$2:$A$100,0))),"")) | F14: =IF($A14="","",IFERROR(IF(INDEX('WP PROGRESS'!$G$2:$G$100,MATCH($A14,'WP PROGRESS'!$A$2:$A$100,0))="","",INDEX('WP PROGRESS'!$G$2:$G$100,MATCH($A14,'WP PROGRESS'!$A$2:$A$100,0))),"")) | G14: =IF($A14="","",IFERROR(IF(INDEX('WP PROGRESS'!$H$2:$H$100,MATCH($A14,'WP PROGRESS'!$A$2:$A$100,0))="","",INDEX('WP PROGRESS'!$H$2:$H$100,MATCH($A14,'WP PROGRESS'!$A$2:$A$100,0))),"")) | H14: =IF($A14="","",IFERROR(IF(INDEX('WP PROGRESS'!$I$2:$I$100,MATCH($A14,'WP PROGRESS'!$A$2:$A$100,0))="","",INDEX('WP PROGRESS'!$I$2:$I$100,MATCH($A14,'WP PROGRESS'!$A$2:$A$100,0))),"")) | I14: =IF($A14="","",IFERROR(IF(INDEX('WP PROGRESS'!$K$2:$K$100,MATCH($A14,'WP PROGRESS'!$A$2:$A$100,0))="","",INDEX('WP PROGRESS'!$K$2:$K$100,MATCH($A14,'WP PROGRESS'!$A$2:$A$100,0))),"")) | P14: =IF($A14="","",IFERROR(IF(INDEX('WP PROGRESS'!$V$2:$V$100,MATCH($A14,'WP PROGRESS'!$A$2:$A$100,0))="","",INDEX('WP PROGRESS'!$V$2:$V$100,MATCH($A14,'WP PROGRESS'!$A$2:$A$100,0))),"")) | Q14: =IF($A14="","",IFERROR(IF(INDEX('WP PROGRESS'!$E$2:$E$100,MATCH($A14,'WP PROGRESS'!$A$2:$A$100,0))="","",INDEX('WP PROGRESS'!$E$2:$E$100,MATCH($A14,'WP PROGRESS'!$A$2:$A$100,0))),"")) | R14: =IF($A14="","",IFERROR(IF(INDEX('WP PROGRESS'!$Z$2:$Z$100,MATCH($A14,'WP PROGRESS'!$A$2:$A$100,0))="","",INDEX('WP PROGRESS'!$Z$2:$Z$100,MATCH($A14,'WP PROGRESS'!$A$2:$A$100,0))),"")) | S14: =IF($A14="","",COUNTIFS(ISSUES!$P$5:$P$200,"*"&$A14&"*",ISSUES!$H$5:$H$200,"<>Closed",ISSUES!$H$5:$H$200,"<>Resolved",ISSUES!$H$5:$H$200,"<>Cancelled",ISSUES!$H$5:$H$200,"<>",ISSUES!$A$5:$A$200,"<>")) | U14: =IF($A14="","",IFERROR(IF(INDEX('WORK PACKAGES'!$G$2:$G$100,MATCH($A14,'WORK PACKAGES'!$A$2:$A$100,0))="","",INDEX('WORK PACKAGES'!$G$2:$G$100,MATCH($A14,'WORK PACKAGES'!$A$2:$A$100,0))),""))
... B51: =IF($A51="","",IFERROR(IF(INDEX('WORK PACKAGES'!$B$2:$B$100,MATCH($A51,'WORK PACKAGES'!$A$2:$A$100,0))="","",INDEX('WORK PACKAGES'!$B$2:$B$100,MATCH($A51,'WORK PACKAGES'!$A$2:$A$100,0))),"")) | C51: =IF($A51="","",IFERROR(IF(INDEX('WORK PACKAGES'!$E$2:$E$100,MATCH($A51,'WORK PACKAGES'!$A$2:$A$100,0))="","",INDEX('WORK PACKAGES'!$E$2:$E$100,MATCH($A51,'WORK PACKAGES'!$A$2:$A$100,0))),"")) | E51: =IF($A51="","",IFERROR(IF(INDEX('WP PROGRESS'!$F$2:$F$100,MATCH($A51,'WP PROGRESS'!$A$2:$A$100,0))="","",INDEX('WP PROGRESS'!$F$2:$F$100,MATCH($A51,'WP PROGRESS'!$A$2:$A$100,0))),"")) | F51: =IF($A51="","",IFERROR(IF(INDEX('WP PROGRESS'!$G$2:$G$100,MATCH($A51,'WP PROGRESS'!$A$2:$A$100,0))="","",INDEX('WP PROGRESS'!$G$2:$G$100,MATCH($A51,'WP PROGRESS'!$A$2:$A$100,0))),"")) | G51: =IF($A51="","",IFERROR(IF(INDEX('WP PROGRESS'!$H$2:$H$100,MATCH($A51,'WP PROGRESS'!$A$2:$A$100,0))="","",INDEX('WP PROGRESS'!$H$2:$H$100,MATCH($A51,'WP PROGRESS'!$A$2:$A$100,0))),"")) | H51: =IF($A51="","",IFERROR(IF(INDEX('WP PROGRESS'!$I$2:$I$100,MATCH($A51,'WP PROGRESS'!$A$2:$A$100,0))="","",INDEX('WP PROGRESS'!$I$2:$I$100,MATCH($A51,'WP PROGRESS'!$A$2:$A$100,0))),"")) | I51: =IF($A51="","",IFERROR(IF(INDEX('WP PROGRESS'!$K$2:$K$100,MATCH($A51,'WP PROGRESS'!$A$2:$A$100,0))="","",INDEX('WP PROGRESS'!$K$2:$K$100,MATCH($A51,'WP PROGRESS'!$A$2:$A$100,0))),"")) | P51: =IF($A51="","",IFERROR(IF(INDEX('WP PROGRESS'!$V$2:$V$100,MATCH($A51,'WP PROGRESS'!$A$2:$A$100,0))="","",INDEX('WP PROGRESS'!$V$2:$V$100,MATCH($A51,'WP PROGRESS'!$A$2:$A$100,0))),"")) | Q51: =IF($A51="","",IFERROR(IF(INDEX('WP PROGRESS'!$E$2:$E$100,MATCH($A51,'WP PROGRESS'!$A$2:$A$100,0))="","",INDEX('WP PROGRESS'!$E$2:$E$100,MATCH($A51,'WP PROGRESS'!$A$2:$A$100,0))),"")) | R51: =IF($A51="","",IFERROR(IF(INDEX('WP PROGRESS'!$Z$2:$Z$100,MATCH($A51,'WP PROGRESS'!$A$2:$A$100,0))="","",INDEX('WP PROGRESS'!$Z$2:$Z$100,MATCH($A51,'WP PROGRESS'!$A$2:$A$100,0))),"")) | S51: =IF($A51="","",COUNTIFS(ISSUES!$P$5:$P$200,"*"&$A51&"*",ISSUES!$H$5:$H$200,"<>Closed",ISSUES!$H$5:$H$200,"<>Resolved",ISSUES!$H$5:$H$200,"<>Cancelled",ISSUES!$H$5:$H$200,"<>",ISSUES!$A$5:$A$200,"<>")) | U51: =IF($A51="","",IFERROR(IF(INDEX('WORK PACKAGES'!$G$2:$G$100,MATCH($A51,'WORK PACKAGES'!$A$2:$A$100,0))="","",INDEX('WORK PACKAGES'!$G$2:$G$100,MATCH($A51,'WORK PACKAGES'!$A$2:$A$100,0))),""))

Sheet SCOPE DASHBOARD
A1: SCOPE DASHBOARD | ENGINEERING REVIEW
A2: Scope rows are manually identified by Scope ID. Values below are calculated; blocking X is human-managed. No automatic flag propagation.
A3: Scope progress (H:M) is derived from WP PROGRESS: average of each column over work packages whose Primary Scope is this scope, each WP weighted equally. Blank and '--' are left out; enter 0 for 'in use, not started'. Blocked? (X) stays human-managed; 'Blocked WPs' is information only.
A4: Scope ID | B4: Engineering Scope | C4: WP Count | D4: Open Issues | E4: Open RFIs | F4: Blocked? (X) | G4: Engineering State | H4: Eng % | I4: Prog % | J4: Cond & Wire % | K4: Device % | L4: Loop Check % | M4: PreComm % | N4: WPs Gate Complete | O4: Blocked WPs (count)
B5: =IF($A5="","",IFERROR(INDEX(SCOPES!$B$5:$B$200,MATCH($A5,SCOPES!$A$5:$A$200,0)),"")) | C5: =IF($A5="","",COUNTIF('WORK PACKAGES'!$G$2:$G$100,$A5)) | D5: =IF($A5="","",COUNTIFS(ISSUES!$O$5:$O$200,$A5,ISSUES!$H$5:$H$200,"<>Closed",ISSUES!$H$5:$H$200,"<>Resolved",ISSUES!$H$5:$H$200,"<>Cancelled",ISSUES!$H$5:$H$200,"<>",ISSUES!$A$5:$A$200,"<>")) | E5: =IF($A5="","",COUNTIFS('RFI REGISTER'!$F$5:$F$250,"*"&$A5&"*",'RFI REGISTER'!$C$5:$C$250,"<>Closed",'RFI REGISTER'!$C$5:$C$250,"<>Cancelled",'RFI REGISTER'!$C$5:$C$250,"<>",'RFI REGISTER'!$A$5:$A$250,"<>")) | G5: =IF($A5="","",IFERROR(INDEX(SCOPES!$K$5:$K$200,MATCH($A5,SCOPES!$A$5:$A$200,0)),"")) | H5: =IF($A5="","",IFERROR(AVERAGEIFS('WP PROGRESS'!$F$2:$F$100,'WP PROGRESS'!$C$2:$C$100,$A5),"")) | I5: =IF($A5="","",IFERROR(AVERAGEIFS('WP PROGRESS'!$G$2:$G$100,'WP PROGRESS'!$C$2:$C$100,$A5),"")) | J5: =IF($A5="","",IFERROR(AVERAGEIFS('WP PROGRESS'!$H$2:$H$100,'WP PROGRESS'!$C$2:$C$100,$A5),"")) | K5: =IF($A5="","",IFERROR(AVERAGEIFS('WP PROGRESS'!$I$2:$I$100,'WP PROGRESS'!$C$2:$C$100,$A5),"")) | L5: =IF($A5="","",IFERROR(AVERAGEIFS('WP PROGRESS'!$J$2:$J$100,'WP PROGRESS'!$C$2:$C$100,$A5),"")) | M5: =IF($A5="","",IFERROR(AVERAGEIFS('WP PROGRESS'!$K$2:$K$100,'WP PROGRESS'!$C$2:$C$100,$A5),"")) | N5: =IF(OR($A5="",C5=0),"",COUNTIFS('WP PROGRESS'!$C$2:$C$100,$A5,'WP PROGRESS'!$V$2:$V$100,"Yes")+COUNTIFS('WP PROGRESS'!$C$2:$C$100,$A5,'WP PROGRESS'!$V$2:$V$100,"--")&" of "&C5) | O5: =IF($A5="","",COUNTIFS('WP PROGRESS'!$C$2:$C$100,$A5,'WP PROGRESS'!$Y$2:$Y$100,"X"))
B6: =IF($A6="","",IFERROR(INDEX(SCOPES!$B$5:$B$200,MATCH($A6,SCOPES!$A$5:$A$200,0)),"")) | C6: =IF($A6="","",COUNTIF('WORK PACKAGES'!$G$2:$G$100,$A6)) | D6: =IF($A6="","",COUNTIFS(ISSUES!$O$5:$O$200,$A6,ISSUES!$H$5:$H$200,"<>Closed",ISSUES!$H$5:$H$200,"<>Resolved",ISSUES!$H$5:$H$200,"<>Cancelled",ISSUES!$H$5:$H$200,"<>",ISSUES!$A$5:$A$200,"<>")) | E6: =IF($A6="","",COUNTIFS('RFI REGISTER'!$F$5:$F$250,"*"&$A6&"*",'RFI REGISTER'!$C$5:$C$250,"<>Closed",'RFI REGISTER'!$C$5:$C$250,"<>Cancelled",'RFI REGISTER'!$C$5:$C$250,"<>",'RFI REGISTER'!$A$5:$A$250,"<>")) | G6: =IF($A6="","",IFERROR(INDEX(SCOPES!$K$5:$K$200,MATCH($A6,SCOPES!$A$5:$A$200,0)),"")) | H6: =IF($A6="","",IFERROR(AVERAGEIFS('WP PROGRESS'!$F$2:$F$100,'WP PROGRESS'!$C$2:$C$100,$A6),"")) | I6: =IF($A6="","",IFERROR(AVERAGEIFS('WP PROGRESS'!$G$2:$G$100,'WP PROGRESS'!$C$2:$C$100,$A6),"")) | J6: =IF($A6="","",IFERROR(AVERAGEIFS('WP PROGRESS'!$H$2:$H$100,'WP PROGRESS'!$C$2:$C$100,$A6),"")) | K6: =IF($A6="","",IFERROR(AVERAGEIFS('WP PROGRESS'!$I$2:$I$100,'WP PROGRESS'!$C$2:$C$100,$A6),"")) | L6: =IF($A6="","",IFERROR(AVERAGEIFS('WP PROGRESS'!$J$2:$J$100,'WP PROGRESS'!$C$2:$C$100,$A6),"")) | M6: =IF($A6="","",IFERROR(AVERAGEIFS('WP PROGRESS'!$K$2:$K$100,'WP PROGRESS'!$C$2:$C$100,$A6),"")) | N6: =IF(OR($A6="",C6=0),"",COUNTIFS('WP PROGRESS'!$C$2:$C$100,$A6,'WP PROGRESS'!$V$2:$V$100,"Yes")+COUNTIFS('WP PROGRESS'!$C$2:$C$100,$A6,'WP PROGRESS'!$V$2:$V$100,"--")&" of "&C6) | O6: =IF($A6="","",COUNTIFS('WP PROGRESS'!$C$2:$C$100,$A6,'WP PROGRESS'!$Y$2:$Y$100,"X"))
B7: =IF($A7="","",IFERROR(INDEX(SCOPES!$B$5:$B$200,MATCH($A7,SCOPES!$A$5:$A$200,0)),"")) | C7: =IF($A7="","",COUNTIF('WORK PACKAGES'!$G$2:$G$100,$A7)) | D7: =IF($A7="","",COUNTIFS(ISSUES!$O$5:$O$200,$A7,ISSUES!$H$5:$H$200,"<>Closed",ISSUES!$H$5:$H$200,"<>Resolved",ISSUES!$H$5:$H$200,"<>Cancelled",ISSUES!$H$5:$H$200,"<>",ISSUES!$A$5:$A$200,"<>")) | E7: =IF($A7="","",COUNTIFS('RFI REGISTER'!$F$5:$F$250,"*"&$A7&"*",'RFI REGISTER'!$C$5:$C$250,"<>Closed",'RFI REGISTER'!$C$5:$C$250,"<>Cancelled",'RFI REGISTER'!$C$5:$C$250,"<>",'RFI REGISTER'!$A$5:$A$250,"<>")) | G7: =IF($A7="","",IFERROR(INDEX(SCOPES!$K$5:$K$200,MATCH($A7,SCOPES!$A$5:$A$200,0)),"")) | H7: =IF($A7="","",IFERROR(AVERAGEIFS('WP PROGRESS'!$F$2:$F$100,'WP PROGRESS'!$C$2:$C$100,$A7),"")) | I7: =IF($A7="","",IFERROR(AVERAGEIFS('WP PROGRESS'!$G$2:$G$100,'WP PROGRESS'!$C$2:$C$100,$A7),"")) | J7: =IF($A7="","",IFERROR(AVERAGEIFS('WP PROGRESS'!$H$2:$H$100,'WP PROGRESS'!$C$2:$C$100,$A7),"")) | K7: =IF($A7="","",IFERROR(AVERAGEIFS('WP PROGRESS'!$I$2:$I$100,'WP PROGRESS'!$C$2:$C$100,$A7),"")) | L7: =IF($A7="","",IFERROR(AVERAGEIFS('WP PROGRESS'!$J$2:$J$100,'WP PROGRESS'!$C$2:$C$100,$A7),"")) | M7: =IF($A7="","",IFERROR(AVERAGEIFS('WP PROGRESS'!$K$2:$K$100,'WP PROGRESS'!$C$2:$C$100,$A7),"")) | N7: =IF(OR($A7="",C7=0),"",COUNTIFS('WP PROGRESS'!$C$2:$C$100,$A7,'WP PROGRESS'!$V$2:$V$100,"Yes")+COUNTIFS('WP PROGRESS'!$C$2:$C$100,$A7,'WP PROGRESS'!$V$2:$V$100,"--")&" of "&C7) | O7: =IF($A7="","",COUNTIFS('WP PROGRESS'!$C$2:$C$100,$A7,'WP PROGRESS'!$Y$2:$Y$100,"X"))
B8: =IF($A8="","",IFERROR(INDEX(SCOPES!$B$5:$B$200,MATCH($A8,SCOPES!$A$5:$A$200,0)),"")) | C8: =IF($A8="","",COUNTIF('WORK PACKAGES'!$G$2:$G$100,$A8)) | D8: =IF($A8="","",COUNTIFS(ISSUES!$O$5:$O$200,$A8,ISSUES!$H$5:$H$200,"<>Closed",ISSUES!$H$5:$H$200,"<>Resolved",ISSUES!$H$5:$H$200,"<>Cancelled",ISSUES!$H$5:$H$200,"<>",ISSUES!$A$5:$A$200,"<>")) | E8: =IF($A8="","",COUNTIFS('RFI REGISTER'!$F$5:$F$250,"*"&$A8&"*",'RFI REGISTER'!$C$5:$C$250,"<>Closed",'RFI REGISTER'!$C$5:$C$250,"<>Cancelled",'RFI REGISTER'!$C$5:$C$250,"<>",'RFI REGISTER'!$A$5:$A$250,"<>")) | G8: =IF($A8="","",IFERROR(INDEX(SCOPES!$K$5:$K$200,MATCH($A8,SCOPES!$A$5:$A$200,0)),"")) | H8: =IF($A8="","",IFERROR(AVERAGEIFS('WP PROGRESS'!$F$2:$F$100,'WP PROGRESS'!$C$2:$C$100,$A8),"")) | I8: =IF($A8="","",IFERROR(AVERAGEIFS('WP PROGRESS'!$G$2:$G$100,'WP PROGRESS'!$C$2:$C$100,$A8),"")) | J8: =IF($A8="","",IFERROR(AVERAGEIFS('WP PROGRESS'!$H$2:$H$100,'WP PROGRESS'!$C$2:$C$100,$A8),"")) | K8: =IF($A8="","",IFERROR(AVERAGEIFS('WP PROGRESS'!$I$2:$I$100,'WP PROGRESS'!$C$2:$C$100,$A8),"")) | L8: =IF($A8="","",IFERROR(AVERAGEIFS('WP PROGRESS'!$J$2:$J$100,'WP PROGRESS'!$C$2:$C$100,$A8),"")) | M8: =IF($A8="","",IFERROR(AVERAGEIFS('WP PROGRESS'!$K$2:$K$100,'WP PROGRESS'!$C$2:$C$100,$A8),"")) | N8: =IF(OR($A8="",C8=0),"",COUNTIFS('WP PROGRESS'!$C$2:$C$100,$A8,'WP PROGRESS'!$V$2:$V$100,"Yes")+COUNTIFS('WP PROGRESS'!$C$2:$C$100,$A8,'WP PROGRESS'!$V$2:$V$100,"--")&" of "&C8) | O8: =IF($A8="","",COUNTIFS('WP PROGRESS'!$C$2:$C$100,$A8,'WP PROGRESS'!$Y$2:$Y$100,"X"))
B9: =IF($A9="","",IFERROR(INDEX(SCOPES!$B$5:$B$200,MATCH($A9,SCOPES!$A$5:$A$200,0)),"")) | C9: =IF($A9="","",COUNTIF('WORK PACKAGES'!$G$2:$G$100,$A9)) | D9: =IF($A9="","",COUNTIFS(ISSUES!$O$5:$O$200,$A9,ISSUES!$H$5:$H$200,"<>Closed",ISSUES!$H$5:$H$200,"<>Resolved",ISSUES!$H$5:$H$200,"<>Cancelled",ISSUES!$H$5:$H$200,"<>",ISSUES!$A$5:$A$200,"<>")) | E9: =IF($A9="","",COUNTIFS('RFI REGISTER'!$F$5:$F$250,"*"&$A9&"*",'RFI REGISTER'!$C$5:$C$250,"<>Closed",'RFI REGISTER'!$C$5:$C$250,"<>Cancelled",'RFI REGISTER'!$C$5:$C$250,"<>",'RFI REGISTER'!$A$5:$A$250,"<>")) | G9: =IF($A9="","",IFERROR(INDEX(SCOPES!$K$5:$K$200,MATCH($A9,SCOPES!$A$5:$A$200,0)),"")) | H9: =IF($A9="","",IFERROR(AVERAGEIFS('WP PROGRESS'!$F$2:$F$100,'WP PROGRESS'!$C$2:$C$100,$A9),"")) | I9: =IF($A9="","",IFERROR(AVERAGEIFS('WP PROGRESS'!$G$2:$G$100,'WP PROGRESS'!$C$2:$C$100,$A9),"")) | J9: =IF($A9="","",IFERROR(AVERAGEIFS('WP PROGRESS'!$H$2:$H$100,'WP PROGRESS'!$C$2:$C$100,$A9),"")) | K9: =IF($A9="","",IFERROR(AVERAGEIFS('WP PROGRESS'!$I$2:$I$100,'WP PROGRESS'!$C$2:$C$100,$A9),"")) | L9: =IF($A9="","",IFERROR(AVERAGEIFS('WP PROGRESS'!$J$2:$J$100,'WP PROGRESS'!$C$2:$C$100,$A9),"")) | M9: =IF($A9="","",IFERROR(AVERAGEIFS('WP PROGRESS'!$K$2:$K$100,'WP PROGRESS'!$C$2:$C$100,$A9),"")) | N9: =IF(OR($A9="",C9=0),"",COUNTIFS('WP PROGRESS'!$C$2:$C$100,$A9,'WP PROGRESS'!$V$2:$V$100,"Yes")+COUNTIFS('WP PROGRESS'!$C$2:$C$100,$A9,'WP PROGRESS'!$V$2:$V$100,"--")&" of "&C9) | O9: =IF($A9="","",COUNTIFS('WP PROGRESS'!$C$2:$C$100,$A9,'WP PROGRESS'!$Y$2:$Y$100,"X"))
B10: =IF($A10="","",IFERROR(INDEX(SCOPES!$B$5:$B$200,MATCH($A10,SCOPES!$A$5:$A$200,0)),"")) | C10: =IF($A10="","",COUNTIF('WORK PACKAGES'!$G$2:$G$100,$A10)) | D10: =IF($A10="","",COUNTIFS(ISSUES!$O$5:$O$200,$A10,ISSUES!$H$5:$H$200,"<>Closed",ISSUES!$H$5:$H$200,"<>Resolved",ISSUES!$H$5:$H$200,"<>Cancelled",ISSUES!$H$5:$H$200,"<>",ISSUES!$A$5:$A$200,"<>")) | E10: =IF($A10="","",COUNTIFS('RFI REGISTER'!$F$5:$F$250,"*"&$A10&"*",'RFI REGISTER'!$C$5:$C$250,"<>Closed",'RFI REGISTER'!$C$5:$C$250,"<>Cancelled",'RFI REGISTER'!$C$5:$C$250,"<>",'RFI REGISTER'!$A$5:$A$250,"<>")) | G10: =IF($A10="","",IFERROR(INDEX(SCOPES!$K$5:$K$200,MATCH($A10,SCOPES!$A$5:$A$200,0)),"")) | H10: =IF($A10="","",IFERROR(AVERAGEIFS('WP PROGRESS'!$F$2:$F$100,'WP PROGRESS'!$C$2:$C$100,$A10),"")) | I10: =IF($A10="","",IFERROR(AVERAGEIFS('WP PROGRESS'!$G$2:$G$100,'WP PROGRESS'!$C$2:$C$100,$A10),"")) | J10: =IF($A10="","",IFERROR(AVERAGEIFS('WP PROGRESS'!$H$2:$H$100,'WP PROGRESS'!$C$2:$C$100,$A10),"")) | K10: =IF($A10="","",IFERROR(AVERAGEIFS('WP PROGRESS'!$I$2:$I$100,'WP PROGRESS'!$C$2:$C$100,$A10),"")) | L10: =IF($A10="","",IFERROR(AVERAGEIFS('WP PROGRESS'!$J$2:$J$100,'WP PROGRESS'!$C$2:$C$100,$A10),"")) | M10: =IF($A10="","",IFERROR(AVERAGEIFS('WP PROGRESS'!$K$2:$K$100,'WP PROGRESS'!$C$2:$C$100,$A10),"")) | N10: =IF(OR($A10="",C10=0),"",COUNTIFS('WP PROGRESS'!$C$2:$C$100,$A10,'WP PROGRESS'!$V$2:$V$100,"Yes")+COUNTIFS('WP PROGRESS'!$C$2:$C$100,$A10,'WP PROGRESS'!$V$2:$V$100,"--")&" of "&C10) | O10: =IF($A10="","",COUNTIFS('WP PROGRESS'!$C$2:$C$100,$A10,'WP PROGRESS'!$Y$2:$Y$100,"X"))
B11: =IF($A11="","",IFERROR(INDEX(SCOPES!$B$5:$B$200,MATCH($A11,SCOPES!$A$5:$A$200,0)),"")) | C11: =IF($A11="","",COUNTIF('WORK PACKAGES'!$G$2:$G$100,$A11)) | D11: =IF($A11="","",COUNTIFS(ISSUES!$O$5:$O$200,$A11,ISSUES!$H$5:$H$200,"<>Closed",ISSUES!$H$5:$H$200,"<>Resolved",ISSUES!$H$5:$H$200,"<>Cancelled",ISSUES!$H$5:$H$200,"<>",ISSUES!$A$5:$A$200,"<>")) | E11: =IF($A11="","",COUNTIFS('RFI REGISTER'!$F$5:$F$250,"*"&$A11&"*",'RFI REGISTER'!$C$5:$C$250,"<>Closed",'RFI REGISTER'!$C$5:$C$250,"<>Cancelled",'RFI REGISTER'!$C$5:$C$250,"<>",'RFI REGISTER'!$A$5:$A$250,"<>")) | G11: =IF($A11="","",IFERROR(INDEX(SCOPES!$K$5:$K$200,MATCH($A11,SCOPES!$A$5:$A$200,0)),"")) | H11: =IF($A11="","",IFERROR(AVERAGEIFS('WP PROGRESS'!$F$2:$F$100,'WP PROGRESS'!$C$2:$C$100,$A11),"")) | I11: =IF($A11="","",IFERROR(AVERAGEIFS('WP PROGRESS'!$G$2:$G$100,'WP PROGRESS'!$C$2:$C$100,$A11),"")) | J11: =IF($A11="","",IFERROR(AVERAGEIFS('WP PROGRESS'!$H$2:$H$100,'WP PROGRESS'!$C$2:$C$100,$A11),"")) | K11: =IF($A11="","",IFERROR(AVERAGEIFS('WP PROGRESS'!$I$2:$I$100,'WP PROGRESS'!$C$2:$C$100,$A11),"")) | L11: =IF($A11="","",IFERROR(AVERAGEIFS('WP PROGRESS'!$J$2:$J$100,'WP PROGRESS'!$C$2:$C$100,$A11),"")) | M11: =IF($A11="","",IFERROR(AVERAGEIFS('WP PROGRESS'!$K$2:$K$100,'WP PROGRESS'!$C$2:$C$100,$A11),"")) | N11: =IF(OR($A11="",C11=0),"",COUNTIFS('WP PROGRESS'!$C$2:$C$100,$A11,'WP PROGRESS'!$V$2:$V$100,"Yes")+COUNTIFS('WP PROGRESS'!$C$2:$C$100,$A11,'WP PROGRESS'!$V$2:$V$100,"--")&" of "&C11) | O11: =IF($A11="","",COUNTIFS('WP PROGRESS'!$C$2:$C$100,$A11,'WP PROGRESS'!$Y$2:$Y$100,"X"))
B12: =IF($A12="","",IFERROR(INDEX(SCOPES!$B$5:$B$200,MATCH($A12,SCOPES!$A$5:$A$200,0)),"")) | C12: =IF($A12="","",COUNTIF('WORK PACKAGES'!$G$2:$G$100,$A12)) | D12: =IF($A12="","",COUNTIFS(ISSUES!$O$5:$O$200,$A12,ISSUES!$H$5:$H$200,"<>Closed",ISSUES!$H$5:$H$200,"<>Resolved",ISSUES!$H$5:$H$200,"<>Cancelled",ISSUES!$H$5:$H$200,"<>",ISSUES!$A$5:$A$200,"<>")) | E12: =IF($A12="","",COUNTIFS('RFI REGISTER'!$F$5:$F$250,"*"&$A12&"*",'RFI REGISTER'!$C$5:$C$250,"<>Closed",'RFI REGISTER'!$C$5:$C$250,"<>Cancelled",'RFI REGISTER'!$C$5:$C$250,"<>",'RFI REGISTER'!$A$5:$A$250,"<>")) | G12: =IF($A12="","",IFERROR(INDEX(SCOPES!$K$5:$K$200,MATCH($A12,SCOPES!$A$5:$A$200,0)),"")) | H12: =IF($A12="","",IFERROR(AVERAGEIFS('WP PROGRESS'!$F$2:$F$100,'WP PROGRESS'!$C$2:$C$100,$A12),"")) | I12: =IF($A12="","",IFERROR(AVERAGEIFS('WP PROGRESS'!$G$2:$G$100,'WP PROGRESS'!$C$2:$C$100,$A12),"")) | J12: =IF($A12="","",IFERROR(AVERAGEIFS('WP PROGRESS'!$H$2:$H$100,'WP PROGRESS'!$C$2:$C$100,$A12),"")) | K12: =IF($A12="","",IFERROR(AVERAGEIFS('WP PROGRESS'!$I$2:$I$100,'WP PROGRESS'!$C$2:$C$100,$A12),"")) | L12: =IF($A12="","",IFERROR(AVERAGEIFS('WP PROGRESS'!$J$2:$J$100,'WP PROGRESS'!$C$2:$C$100,$A12),"")) | M12: =IF($A12="","",IFERROR(AVERAGEIFS('WP PROGRESS'!$K$2:$K$100,'WP PROGRESS'!$C$2:$C$100,$A12),"")) | N12: =IF(OR($A12="",C12=0),"",COUNTIFS('WP PROGRESS'!$C$2:$C$100,$A12,'WP PROGRESS'!$V$2:$V$100,"Yes")+COUNTIFS('WP PROGRESS'!$C$2:$C$100,$A12,'WP PROGRESS'!$V$2:$V$100,"--")&" of "&C12) | O12: =IF($A12="","",COUNTIFS('WP PROGRESS'!$C$2:$C$100,$A12,'WP PROGRESS'!$Y$2:$Y$100,"X"))
B13: =IF($A13="","",IFERROR(INDEX(SCOPES!$B$5:$B$200,MATCH($A13,SCOPES!$A$5:$A$200,0)),"")) | C13: =IF($A13="","",COUNTIF('WORK PACKAGES'!$G$2:$G$100,$A13)) | D13: =IF($A13="","",COUNTIFS(ISSUES!$O$5:$O$200,$A13,ISSUES!$H$5:$H$200,"<>Closed",ISSUES!$H$5:$H$200,"<>Resolved",ISSUES!$H$5:$H$200,"<>Cancelled",ISSUES!$H$5:$H$200,"<>",ISSUES!$A$5:$A$200,"<>")) | E13: =IF($A13="","",COUNTIFS('RFI REGISTER'!$F$5:$F$250,"*"&$A13&"*",'RFI REGISTER'!$C$5:$C$250,"<>Closed",'RFI REGISTER'!$C$5:$C$250,"<>Cancelled",'RFI REGISTER'!$C$5:$C$250,"<>",'RFI REGISTER'!$A$5:$A$250,"<>")) | G13: =IF($A13="","",IFERROR(INDEX(SCOPES!$K$5:$K$200,MATCH($A13,SCOPES!$A$5:$A$200,0)),"")) | H13: =IF($A13="","",IFERROR(AVERAGEIFS('WP PROGRESS'!$F$2:$F$100,'WP PROGRESS'!$C$2:$C$100,$A13),"")) | I13: =IF($A13="","",IFERROR(AVERAGEIFS('WP PROGRESS'!$G$2:$G$100,'WP PROGRESS'!$C$2:$C$100,$A13),"")) | J13: =IF($A13="","",IFERROR(AVERAGEIFS('WP PROGRESS'!$H$2:$H$100,'WP PROGRESS'!$C$2:$C$100,$A13),"")) | K13: =IF($A13="","",IFERROR(AVERAGEIFS('WP PROGRESS'!$I$2:$I$100,'WP PROGRESS'!$C$2:$C$100,$A13),"")) | L13: =IF($A13="","",IFERROR(AVERAGEIFS('WP PROGRESS'!$J$2:$J$100,'WP PROGRESS'!$C$2:$C$100,$A13),"")) | M13: =IF($A13="","",IFERROR(AVERAGEIFS('WP PROGRESS'!$K$2:$K$100,'WP PROGRESS'!$C$2:$C$100,$A13),"")) | N13: =IF(OR($A13="",C13=0),"",COUNTIFS('WP PROGRESS'!$C$2:$C$100,$A13,'WP PROGRESS'!$V$2:$V$100,"Yes")+COUNTIFS('WP PROGRESS'!$C$2:$C$100,$A13,'WP PROGRESS'!$V$2:$V$100,"--")&" of "&C13) | O13: =IF($A13="","",COUNTIFS('WP PROGRESS'!$C$2:$C$100,$A13,'WP PROGRESS'!$Y$2:$Y$100,"X"))
B14: =IF($A14="","",IFERROR(INDEX(SCOPES!$B$5:$B$200,MATCH($A14,SCOPES!$A$5:$A$200,0)),"")) | C14: =IF($A14="","",COUNTIF('WORK PACKAGES'!$G$2:$G$100,$A14)) | D14: =IF($A14="","",COUNTIFS(ISSUES!$O$5:$O$200,$A14,ISSUES!$H$5:$H$200,"<>Closed",ISSUES!$H$5:$H$200,"<>Resolved",ISSUES!$H$5:$H$200,"<>Cancelled",ISSUES!$H$5:$H$200,"<>",ISSUES!$A$5:$A$200,"<>")) | E14: =IF($A14="","",COUNTIFS('RFI REGISTER'!$F$5:$F$250,"*"&$A14&"*",'RFI REGISTER'!$C$5:$C$250,"<>Closed",'RFI REGISTER'!$C$5:$C$250,"<>Cancelled",'RFI REGISTER'!$C$5:$C$250,"<>",'RFI REGISTER'!$A$5:$A$250,"<>")) | G14: =IF($A14="","",IFERROR(INDEX(SCOPES!$K$5:$K$200,MATCH($A14,SCOPES!$A$5:$A$200,0)),"")) | H14: =IF($A14="","",IFERROR(AVERAGEIFS('WP PROGRESS'!$F$2:$F$100,'WP PROGRESS'!$C$2:$C$100,$A14),"")) | I14: =IF($A14="","",IFERROR(AVERAGEIFS('WP PROGRESS'!$G$2:$G$100,'WP PROGRESS'!$C$2:$C$100,$A14),"")) | J14: =IF($A14="","",IFERROR(AVERAGEIFS('WP PROGRESS'!$H$2:$H$100,'WP PROGRESS'!$C$2:$C$100,$A14),"")) | K14: =IF($A14="","",IFERROR(AVERAGEIFS('WP PROGRESS'!$I$2:$I$100,'WP PROGRESS'!$C$2:$C$100,$A14),"")) | L14: =IF($A14="","",IFERROR(AVERAGEIFS('WP PROGRESS'!$J$2:$J$100,'WP PROGRESS'!$C$2:$C$100,$A14),"")) | M14: =IF($A14="","",IFERROR(AVERAGEIFS('WP PROGRESS'!$K$2:$K$100,'WP PROGRESS'!$C$2:$C$100,$A14),"")) | N14: =IF(OR($A14="",C14=0),"",COUNTIFS('WP PROGRESS'!$C$2:$C$100,$A14,'WP PROGRESS'!$V$2:$V$100,"Yes")+COUNTIFS('WP PROGRESS'!$C$2:$C$100,$A14,'WP PROGRESS'!$V$2:$V$100,"--")&" of "&C14) | O14: =IF($A14="","",COUNTIFS('WP PROGRESS'!$C$2:$C$100,$A14,'WP PROGRESS'!$Y$2:$Y$100,"X"))
B15: =IF($A15="","",IFERROR(INDEX(SCOPES!$B$5:$B$200,MATCH($A15,SCOPES!$A$5:$A$200,0)),"")) | C15: =IF($A15="","",COUNTIF('WORK PACKAGES'!$G$2:$G$100,$A15)) | D15: =IF($A15="","",COUNTIFS(ISSUES!$O$5:$O$200,$A15,ISSUES!$H$5:$H$200,"<>Closed",ISSUES!$H$5:$H$200,"<>Resolved",ISSUES!$H$5:$H$200,"<>Cancelled",ISSUES!$H$5:$H$200,"<>",ISSUES!$A$5:$A$200,"<>")) | E15: =IF($A15="","",COUNTIFS('RFI REGISTER'!$F$5:$F$250,"*"&$A15&"*",'RFI REGISTER'!$C$5:$C$250,"<>Closed",'RFI REGISTER'!$C$5:$C$250,"<>Cancelled",'RFI REGISTER'!$C$5:$C$250,"<>",'RFI REGISTER'!$A$5:$A$250,"<>")) | G15: =IF($A15="","",IFERROR(INDEX(SCOPES!$K$5:$K$200,MATCH($A15,SCOPES!$A$5:$A$200,0)),"")) | H15: =IF($A15="","",IFERROR(AVERAGEIFS('WP PROGRESS'!$F$2:$F$100,'WP PROGRESS'!$C$2:$C$100,$A15),"")) | I15: =IF($A15="","",IFERROR(AVERAGEIFS('WP PROGRESS'!$G$2:$G$100,'WP PROGRESS'!$C$2:$C$100,$A15),"")) | J15: =IF($A15="","",IFERROR(AVERAGEIFS('WP PROGRESS'!$H$2:$H$100,'WP PROGRESS'!$C$2:$C$100,$A15),"")) | K15: =IF($A15="","",IFERROR(AVERAGEIFS('WP PROGRESS'!$I$2:$I$100,'WP PROGRESS'!$C$2:$C$100,$A15),"")) | L15: =IF($A15="","",IFERROR(AVERAGEIFS('WP PROGRESS'!$J$2:$J$100,'WP PROGRESS'!$C$2:$C$100,$A15),"")) | M15: =IF($A15="","",IFERROR(AVERAGEIFS('WP PROGRESS'!$K$2:$K$100,'WP PROGRESS'!$C$2:$C$100,$A15),"")) | N15: =IF(OR($A15="",C15=0),"",COUNTIFS('WP PROGRESS'!$C$2:$C$100,$A15,'WP PROGRESS'!$V$2:$V$100,"Yes")+COUNTIFS('WP PROGRESS'!$C$2:$C$100,$A15,'WP PROGRESS'!$V$2:$V$100,"--")&" of "&C15) | O15: =IF($A15="","",COUNTIFS('WP PROGRESS'!$C$2:$C$100,$A15,'WP PROGRESS'!$Y$2:$Y$100,"X"))
B16: =IF($A16="","",IFERROR(INDEX(SCOPES!$B$5:$B$200,MATCH($A16,SCOPES!$A$5:$A$200,0)),"")) | C16: =IF($A16="","",COUNTIF('WORK PACKAGES'!$G$2:$G$100,$A16)) | D16: =IF($A16="","",COUNTIFS(ISSUES!$O$5:$O$200,$A16,ISSUES!$H$5:$H$200,"<>Closed",ISSUES!$H$5:$H$200,"<>Resolved",ISSUES!$H$5:$H$200,"<>Cancelled",ISSUES!$H$5:$H$200,"<>",ISSUES!$A$5:$A$200,"<>")) | E16: =IF($A16="","",COUNTIFS('RFI REGISTER'!$F$5:$F$250,"*"&$A16&"*",'RFI REGISTER'!$C$5:$C$250,"<>Closed",'RFI REGISTER'!$C$5:$C$250,"<>Cancelled",'RFI REGISTER'!$C$5:$C$250,"<>",'RFI REGISTER'!$A$5:$A$250,"<>")) | G16: =IF($A16="","",IFERROR(INDEX(SCOPES!$K$5:$K$200,MATCH($A16,SCOPES!$A$5:$A$200,0)),"")) | H16: =IF($A16="","",IFERROR(AVERAGEIFS('WP PROGRESS'!$F$2:$F$100,'WP PROGRESS'!$C$2:$C$100,$A16),"")) | I16: =IF($A16="","",IFERROR(AVERAGEIFS('WP PROGRESS'!$G$2:$G$100,'WP PROGRESS'!$C$2:$C$100,$A16),"")) | J16: =IF($A16="","",IFERROR(AVERAGEIFS('WP PROGRESS'!$H$2:$H$100,'WP PROGRESS'!$C$2:$C$100,$A16),"")) | K16: =IF($A16="","",IFERROR(AVERAGEIFS('WP PROGRESS'!$I$2:$I$100,'WP PROGRESS'!$C$2:$C$100,$A16),"")) | L16: =IF($A16="","",IFERROR(AVERAGEIFS('WP PROGRESS'!$J$2:$J$100,'WP PROGRESS'!$C$2:$C$100,$A16),"")) | M16: =IF($A16="","",IFERROR(AVERAGEIFS('WP PROGRESS'!$K$2:$K$100,'WP PROGRESS'!$C$2:$C$100,$A16),"")) | N16: =IF(OR($A16="",C16=0),"",COUNTIFS('WP PROGRESS'!$C$2:$C$100,$A16,'WP PROGRESS'!$V$2:$V$100,"Yes")+COUNTIFS('WP PROGRESS'!$C$2:$C$100,$A16,'WP PROGRESS'!$V$2:$V$100,"--")&" of "&C16) | O16: =IF($A16="","",COUNTIFS('WP PROGRESS'!$C$2:$C$100,$A16,'WP PROGRESS'!$Y$2:$Y$100,"X"))
... B44: =IF($A44="","",IFERROR(INDEX(SCOPES!$B$5:$B$200,MATCH($A44,SCOPES!$A$5:$A$200,0)),"")) | C44: =IF($A44="","",COUNTIF('WORK PACKAGES'!$G$2:$G$100,$A44)) | D44: =IF($A44="","",COUNTIFS(ISSUES!$O$5:$O$200,$A44,ISSUES!$H$5:$H$200,"<>Closed",ISSUES!$H$5:$H$200,"<>Resolved",ISSUES!$H$5:$H$200,"<>Cancelled",ISSUES!$H$5:$H$200,"<>",ISSUES!$A$5:$A$200,"<>")) | E44: =IF($A44="","",COUNTIFS('RFI REGISTER'!$F$5:$F$250,"*"&$A44&"*",'RFI REGISTER'!$C$5:$C$250,"<>Closed",'RFI REGISTER'!$C$5:$C$250,"<>Cancelled",'RFI REGISTER'!$C$5:$C$250,"<>",'RFI REGISTER'!$A$5:$A$250,"<>")) | G44: =IF($A44="","",IFERROR(INDEX(SCOPES!$K$5:$K$200,MATCH($A44,SCOPES!$A$5:$A$200,0)),"")) | H44: =IF($A44="","",IFERROR(AVERAGEIFS('WP PROGRESS'!$F$2:$F$100,'WP PROGRESS'!$C$2:$C$100,$A44),"")) | I44: =IF($A44="","",IFERROR(AVERAGEIFS('WP PROGRESS'!$G$2:$G$100,'WP PROGRESS'!$C$2:$C$100,$A44),"")) | J44: =IF($A44="","",IFERROR(AVERAGEIFS('WP PROGRESS'!$H$2:$H$100,'WP PROGRESS'!$C$2:$C$100,$A44),"")) | K44: =IF($A44="","",IFERROR(AVERAGEIFS('WP PROGRESS'!$I$2:$I$100,'WP PROGRESS'!$C$2:$C$100,$A44),"")) | L44: =IF($A44="","",IFERROR(AVERAGEIFS('WP PROGRESS'!$J$2:$J$100,'WP PROGRESS'!$C$2:$C$100,$A44),"")) | M44: =IF($A44="","",IFERROR(AVERAGEIFS('WP PROGRESS'!$K$2:$K$100,'WP PROGRESS'!$C$2:$C$100,$A44),"")) | N44: =IF(OR($A44="",C44=0),"",COUNTIFS('WP PROGRESS'!$C$2:$C$100,$A44,'WP PROGRESS'!$V$2:$V$100,"Yes")+COUNTIFS('WP PROGRESS'!$C$2:$C$100,$A44,'WP PROGRESS'!$V$2:$V$100,"--")&" of "&C44) | O44: =IF($A44="","",COUNTIFS('WP PROGRESS'!$C$2:$C$100,$A44,'WP PROGRESS'!$Y$2:$Y$100,"X"))

Sheet WP PROGRESS
A1: Work Package ID | B1: Package Code | C1: Primary Scope ID | D1: Priority Sequence | E1: Open Punch Items | F1: Eng % Complete | G1: Prog % Complete | H1: Cond & Wire % Complete | I1: Device Install % Complete | J1: Loop Check % Complete | K1: PreComm % Complete | L1: C&E Values Received | M1: CE Target Test Date | N1: Engineering Completed? | O1: Programming Completed? | P1: Cond & Wire Completed? | Q1: Device Install Completed | R1: Loops Check Completed | S1: PreComm Complete? | T1: Program Changes Required | U1: Program changes Completed | V1: Internal Progress Gates Complete? | W1: Site Acceptance Test Complete? | X1: Vendor Completed Checks | Y1: Blocked? (X) | Z1: Open RFIs | AA1: Open Engineering Issues | AB1: Progress Comments | AC1: Row Check (derived)
B2: =IF($A2="","",IFERROR(IF(INDEX('WORK PACKAGES'!$B$2:$B$100,MATCH($A2,'WORK PACKAGES'!$A$2:$A$100,0))="","",INDEX('WORK PACKAGES'!$B$2:$B$100,MATCH($A2,'WORK PACKAGES'!$A$2:$A$100,0))),"")) | C2: =IF($A2="","",IFERROR(IF(INDEX('WORK PACKAGES'!$G$2:$G$100,MATCH($A2,'WORK PACKAGES'!$A$2:$A$100,0))="","",INDEX('WORK PACKAGES'!$G$2:$G$100,MATCH($A2,'WORK PACKAGES'!$A$2:$A$100,0))),"")) | D2: =IF($A2="","",IFERROR(IF(INDEX('WORK PACKAGES'!$E$2:$E$100,MATCH($A2,'WORK PACKAGES'!$A$2:$A$100,0))="","",INDEX('WORK PACKAGES'!$E$2:$E$100,MATCH($A2,'WORK PACKAGES'!$A$2:$A$100,0))),"")) | E2: =IF(A2="","",IF(COUNTIFS('PUNCH LIST'!$G$3:$G$464,A2,'PUNCH LIST'!$Q$3:$Q$464,"Open")=0,"",COUNTIFS('PUNCH LIST'!$G$3:$G$464,A2,'PUNCH LIST'!$Q$3:$Q$464,"Open"))) | N2: =IF($A2="","",IF(ISBLANK(F2),"",IF(TRIM(F2)="--","--",IF(ISNUMBER(F2),IF(F2>=1,"Yes",IF(F2=0,"No","PARTIAL")),"CHECK")))) | O2: =IF($A2="","",IF(ISBLANK(G2),"",IF(TRIM(G2)="--","--",IF(ISNUMBER(G2),IF(G2>=1,"Yes",IF(G2=0,"No","PARTIAL")),"CHECK")))) | P2: =IF($A2="","",IF(ISBLANK(H2),"",IF(TRIM(H2)="--","--",IF(ISNUMBER(H2),IF(H2>=1,"Yes",IF(H2=0,"No","PARTIAL")),"CHECK")))) | Q2: =IF($A2="","",IF(ISBLANK(I2),"",IF(TRIM(I2)="--","--",IF(ISNUMBER(I2),IF(I2>=1,"Yes",IF(I2=0,"No","PARTIAL")),"CHECK")))) | R2: =IF($A2="","",IF(ISBLANK(J2),"",IF(TRIM(J2)="--","--",IF(ISNUMBER(J2),IF(J2>=1,"Yes",IF(J2=0,"No","PARTIAL")),"CHECK")))) | S2: =IF($A2="","",IF(ISBLANK(K2),"",IF(TRIM(K2)="--","--",IF(ISNUMBER(K2),IF(K2>=1,"Yes",IF(K2=0,"No","PARTIAL")),"CHECK")))) | V2: =IF($A2="","",IF(COUNTIF(N2:S2,"--")=6,"--",IF(COUNTIF(N2:S2,"Yes")+COUNTIF(N2:S2,"--")=6,"Yes","No"))) | Z2: =IF($A2="","",COUNTIFS('RFI REGISTER'!$D$5:$D$250,$A2,'RFI REGISTER'!$A$5:$A$250,"RFI-*",'RFI REGISTER'!$C$5:$C$250,"<>Closed",'RFI REGISTER'!$C$5:$C$250,"<>Cancelled")) | AA2: =IF($A2="","",COUNTIFS(ISSUES!$P$5:$P$200,"*"&$A2&"*",ISSUES!$H$5:$H$200,"<>Closed",ISSUES!$H$5:$H$200,"<>Resolved",ISSUES!$H$5:$H$200,"<>Cancelled",ISSUES!$H$5:$H$200,"<>",ISSUES!$A$5:$A$200,"<>")) | AC2: =IF(A2="","",IF(COUNTIF('WORK PACKAGES'!$A$2:$A$100,A2)=0,"NOT IN WORK PACKAGES",IF(COUNTIF($A$2:$A$100,A2)>1,"DUPLICATE","OK")))
B3: =IF($A3="","",IFERROR(IF(INDEX('WORK PACKAGES'!$B$2:$B$100,MATCH($A3,'WORK PACKAGES'!$A$2:$A$100,0))="","",INDEX('WORK PACKAGES'!$B$2:$B$100,MATCH($A3,'WORK PACKAGES'!$A$2:$A$100,0))),"")) | C3: =IF($A3="","",IFERROR(IF(INDEX('WORK PACKAGES'!$G$2:$G$100,MATCH($A3,'WORK PACKAGES'!$A$2:$A$100,0))="","",INDEX('WORK PACKAGES'!$G$2:$G$100,MATCH($A3,'WORK PACKAGES'!$A$2:$A$100,0))),"")) | D3: =IF($A3="","",IFERROR(IF(INDEX('WORK PACKAGES'!$E$2:$E$100,MATCH($A3,'WORK PACKAGES'!$A$2:$A$100,0))="","",INDEX('WORK PACKAGES'!$E$2:$E$100,MATCH($A3,'WORK PACKAGES'!$A$2:$A$100,0))),"")) | E3: =IF(A3="","",IF(COUNTIFS('PUNCH LIST'!$G$3:$G$464,A3,'PUNCH LIST'!$Q$3:$Q$464,"Open")=0,"",COUNTIFS('PUNCH LIST'!$G$3:$G$464,A3,'PUNCH LIST'!$Q$3:$Q$464,"Open"))) | N3: =IF($A3="","",IF(ISBLANK(F3),"",IF(TRIM(F3)="--","--",IF(ISNUMBER(F3),IF(F3>=1,"Yes",IF(F3=0,"No","PARTIAL")),"CHECK")))) | O3: =IF($A3="","",IF(ISBLANK(G3),"",IF(TRIM(G3)="--","--",IF(ISNUMBER(G3),IF(G3>=1,"Yes",IF(G3=0,"No","PARTIAL")),"CHECK")))) | P3: =IF($A3="","",IF(ISBLANK(H3),"",IF(TRIM(H3)="--","--",IF(ISNUMBER(H3),IF(H3>=1,"Yes",IF(H3=0,"No","PARTIAL")),"CHECK")))) | Q3: =IF($A3="","",IF(ISBLANK(I3),"",IF(TRIM(I3)="--","--",IF(ISNUMBER(I3),IF(I3>=1,"Yes",IF(I3=0,"No","PARTIAL")),"CHECK")))) | R3: =IF($A3="","",IF(ISBLANK(J3),"",IF(TRIM(J3)="--","--",IF(ISNUMBER(J3),IF(J3>=1,"Yes",IF(J3=0,"No","PARTIAL")),"CHECK")))) | S3: =IF($A3="","",IF(ISBLANK(K3),"",IF(TRIM(K3)="--","--",IF(ISNUMBER(K3),IF(K3>=1,"Yes",IF(K3=0,"No","PARTIAL")),"CHECK")))) | V3: =IF($A3="","",IF(COUNTIF(N3:S3,"--")=6,"--",IF(COUNTIF(N3:S3,"Yes")+COUNTIF(N3:S3,"--")=6,"Yes","No"))) | Z3: =IF($A3="","",COUNTIFS('RFI REGISTER'!$D$5:$D$250,$A3,'RFI REGISTER'!$A$5:$A$250,"RFI-*",'RFI REGISTER'!$C$5:$C$250,"<>Closed",'RFI REGISTER'!$C$5:$C$250,"<>Cancelled")) | AA3: =IF($A3="","",COUNTIFS(ISSUES!$P$5:$P$200,"*"&$A3&"*",ISSUES!$H$5:$H$200,"<>Closed",ISSUES!$H$5:$H$200,"<>Resolved",ISSUES!$H$5:$H$200,"<>Cancelled",ISSUES!$H$5:$H$200,"<>",ISSUES!$A$5:$A$200,"<>")) | AC3: =IF(A3="","",IF(COUNTIF('WORK PACKAGES'!$A$2:$A$100,A3)=0,"NOT IN WORK PACKAGES",IF(COUNTIF($A$2:$A$100,A3)>1,"DUPLICATE","OK")))
B4: =IF($A4="","",IFERROR(IF(INDEX('WORK PACKAGES'!$B$2:$B$100,MATCH($A4,'WORK PACKAGES'!$A$2:$A$100,0))="","",INDEX('WORK PACKAGES'!$B$2:$B$100,MATCH($A4,'WORK PACKAGES'!$A$2:$A$100,0))),"")) | C4: =IF($A4="","",IFERROR(IF(INDEX('WORK PACKAGES'!$G$2:$G$100,MATCH($A4,'WORK PACKAGES'!$A$2:$A$100,0))="","",INDEX('WORK PACKAGES'!$G$2:$G$100,MATCH($A4,'WORK PACKAGES'!$A$2:$A$100,0))),"")) | D4: =IF($A4="","",IFERROR(IF(INDEX('WORK PACKAGES'!$E$2:$E$100,MATCH($A4,'WORK PACKAGES'!$A$2:$A$100,0))="","",INDEX('WORK PACKAGES'!$E$2:$E$100,MATCH($A4,'WORK PACKAGES'!$A$2:$A$100,0))),"")) | E4: =IF(A4="","",IF(COUNTIFS('PUNCH LIST'!$G$3:$G$464,A4,'PUNCH LIST'!$Q$3:$Q$464,"Open")=0,"",COUNTIFS('PUNCH LIST'!$G$3:$G$464,A4,'PUNCH LIST'!$Q$3:$Q$464,"Open"))) | N4: =IF($A4="","",IF(ISBLANK(F4),"",IF(TRIM(F4)="--","--",IF(ISNUMBER(F4),IF(F4>=1,"Yes",IF(F4=0,"No","PARTIAL")),"CHECK")))) | O4: =IF($A4="","",IF(ISBLANK(G4),"",IF(TRIM(G4)="--","--",IF(ISNUMBER(G4),IF(G4>=1,"Yes",IF(G4=0,"No","PARTIAL")),"CHECK")))) | P4: =IF($A4="","",IF(ISBLANK(H4),"",IF(TRIM(H4)="--","--",IF(ISNUMBER(H4),IF(H4>=1,"Yes",IF(H4=0,"No","PARTIAL")),"CHECK")))) | Q4: =IF($A4="","",IF(ISBLANK(I4),"",IF(TRIM(I4)="--","--",IF(ISNUMBER(I4),IF(I4>=1,"Yes",IF(I4=0,"No","PARTIAL")),"CHECK")))) | R4: =IF($A4="","",IF(ISBLANK(J4),"",IF(TRIM(J4)="--","--",IF(ISNUMBER(J4),IF(J4>=1,"Yes",IF(J4=0,"No","PARTIAL")),"CHECK")))) | S4: =IF($A4="","",IF(ISBLANK(K4),"",IF(TRIM(K4)="--","--",IF(ISNUMBER(K4),IF(K4>=1,"Yes",IF(K4=0,"No","PARTIAL")),"CHECK")))) | V4: =IF($A4="","",IF(COUNTIF(N4:S4,"--")=6,"--",IF(COUNTIF(N4:S4,"Yes")+COUNTIF(N4:S4,"--")=6,"Yes","No"))) | Z4: =IF($A4="","",COUNTIFS('RFI REGISTER'!$D$5:$D$250,$A4,'RFI REGISTER'!$A$5:$A$250,"RFI-*",'RFI REGISTER'!$C$5:$C$250,"<>Closed",'RFI REGISTER'!$C$5:$C$250,"<>Cancelled")) | AA4: =IF($A4="","",COUNTIFS(ISSUES!$P$5:$P$200,"*"&$A4&"*",ISSUES!$H$5:$H$200,"<>Closed",ISSUES!$H$5:$H$200,"<>Resolved",ISSUES!$H$5:$H$200,"<>Cancelled",ISSUES!$H$5:$H$200,"<>",ISSUES!$A$5:$A$200,"<>")) | AC4: =IF(A4="","",IF(COUNTIF('WORK PACKAGES'!$A$2:$A$100,A4)=0,"NOT IN WORK PACKAGES",IF(COUNTIF($A$2:$A$100,A4)>1,"DUPLICATE","OK")))
B5: =IF($A5="","",IFERROR(IF(INDEX('WORK PACKAGES'!$B$2:$B$100,MATCH($A5,'WORK PACKAGES'!$A$2:$A$100,0))="","",INDEX('WORK PACKAGES'!$B$2:$B$100,MATCH($A5,'WORK PACKAGES'!$A$2:$A$100,0))),"")) | C5: =IF($A5="","",IFERROR(IF(INDEX('WORK PACKAGES'!$G$2:$G$100,MATCH($A5,'WORK PACKAGES'!$A$2:$A$100,0))="","",INDEX('WORK PACKAGES'!$G$2:$G$100,MATCH($A5,'WORK PACKAGES'!$A$2:$A$100,0))),"")) | D5: =IF($A5="","",IFERROR(IF(INDEX('WORK PACKAGES'!$E$2:$E$100,MATCH($A5,'WORK PACKAGES'!$A$2:$A$100,0))="","",INDEX('WORK PACKAGES'!$E$2:$E$100,MATCH($A5,'WORK PACKAGES'!$A$2:$A$100,0))),"")) | E5: =IF(A5="","",IF(COUNTIFS('PUNCH LIST'!$G$3:$G$464,A5,'PUNCH LIST'!$Q$3:$Q$464,"Open")=0,"",COUNTIFS('PUNCH LIST'!$G$3:$G$464,A5,'PUNCH LIST'!$Q$3:$Q$464,"Open"))) | N5: =IF($A5="","",IF(ISBLANK(F5),"",IF(TRIM(F5)="--","--",IF(ISNUMBER(F5),IF(F5>=1,"Yes",IF(F5=0,"No","PARTIAL")),"CHECK")))) | O5: =IF($A5="","",IF(ISBLANK(G5),"",IF(TRIM(G5)="--","--",IF(ISNUMBER(G5),IF(G5>=1,"Yes",IF(G5=0,"No","PARTIAL")),"CHECK")))) | P5: =IF($A5="","",IF(ISBLANK(H5),"",IF(TRIM(H5)="--","--",IF(ISNUMBER(H5),IF(H5>=1,"Yes",IF(H5=0,"No","PARTIAL")),"CHECK")))) | Q5: =IF($A5="","",IF(ISBLANK(I5),"",IF(TRIM(I5)="--","--",IF(ISNUMBER(I5),IF(I5>=1,"Yes",IF(I5=0,"No","PARTIAL")),"CHECK")))) | R5: =IF($A5="","",IF(ISBLANK(J5),"",IF(TRIM(J5)="--","--",IF(ISNUMBER(J5),IF(J5>=1,"Yes",IF(J5=0,"No","PARTIAL")),"CHECK")))) | S5: =IF($A5="","",IF(ISBLANK(K5),"",IF(TRIM(K5)="--","--",IF(ISNUMBER(K5),IF(K5>=1,"Yes",IF(K5=0,"No","PARTIAL")),"CHECK")))) | V5: =IF($A5="","",IF(COUNTIF(N5:S5,"--")=6,"--",IF(COUNTIF(N5:S5,"Yes")+COUNTIF(N5:S5,"--")=6,"Yes","No"))) | Z5: =IF($A5="","",COUNTIFS('RFI REGISTER'!$D$5:$D$250,$A5,'RFI REGISTER'!$A$5:$A$250,"RFI-*",'RFI REGISTER'!$C$5:$C$250,"<>Closed",'RFI REGISTER'!$C$5:$C$250,"<>Cancelled")) | AA5: =IF($A5="","",COUNTIFS(ISSUES!$P$5:$P$200,"*"&$A5&"*",ISSUES!$H$5:$H$200,"<>Closed",ISSUES!$H$5:$H$200,"<>Resolved",ISSUES!$H$5:$H$200,"<>Cancelled",ISSUES!$H$5:$H$200,"<>",ISSUES!$A$5:$A$200,"<>")) | AC5: =IF(A5="","",IF(COUNTIF('WORK PACKAGES'!$A$2:$A$100,A5)=0,"NOT IN WORK PACKAGES",IF(COUNTIF($A$2:$A$100,A5)>1,"DUPLICATE","OK")))
B6: =IF($A6="","",IFERROR(IF(INDEX('WORK PACKAGES'!$B$2:$B$100,MATCH($A6,'WORK PACKAGES'!$A$2:$A$100,0))="","",INDEX('WORK PACKAGES'!$B$2:$B$100,MATCH($A6,'WORK PACKAGES'!$A$2:$A$100,0))),"")) | C6: =IF($A6="","",IFERROR(IF(INDEX('WORK PACKAGES'!$G$2:$G$100,MATCH($A6,'WORK PACKAGES'!$A$2:$A$100,0))="","",INDEX('WORK PACKAGES'!$G$2:$G$100,MATCH($A6,'WORK PACKAGES'!$A$2:$A$100,0))),"")) | D6: =IF($A6="","",IFERROR(IF(INDEX('WORK PACKAGES'!$E$2:$E$100,MATCH($A6,'WORK PACKAGES'!$A$2:$A$100,0))="","",INDEX('WORK PACKAGES'!$E$2:$E$100,MATCH($A6,'WORK PACKAGES'!$A$2:$A$100,0))),"")) | E6: =IF(A6="","",IF(COUNTIFS('PUNCH LIST'!$G$3:$G$464,A6,'PUNCH LIST'!$Q$3:$Q$464,"Open")=0,"",COUNTIFS('PUNCH LIST'!$G$3:$G$464,A6,'PUNCH LIST'!$Q$3:$Q$464,"Open"))) | N6: =IF($A6="","",IF(ISBLANK(F6),"",IF(TRIM(F6)="--","--",IF(ISNUMBER(F6),IF(F6>=1,"Yes",IF(F6=0,"No","PARTIAL")),"CHECK")))) | O6: =IF($A6="","",IF(ISBLANK(G6),"",IF(TRIM(G6)="--","--",IF(ISNUMBER(G6),IF(G6>=1,"Yes",IF(G6=0,"No","PARTIAL")),"CHECK")))) | P6: =IF($A6="","",IF(ISBLANK(H6),"",IF(TRIM(H6)="--","--",IF(ISNUMBER(H6),IF(H6>=1,"Yes",IF(H6=0,"No","PARTIAL")),"CHECK")))) | Q6: =IF($A6="","",IF(ISBLANK(I6),"",IF(TRIM(I6)="--","--",IF(ISNUMBER(I6),IF(I6>=1,"Yes",IF(I6=0,"No","PARTIAL")),"CHECK")))) | R6: =IF($A6="","",IF(ISBLANK(J6),"",IF(TRIM(J6)="--","--",IF(ISNUMBER(J6),IF(J6>=1,"Yes",IF(J6=0,"No","PARTIAL")),"CHECK")))) | S6: =IF($A6="","",IF(ISBLANK(K6),"",IF(TRIM(K6)="--","--",IF(ISNUMBER(K6),IF(K6>=1,"Yes",IF(K6=0,"No","PARTIAL")),"CHECK")))) | V6: =IF($A6="","",IF(COUNTIF(N6:S6,"--")=6,"--",IF(COUNTIF(N6:S6,"Yes")+COUNTIF(N6:S6,"--")=6,"Yes","No"))) | Z6: =IF($A6="","",COUNTIFS('RFI REGISTER'!$D$5:$D$250,$A6,'RFI REGISTER'!$A$5:$A$250,"RFI-*",'RFI REGISTER'!$C$5:$C$250,"<>Closed",'RFI REGISTER'!$C$5:$C$250,"<>Cancelled")) | AA6: =IF($A6="","",COUNTIFS(ISSUES!$P$5:$P$200,"*"&$A6&"*",ISSUES!$H$5:$H$200,"<>Closed",ISSUES!$H$5:$H$200,"<>Resolved",ISSUES!$H$5:$H$200,"<>Cancelled",ISSUES!$H$5:$H$200,"<>",ISSUES!$A$5:$A$200,"<>")) | AC6: =IF(A6="","",IF(COUNTIF('WORK PACKAGES'!$A$2:$A$100,A6)=0,"NOT IN WORK PACKAGES",IF(COUNTIF($A$2:$A$100,A6)>1,"DUPLICATE","OK")))
B7: =IF($A7="","",IFERROR(IF(INDEX('WORK PACKAGES'!$B$2:$B$100,MATCH($A7,'WORK PACKAGES'!$A$2:$A$100,0))="","",INDEX('WORK PACKAGES'!$B$2:$B$100,MATCH($A7,'WORK PACKAGES'!$A$2:$A$100,0))),"")) | C7: =IF($A7="","",IFERROR(IF(INDEX('WORK PACKAGES'!$G$2:$G$100,MATCH($A7,'WORK PACKAGES'!$A$2:$A$100,0))="","",INDEX('WORK PACKAGES'!$G$2:$G$100,MATCH($A7,'WORK PACKAGES'!$A$2:$A$100,0))),"")) | D7: =IF($A7="","",IFERROR(IF(INDEX('WORK PACKAGES'!$E$2:$E$100,MATCH($A7,'WORK PACKAGES'!$A$2:$A$100,0))="","",INDEX('WORK PACKAGES'!$E$2:$E$100,MATCH($A7,'WORK PACKAGES'!$A$2:$A$100,0))),"")) | E7: =IF(A7="","",IF(COUNTIFS('PUNCH LIST'!$G$3:$G$464,A7,'PUNCH LIST'!$Q$3:$Q$464,"Open")=0,"",COUNTIFS('PUNCH LIST'!$G$3:$G$464,A7,'PUNCH LIST'!$Q$3:$Q$464,"Open"))) | N7: =IF($A7="","",IF(ISBLANK(F7),"",IF(TRIM(F7)="--","--",IF(ISNUMBER(F7),IF(F7>=1,"Yes",IF(F7=0,"No","PARTIAL")),"CHECK")))) | O7: =IF($A7="","",IF(ISBLANK(G7),"",IF(TRIM(G7)="--","--",IF(ISNUMBER(G7),IF(G7>=1,"Yes",IF(G7=0,"No","PARTIAL")),"CHECK")))) | P7: =IF($A7="","",IF(ISBLANK(H7),"",IF(TRIM(H7)="--","--",IF(ISNUMBER(H7),IF(H7>=1,"Yes",IF(H7=0,"No","PARTIAL")),"CHECK")))) | Q7: =IF($A7="","",IF(ISBLANK(I7),"",IF(TRIM(I7)="--","--",IF(ISNUMBER(I7),IF(I7>=1,"Yes",IF(I7=0,"No","PARTIAL")),"CHECK")))) | R7: =IF($A7="","",IF(ISBLANK(J7),"",IF(TRIM(J7)="--","--",IF(ISNUMBER(J7),IF(J7>=1,"Yes",IF(J7=0,"No","PARTIAL")),"CHECK")))) | S7: =IF($A7="","",IF(ISBLANK(K7),"",IF(TRIM(K7)="--","--",IF(ISNUMBER(K7),IF(K7>=1,"Yes",IF(K7=0,"No","PARTIAL")),"CHECK")))) | V7: =IF($A7="","",IF(COUNTIF(N7:S7,"--")=6,"--",IF(COUNTIF(N7:S7,"Yes")+COUNTIF(N7:S7,"--")=6,"Yes","No"))) | Z7: =IF($A7="","",COUNTIFS('RFI REGISTER'!$D$5:$D$250,$A7,'RFI REGISTER'!$A$5:$A$250,"RFI-*",'RFI REGISTER'!$C$5:$C$250,"<>Closed",'RFI REGISTER'!$C$5:$C$250,"<>Cancelled")) | AA7: =IF($A7="","",COUNTIFS(ISSUES!$P$5:$P$200,"*"&$A7&"*",ISSUES!$H$5:$H$200,"<>Closed",ISSUES!$H$5:$H$200,"<>Resolved",ISSUES!$H$5:$H$200,"<>Cancelled",ISSUES!$H$5:$H$200,"<>",ISSUES!$A$5:$A$200,"<>")) | AC7: =IF(A7="","",IF(COUNTIF('WORK PACKAGES'!$A$2:$A$100,A7)=0,"NOT IN WORK PACKAGES",IF(COUNTIF($A$2:$A$100,A7)>1,"DUPLICATE","OK")))
B8: =IF($A8="","",IFERROR(IF(INDEX('WORK PACKAGES'!$B$2:$B$100,MATCH($A8,'WORK PACKAGES'!$A$2:$A$100,0))="","",INDEX('WORK PACKAGES'!$B$2:$B$100,MATCH($A8,'WORK PACKAGES'!$A$2:$A$100,0))),"")) | C8: =IF($A8="","",IFERROR(IF(INDEX('WORK PACKAGES'!$G$2:$G$100,MATCH($A8,'WORK PACKAGES'!$A$2:$A$100,0))="","",INDEX('WORK PACKAGES'!$G$2:$G$100,MATCH($A8,'WORK PACKAGES'!$A$2:$A$100,0))),"")) | D8: =IF($A8="","",IFERROR(IF(INDEX('WORK PACKAGES'!$E$2:$E$100,MATCH($A8,'WORK PACKAGES'!$A$2:$A$100,0))="","",INDEX('WORK PACKAGES'!$E$2:$E$100,MATCH($A8,'WORK PACKAGES'!$A$2:$A$100,0))),"")) | E8: =IF(A8="","",IF(COUNTIFS('PUNCH LIST'!$G$3:$G$464,A8,'PUNCH LIST'!$Q$3:$Q$464,"Open")=0,"",COUNTIFS('PUNCH LIST'!$G$3:$G$464,A8,'PUNCH LIST'!$Q$3:$Q$464,"Open"))) | N8: =IF($A8="","",IF(ISBLANK(F8),"",IF(TRIM(F8)="--","--",IF(ISNUMBER(F8),IF(F8>=1,"Yes",IF(F8=0,"No","PARTIAL")),"CHECK")))) | O8: =IF($A8="","",IF(ISBLANK(G8),"",IF(TRIM(G8)="--","--",IF(ISNUMBER(G8),IF(G8>=1,"Yes",IF(G8=0,"No","PARTIAL")),"CHECK")))) | P8: =IF($A8="","",IF(ISBLANK(H8),"",IF(TRIM(H8)="--","--",IF(ISNUMBER(H8),IF(H8>=1,"Yes",IF(H8=0,"No","PARTIAL")),"CHECK")))) | Q8: =IF($A8="","",IF(ISBLANK(I8),"",IF(TRIM(I8)="--","--",IF(ISNUMBER(I8),IF(I8>=1,"Yes",IF(I8=0,"No","PARTIAL")),"CHECK")))) | R8: =IF($A8="","",IF(ISBLANK(J8),"",IF(TRIM(J8)="--","--",IF(ISNUMBER(J8),IF(J8>=1,"Yes",IF(J8=0,"No","PARTIAL")),"CHECK")))) | S8: =IF($A8="","",IF(ISBLANK(K8),"",IF(TRIM(K8)="--","--",IF(ISNUMBER(K8),IF(K8>=1,"Yes",IF(K8=0,"No","PARTIAL")),"CHECK")))) | V8: =IF($A8="","",IF(COUNTIF(N8:S8,"--")=6,"--",IF(COUNTIF(N8:S8,"Yes")+COUNTIF(N8:S8,"--")=6,"Yes","No"))) | Z8: =IF($A8="","",COUNTIFS('RFI REGISTER'!$D$5:$D$250,$A8,'RFI REGISTER'!$A$5:$A$250,"RFI-*",'RFI REGISTER'!$C$5:$C$250,"<>Closed",'RFI REGISTER'!$C$5:$C$250,"<>Cancelled")) | AA8: =IF($A8="","",COUNTIFS(ISSUES!$P$5:$P$200,"*"&$A8&"*",ISSUES!$H$5:$H$200,"<>Closed",ISSUES!$H$5:$H$200,"<>Resolved",ISSUES!$H$5:$H$200,"<>Cancelled",ISSUES!$H$5:$H$200,"<>",ISSUES!$A$5:$A$200,"<>")) | AC8: =IF(A8="","",IF(COUNTIF('WORK PACKAGES'!$A$2:$A$100,A8)=0,"NOT IN WORK PACKAGES",IF(COUNTIF($A$2:$A$100,A8)>1,"DUPLICATE","OK")))
B9: =IF($A9="","",IFERROR(IF(INDEX('WORK PACKAGES'!$B$2:$B$100,MATCH($A9,'WORK PACKAGES'!$A$2:$A$100,0))="","",INDEX('WORK PACKAGES'!$B$2:$B$100,MATCH($A9,'WORK PACKAGES'!$A$2:$A$100,0))),"")) | C9: =IF($A9="","",IFERROR(IF(INDEX('WORK PACKAGES'!$G$2:$G$100,MATCH($A9,'WORK PACKAGES'!$A$2:$A$100,0))="","",INDEX('WORK PACKAGES'!$G$2:$G$100,MATCH($A9,'WORK PACKAGES'!$A$2:$A$100,0))),"")) | D9: =IF($A9="","",IFERROR(IF(INDEX('WORK PACKAGES'!$E$2:$E$100,MATCH($A9,'WORK PACKAGES'!$A$2:$A$100,0))="","",INDEX('WORK PACKAGES'!$E$2:$E$100,MATCH($A9,'WORK PACKAGES'!$A$2:$A$100,0))),"")) | E9: =IF(A9="","",IF(COUNTIFS('PUNCH LIST'!$G$3:$G$464,A9,'PUNCH LIST'!$Q$3:$Q$464,"Open")=0,"",COUNTIFS('PUNCH LIST'!$G$3:$G$464,A9,'PUNCH LIST'!$Q$3:$Q$464,"Open"))) | N9: =IF($A9="","",IF(ISBLANK(F9),"",IF(TRIM(F9)="--","--",IF(ISNUMBER(F9),IF(F9>=1,"Yes",IF(F9=0,"No","PARTIAL")),"CHECK")))) | O9: =IF($A9="","",IF(ISBLANK(G9),"",IF(TRIM(G9)="--","--",IF(ISNUMBER(G9),IF(G9>=1,"Yes",IF(G9=0,"No","PARTIAL")),"CHECK")))) | P9: =IF($A9="","",IF(ISBLANK(H9),"",IF(TRIM(H9)="--","--",IF(ISNUMBER(H9),IF(H9>=1,"Yes",IF(H9=0,"No","PARTIAL")),"CHECK")))) | Q9: =IF($A9="","",IF(ISBLANK(I9),"",IF(TRIM(I9)="--","--",IF(ISNUMBER(I9),IF(I9>=1,"Yes",IF(I9=0,"No","PARTIAL")),"CHECK")))) | R9: =IF($A9="","",IF(ISBLANK(J9),"",IF(TRIM(J9)="--","--",IF(ISNUMBER(J9),IF(J9>=1,"Yes",IF(J9=0,"No","PARTIAL")),"CHECK")))) | S9: =IF($A9="","",IF(ISBLANK(K9),"",IF(TRIM(K9)="--","--",IF(ISNUMBER(K9),IF(K9>=1,"Yes",IF(K9=0,"No","PARTIAL")),"CHECK")))) | V9: =IF($A9="","",IF(COUNTIF(N9:S9,"--")=6,"--",IF(COUNTIF(N9:S9,"Yes")+COUNTIF(N9:S9,"--")=6,"Yes","No"))) | Z9: =IF($A9="","",COUNTIFS('RFI REGISTER'!$D$5:$D$250,$A9,'RFI REGISTER'!$A$5:$A$250,"RFI-*",'RFI REGISTER'!$C$5:$C$250,"<>Closed",'RFI REGISTER'!$C$5:$C$250,"<>Cancelled")) | AA9: =IF($A9="","",COUNTIFS(ISSUES!$P$5:$P$200,"*"&$A9&"*",ISSUES!$H$5:$H$200,"<>Closed",ISSUES!$H$5:$H$200,"<>Resolved",ISSUES!$H$5:$H$200,"<>Cancelled",ISSUES!$H$5:$H$200,"<>",ISSUES!$A$5:$A$200,"<>")) | AC9: =IF(A9="","",IF(COUNTIF('WORK PACKAGES'!$A$2:$A$100,A9)=0,"NOT IN WORK PACKAGES",IF(COUNTIF($A$2:$A$100,A9)>1,"DUPLICATE","OK")))
B10: =IF($A10="","",IFERROR(IF(INDEX('WORK PACKAGES'!$B$2:$B$100,MATCH($A10,'WORK PACKAGES'!$A$2:$A$100,0))="","",INDEX('WORK PACKAGES'!$B$2:$B$100,MATCH($A10,'WORK PACKAGES'!$A$2:$A$100,0))),"")) | C10: =IF($A10="","",IFERROR(IF(INDEX('WORK PACKAGES'!$G$2:$G$100,MATCH($A10,'WORK PACKAGES'!$A$2:$A$100,0))="","",INDEX('WORK PACKAGES'!$G$2:$G$100,MATCH($A10,'WORK PACKAGES'!$A$2:$A$100,0))),"")) | D10: =IF($A10="","",IFERROR(IF(INDEX('WORK PACKAGES'!$E$2:$E$100,MATCH($A10,'WORK PACKAGES'!$A$2:$A$100,0))="","",INDEX('WORK PACKAGES'!$E$2:$E$100,MATCH($A10,'WORK PACKAGES'!$A$2:$A$100,0))),"")) | E10: =IF(A10="","",IF(COUNTIFS('PUNCH LIST'!$G$3:$G$464,A10,'PUNCH LIST'!$Q$3:$Q$464,"Open")=0,"",COUNTIFS('PUNCH LIST'!$G$3:$G$464,A10,'PUNCH LIST'!$Q$3:$Q$464,"Open"))) | N10: =IF($A10="","",IF(ISBLANK(F10),"",IF(TRIM(F10)="--","--",IF(ISNUMBER(F10),IF(F10>=1,"Yes",IF(F10=0,"No","PARTIAL")),"CHECK")))) | O10: =IF($A10="","",IF(ISBLANK(G10),"",IF(TRIM(G10)="--","--",IF(ISNUMBER(G10),IF(G10>=1,"Yes",IF(G10=0,"No","PARTIAL")),"CHECK")))) | P10: =IF($A10="","",IF(ISBLANK(H10),"",IF(TRIM(H10)="--","--",IF(ISNUMBER(H10),IF(H10>=1,"Yes",IF(H10=0,"No","PARTIAL")),"CHECK")))) | Q10: =IF($A10="","",IF(ISBLANK(I10),"",IF(TRIM(I10)="--","--",IF(ISNUMBER(I10),IF(I10>=1,"Yes",IF(I10=0,"No","PARTIAL")),"CHECK")))) | R10: =IF($A10="","",IF(ISBLANK(J10),"",IF(TRIM(J10)="--","--",IF(ISNUMBER(J10),IF(J10>=1,"Yes",IF(J10=0,"No","PARTIAL")),"CHECK")))) | S10: =IF($A10="","",IF(ISBLANK(K10),"",IF(TRIM(K10)="--","--",IF(ISNUMBER(K10),IF(K10>=1,"Yes",IF(K10=0,"No","PARTIAL")),"CHECK")))) | V10: =IF($A10="","",IF(COUNTIF(N10:S10,"--")=6,"--",IF(COUNTIF(N10:S10,"Yes")+COUNTIF(N10:S10,"--")=6,"Yes","No"))) | Z10: =IF($A10="","",COUNTIFS('RFI REGISTER'!$D$5:$D$250,$A10,'RFI REGISTER'!$A$5:$A$250,"RFI-*",'RFI REGISTER'!$C$5:$C$250,"<>Closed",'RFI REGISTER'!$C$5:$C$250,"<>Cancelled")) | AA10: =IF($A10="","",COUNTIFS(ISSUES!$P$5:$P$200,"*"&$A10&"*",ISSUES!$H$5:$H$200,"<>Closed",ISSUES!$H$5:$H$200,"<>Resolved",ISSUES!$H$5:$H$200,"<>Cancelled",ISSUES!$H$5:$H$200,"<>",ISSUES!$A$5:$A$200,"<>")) | AC10: =IF(A10="","",IF(COUNTIF('WORK PACKAGES'!$A$2:$A$100,A10)=0,"NOT IN WORK PACKAGES",IF(COUNTIF($A$2:$A$100,A10)>1,"DUPLICATE","OK")))
B11: =IF($A11="","",IFERROR(IF(INDEX('WORK PACKAGES'!$B$2:$B$100,MATCH($A11,'WORK PACKAGES'!$A$2:$A$100,0))="","",INDEX('WORK PACKAGES'!$B$2:$B$100,MATCH($A11,'WORK PACKAGES'!$A$2:$A$100,0))),"")) | C11: =IF($A11="","",IFERROR(IF(INDEX('WORK PACKAGES'!$G$2:$G$100,MATCH($A11,'WORK PACKAGES'!$A$2:$A$100,0))="","",INDEX('WORK PACKAGES'!$G$2:$G$100,MATCH($A11,'WORK PACKAGES'!$A$2:$A$100,0))),"")) | D11: =IF($A11="","",IFERROR(IF(INDEX('WORK PACKAGES'!$E$2:$E$100,MATCH($A11,'WORK PACKAGES'!$A$2:$A$100,0))="","",INDEX('WORK PACKAGES'!$E$2:$E$100,MATCH($A11,'WORK PACKAGES'!$A$2:$A$100,0))),"")) | E11: =IF(A11="","",IF(COUNTIFS('PUNCH LIST'!$G$3:$G$464,A11,'PUNCH LIST'!$Q$3:$Q$464,"Open")=0,"",COUNTIFS('PUNCH LIST'!$G$3:$G$464,A11,'PUNCH LIST'!$Q$3:$Q$464,"Open"))) | N11: =IF($A11="","",IF(ISBLANK(F11),"",IF(TRIM(F11)="--","--",IF(ISNUMBER(F11),IF(F11>=1,"Yes",IF(F11=0,"No","PARTIAL")),"CHECK")))) | O11: =IF($A11="","",IF(ISBLANK(G11),"",IF(TRIM(G11)="--","--",IF(ISNUMBER(G11),IF(G11>=1,"Yes",IF(G11=0,"No","PARTIAL")),"CHECK")))) | P11: =IF($A11="","",IF(ISBLANK(H11),"",IF(TRIM(H11)="--","--",IF(ISNUMBER(H11),IF(H11>=1,"Yes",IF(H11=0,"No","PARTIAL")),"CHECK")))) | Q11: =IF($A11="","",IF(ISBLANK(I11),"",IF(TRIM(I11)="--","--",IF(ISNUMBER(I11),IF(I11>=1,"Yes",IF(I11=0,"No","PARTIAL")),"CHECK")))) | R11: =IF($A11="","",IF(ISBLANK(J11),"",IF(TRIM(J11)="--","--",IF(ISNUMBER(J11),IF(J11>=1,"Yes",IF(J11=0,"No","PARTIAL")),"CHECK")))) | S11: =IF($A11="","",IF(ISBLANK(K11),"",IF(TRIM(K11)="--","--",IF(ISNUMBER(K11),IF(K11>=1,"Yes",IF(K11=0,"No","PARTIAL")),"CHECK")))) | V11: =IF($A11="","",IF(COUNTIF(N11:S11,"--")=6,"--",IF(COUNTIF(N11:S11,"Yes")+COUNTIF(N11:S11,"--")=6,"Yes","No"))) | Z11: =IF($A11="","",COUNTIFS('RFI REGISTER'!$D$5:$D$250,$A11,'RFI REGISTER'!$A$5:$A$250,"RFI-*",'RFI REGISTER'!$C$5:$C$250,"<>Closed",'RFI REGISTER'!$C$5:$C$250,"<>Cancelled")) | AA11: =IF($A11="","",COUNTIFS(ISSUES!$P$5:$P$200,"*"&$A11&"*",ISSUES!$H$5:$H$200,"<>Closed",ISSUES!$H$5:$H$200,"<>Resolved",ISSUES!$H$5:$H$200,"<>Cancelled",ISSUES!$H$5:$H$200,"<>",ISSUES!$A$5:$A$200,"<>")) | AC11: =IF(A11="","",IF(COUNTIF('WORK PACKAGES'!$A$2:$A$100,A11)=0,"NOT IN WORK PACKAGES",IF(COUNTIF($A$2:$A$100,A11)>1,"DUPLICATE","OK")))
B12: =IF($A12="","",IFERROR(IF(INDEX('WORK PACKAGES'!$B$2:$B$100,MATCH($A12,'WORK PACKAGES'!$A$2:$A$100,0))="","",INDEX('WORK PACKAGES'!$B$2:$B$100,MATCH($A12,'WORK PACKAGES'!$A$2:$A$100,0))),"")) | C12: =IF($A12="","",IFERROR(IF(INDEX('WORK PACKAGES'!$G$2:$G$100,MATCH($A12,'WORK PACKAGES'!$A$2:$A$100,0))="","",INDEX('WORK PACKAGES'!$G$2:$G$100,MATCH($A12,'WORK PACKAGES'!$A$2:$A$100,0))),"")) | D12: =IF($A12="","",IFERROR(IF(INDEX('WORK PACKAGES'!$E$2:$E$100,MATCH($A12,'WORK PACKAGES'!$A$2:$A$100,0))="","",INDEX('WORK PACKAGES'!$E$2:$E$100,MATCH($A12,'WORK PACKAGES'!$A$2:$A$100,0))),"")) | E12: =IF(A12="","",IF(COUNTIFS('PUNCH LIST'!$G$3:$G$464,A12,'PUNCH LIST'!$Q$3:$Q$464,"Open")=0,"",COUNTIFS('PUNCH LIST'!$G$3:$G$464,A12,'PUNCH LIST'!$Q$3:$Q$464,"Open"))) | N12: =IF($A12="","",IF(ISBLANK(F12),"",IF(TRIM(F12)="--","--",IF(ISNUMBER(F12),IF(F12>=1,"Yes",IF(F12=0,"No","PARTIAL")),"CHECK")))) | O12: =IF($A12="","",IF(ISBLANK(G12),"",IF(TRIM(G12)="--","--",IF(ISNUMBER(G12),IF(G12>=1,"Yes",IF(G12=0,"No","PARTIAL")),"CHECK")))) | P12: =IF($A12="","",IF(ISBLANK(H12),"",IF(TRIM(H12)="--","--",IF(ISNUMBER(H12),IF(H12>=1,"Yes",IF(H12=0,"No","PARTIAL")),"CHECK")))) | Q12: =IF($A12="","",IF(ISBLANK(I12),"",IF(TRIM(I12)="--","--",IF(ISNUMBER(I12),IF(I12>=1,"Yes",IF(I12=0,"No","PARTIAL")),"CHECK")))) | R12: =IF($A12="","",IF(ISBLANK(J12),"",IF(TRIM(J12)="--","--",IF(ISNUMBER(J12),IF(J12>=1,"Yes",IF(J12=0,"No","PARTIAL")),"CHECK")))) | S12: =IF($A12="","",IF(ISBLANK(K12),"",IF(TRIM(K12)="--","--",IF(ISNUMBER(K12),IF(K12>=1,"Yes",IF(K12=0,"No","PARTIAL")),"CHECK")))) | V12: =IF($A12="","",IF(COUNTIF(N12:S12,"--")=6,"--",IF(COUNTIF(N12:S12,"Yes")+COUNTIF(N12:S12,"--")=6,"Yes","No"))) | Z12: =IF($A12="","",COUNTIFS('RFI REGISTER'!$D$5:$D$250,$A12,'RFI REGISTER'!$A$5:$A$250,"RFI-*",'RFI REGISTER'!$C$5:$C$250,"<>Closed",'RFI REGISTER'!$C$5:$C$250,"<>Cancelled")) | AA12: =IF($A12="","",COUNTIFS(ISSUES!$P$5:$P$200,"*"&$A12&"*",ISSUES!$H$5:$H$200,"<>Closed",ISSUES!$H$5:$H$200,"<>Resolved",ISSUES!$H$5:$H$200,"<>Cancelled",ISSUES!$H$5:$H$200,"<>",ISSUES!$A$5:$A$200,"<>")) | AC12: =IF(A12="","",IF(COUNTIF('WORK PACKAGES'!$A$2:$A$100,A12)=0,"NOT IN WORK PACKAGES",IF(COUNTIF($A$2:$A$100,A12)>1,"DUPLICATE","OK")))
B13: =IF($A13="","",IFERROR(IF(INDEX('WORK PACKAGES'!$B$2:$B$100,MATCH($A13,'WORK PACKAGES'!$A$2:$A$100,0))="","",INDEX('WORK PACKAGES'!$B$2:$B$100,MATCH($A13,'WORK PACKAGES'!$A$2:$A$100,0))),"")) | C13: =IF($A13="","",IFERROR(IF(INDEX('WORK PACKAGES'!$G$2:$G$100,MATCH($A13,'WORK PACKAGES'!$A$2:$A$100,0))="","",INDEX('WORK PACKAGES'!$G$2:$G$100,MATCH($A13,'WORK PACKAGES'!$A$2:$A$100,0))),"")) | D13: =IF($A13="","",IFERROR(IF(INDEX('WORK PACKAGES'!$E$2:$E$100,MATCH($A13,'WORK PACKAGES'!$A$2:$A$100,0))="","",INDEX('WORK PACKAGES'!$E$2:$E$100,MATCH($A13,'WORK PACKAGES'!$A$2:$A$100,0))),"")) | E13: =IF(A13="","",IF(COUNTIFS('PUNCH LIST'!$G$3:$G$464,A13,'PUNCH LIST'!$Q$3:$Q$464,"Open")=0,"",COUNTIFS('PUNCH LIST'!$G$3:$G$464,A13,'PUNCH LIST'!$Q$3:$Q$464,"Open"))) | N13: =IF($A13="","",IF(ISBLANK(F13),"",IF(TRIM(F13)="--","--",IF(ISNUMBER(F13),IF(F13>=1,"Yes",IF(F13=0,"No","PARTIAL")),"CHECK")))) | O13: =IF($A13="","",IF(ISBLANK(G13),"",IF(TRIM(G13)="--","--",IF(ISNUMBER(G13),IF(G13>=1,"Yes",IF(G13=0,"No","PARTIAL")),"CHECK")))) | P13: =IF($A13="","",IF(ISBLANK(H13),"",IF(TRIM(H13)="--","--",IF(ISNUMBER(H13),IF(H13>=1,"Yes",IF(H13=0,"No","PARTIAL")),"CHECK")))) | Q13: =IF($A13="","",IF(ISBLANK(I13),"",IF(TRIM(I13)="--","--",IF(ISNUMBER(I13),IF(I13>=1,"Yes",IF(I13=0,"No","PARTIAL")),"CHECK")))) | R13: =IF($A13="","",IF(ISBLANK(J13),"",IF(TRIM(J13)="--","--",IF(ISNUMBER(J13),IF(J13>=1,"Yes",IF(J13=0,"No","PARTIAL")),"CHECK")))) | S13: =IF($A13="","",IF(ISBLANK(K13),"",IF(TRIM(K13)="--","--",IF(ISNUMBER(K13),IF(K13>=1,"Yes",IF(K13=0,"No","PARTIAL")),"CHECK")))) | V13: =IF($A13="","",IF(COUNTIF(N13:S13,"--")=6,"--",IF(COUNTIF(N13:S13,"Yes")+COUNTIF(N13:S13,"--")=6,"Yes","No"))) | Z13: =IF($A13="","",COUNTIFS('RFI REGISTER'!$D$5:$D$250,$A13,'RFI REGISTER'!$A$5:$A$250,"RFI-*",'RFI REGISTER'!$C$5:$C$250,"<>Closed",'RFI REGISTER'!$C$5:$C$250,"<>Cancelled")) | AA13: =IF($A13="","",COUNTIFS(ISSUES!$P$5:$P$200,"*"&$A13&"*",ISSUES!$H$5:$H$200,"<>Closed",ISSUES!$H$5:$H$200,"<>Resolved",ISSUES!$H$5:$H$200,"<>Cancelled",ISSUES!$H$5:$H$200,"<>",ISSUES!$A$5:$A$200,"<>")) | AC13: =IF(A13="","",IF(COUNTIF('WORK PACKAGES'!$A$2:$A$100,A13)=0,"NOT IN WORK PACKAGES",IF(COUNTIF($A$2:$A$100,A13)>1,"DUPLICATE","OK")))
... B100: =IF($A100="","",IFERROR(IF(INDEX('WORK PACKAGES'!$B$2:$B$100,MATCH($A100,'WORK PACKAGES'!$A$2:$A$100,0))="","",INDEX('WORK PACKAGES'!$B$2:$B$100,MATCH($A100,'WORK PACKAGES'!$A$2:$A$100,0))),"")) | C100: =IF($A100="","",IFERROR(IF(INDEX('WORK PACKAGES'!$G$2:$G$100,MATCH($A100,'WORK PACKAGES'!$A$2:$A$100,0))="","",INDEX('WORK PACKAGES'!$G$2:$G$100,MATCH($A100,'WORK PACKAGES'!$A$2:$A$100,0))),"")) | D100: =IF($A100="","",IFERROR(IF(INDEX('WORK PACKAGES'!$E$2:$E$100,MATCH($A100,'WORK PACKAGES'!$A$2:$A$100,0))="","",INDEX('WORK PACKAGES'!$E$2:$E$100,MATCH($A100,'WORK PACKAGES'!$A$2:$A$100,0))),"")) | E100: =IF(A100="","",IF(COUNTIFS('PUNCH LIST'!$G$3:$G$464,A100,'PUNCH LIST'!$Q$3:$Q$464,"Open")=0,"",COUNTIFS('PUNCH LIST'!$G$3:$G$464,A100,'PUNCH LIST'!$Q$3:$Q$464,"Open"))) | N100: =IF($A100="","",IF(ISBLANK(F100),"",IF(TRIM(F100)="--","--",IF(ISNUMBER(F100),IF(F100>=1,"Yes",IF(F100=0,"No","PARTIAL")),"CHECK")))) | O100: =IF($A100="","",IF(ISBLANK(G100),"",IF(TRIM(G100)="--","--",IF(ISNUMBER(G100),IF(G100>=1,"Yes",IF(G100=0,"No","PARTIAL")),"CHECK")))) | P100: =IF($A100="","",IF(ISBLANK(H100),"",IF(TRIM(H100)="--","--",IF(ISNUMBER(H100),IF(H100>=1,"Yes",IF(H100=0,"No","PARTIAL")),"CHECK")))) | Q100: =IF($A100="","",IF(ISBLANK(I100),"",IF(TRIM(I100)="--","--",IF(ISNUMBER(I100),IF(I100>=1,"Yes",IF(I100=0,"No","PARTIAL")),"CHECK")))) | R100: =IF($A100="","",IF(ISBLANK(J100),"",IF(TRIM(J100)="--","--",IF(ISNUMBER(J100),IF(J100>=1,"Yes",IF(J100=0,"No","PARTIAL")),"CHECK")))) | S100: =IF($A100="","",IF(ISBLANK(K100),"",IF(TRIM(K100)="--","--",IF(ISNUMBER(K100),IF(K100>=1,"Yes",IF(K100=0,"No","PARTIAL")),"CHECK")))) | V100: =IF($A100="","",IF(COUNTIF(N100:S100,"--")=6,"--",IF(COUNTIF(N100:S100,"Yes")+COUNTIF(N100:S100,"--")=6,"Yes","No"))) | Z100: =IF($A100="","",COUNTIFS('RFI REGISTER'!$D$5:$D$250,$A100,'RFI REGISTER'!$A$5:$A$250,"RFI-*",'RFI REGISTER'!$C$5:$C$250,"<>Closed",'RFI REGISTER'!$C$5:$C$250,"<>Cancelled")) | AA100: =IF($A100="","",COUNTIFS(ISSUES!$P$5:$P$200,"*"&$A100&"*",ISSUES!$H$5:$H$200,"<>Closed",ISSUES!$H$5:$H$200,"<>Resolved",ISSUES!$H$5:$H$200,"<>Cancelled",ISSUES!$H$5:$H$200,"<>",ISSUES!$A$5:$A$200,"<>")) | AC100: =IF(A100="","",IF(COUNTIF('WORK PACKAGES'!$A$2:$A$100,A100)=0,"NOT IN WORK PACKAGES",IF(COUNTIF($A$2:$A$100,A100)>1,"DUPLICATE","OK")))

Sheet BLOCKED ITEMS REPORT
A1: PM / PE BLOCKED ITEMS REVIEW
A2: Filter the Record ID column to nonblanks. Each X flag is independent; report does not set or clear flags.
A4: Register | B4: Record ID | C4: Scope ID | D4: Work Package ID(s) | E4: Description / Question / Task | F4: Owner | G4: Status | H4: Blocked (X)
A5: =IF('WP PROGRESS'!$Y$2="X","WP PROGRESS","") | B5: =IF('WP PROGRESS'!$Y$2="X",'WP PROGRESS'!A2,"") | C5: =IF('WP PROGRESS'!$Y$2="X",'WP PROGRESS'!C2,"") | D5: =IF('WP PROGRESS'!$Y$2="X",'WP PROGRESS'!A2,"") | E5: =IF('WP PROGRESS'!$Y$2="X",IFERROR(INDEX('WORK PACKAGES'!$C$2:$C$100,MATCH('WP PROGRESS'!A2,'WORK PACKAGES'!$A$2:$A$100,0)),""),"") | H5: =IF('WP PROGRESS'!$Y$2="X","X","")
A6: =IF('WP PROGRESS'!$Y$3="X","WP PROGRESS","") | B6: =IF('WP PROGRESS'!$Y$3="X",'WP PROGRESS'!A3,"") | C6: =IF('WP PROGRESS'!$Y$3="X",'WP PROGRESS'!C3,"") | D6: =IF('WP PROGRESS'!$Y$3="X",'WP PROGRESS'!A3,"") | E6: =IF('WP PROGRESS'!$Y$3="X",IFERROR(INDEX('WORK PACKAGES'!$C$2:$C$100,MATCH('WP PROGRESS'!A3,'WORK PACKAGES'!$A$2:$A$100,0)),""),"") | H6: =IF('WP PROGRESS'!$Y$3="X","X","")
A7: =IF('WP PROGRESS'!$Y$4="X","WP PROGRESS","") | B7: =IF('WP PROGRESS'!$Y$4="X",'WP PROGRESS'!A4,"") | C7: =IF('WP PROGRESS'!$Y$4="X",'WP PROGRESS'!C4,"") | D7: =IF('WP PROGRESS'!$Y$4="X",'WP PROGRESS'!A4,"") | E7: =IF('WP PROGRESS'!$Y$4="X",IFERROR(INDEX('WORK PACKAGES'!$C$2:$C$100,MATCH('WP PROGRESS'!A4,'WORK PACKAGES'!$A$2:$A$100,0)),""),"") | H7: =IF('WP PROGRESS'!$Y$4="X","X","")
A8: =IF('WP PROGRESS'!$Y$5="X","WP PROGRESS","") | B8: =IF('WP PROGRESS'!$Y$5="X",'WP PROGRESS'!A5,"") | C8: =IF('WP PROGRESS'!$Y$5="X",'WP PROGRESS'!C5,"") | D8: =IF('WP PROGRESS'!$Y$5="X",'WP PROGRESS'!A5,"") | E8: =IF('WP PROGRESS'!$Y$5="X",IFERROR(INDEX('WORK PACKAGES'!$C$2:$C$100,MATCH('WP PROGRESS'!A5,'WORK PACKAGES'!$A$2:$A$100,0)),""),"") | H8: =IF('WP PROGRESS'!$Y$5="X","X","")
A9: =IF('WP PROGRESS'!$Y$6="X","WP PROGRESS","") | B9: =IF('WP PROGRESS'!$Y$6="X",'WP PROGRESS'!A6,"") | C9: =IF('WP PROGRESS'!$Y$6="X",'WP PROGRESS'!C6,"") | D9: =IF('WP PROGRESS'!$Y$6="X",'WP PROGRESS'!A6,"") | E9: =IF('WP PROGRESS'!$Y$6="X",IFERROR(INDEX('WORK PACKAGES'!$C$2:$C$100,MATCH('WP PROGRESS'!A6,'WORK PACKAGES'!$A$2:$A$100,0)),""),"") | H9: =IF('WP PROGRESS'!$Y$6="X","X","")
A10: =IF('WP PROGRESS'!$Y$7="X","WP PROGRESS","") | B10: =IF('WP PROGRESS'!$Y$7="X",'WP PROGRESS'!A7,"") | C10: =IF('WP PROGRESS'!$Y$7="X",'WP PROGRESS'!C7,"") | D10: =IF('WP PROGRESS'!$Y$7="X",'WP PROGRESS'!A7,"") | E10: =IF('WP PROGRESS'!$Y$7="X",IFERROR(INDEX('WORK PACKAGES'!$C$2:$C$100,MATCH('WP PROGRESS'!A7,'WORK PACKAGES'!$A$2:$A$100,0)),""),"") | H10: =IF('WP PROGRESS'!$Y$7="X","X","")
A11: =IF('WP PROGRESS'!$Y$8="X","WP PROGRESS","") | B11: =IF('WP PROGRESS'!$Y$8="X",'WP PROGRESS'!A8,"") | C11: =IF('WP PROGRESS'!$Y$8="X",'WP PROGRESS'!C8,"") | D11: =IF('WP PROGRESS'!$Y$8="X",'WP PROGRESS'!A8,"") | E11: =IF('WP PROGRESS'!$Y$8="X",IFERROR(INDEX('WORK PACKAGES'!$C$2:$C$100,MATCH('WP PROGRESS'!A8,'WORK PACKAGES'!$A$2:$A$100,0)),""),"") | H11: =IF('WP PROGRESS'!$Y$8="X","X","")
A12: =IF('WP PROGRESS'!$Y$9="X","WP PROGRESS","") | B12: =IF('WP PROGRESS'!$Y$9="X",'WP PROGRESS'!A9,"") | C12: =IF('WP PROGRESS'!$Y$9="X",'WP PROGRESS'!C9,"") | D12: =IF('WP PROGRESS'!$Y$9="X",'WP PROGRESS'!A9,"") | E12: =IF('WP PROGRESS'!$Y$9="X",IFERROR(INDEX('WORK PACKAGES'!$C$2:$C$100,MATCH('WP PROGRESS'!A9,'WORK PACKAGES'!$A$2:$A$100,0)),""),"") | H12: =IF('WP PROGRESS'!$Y$9="X","X","")
A13: =IF('WP PROGRESS'!$Y$10="X","WP PROGRESS","") | B13: =IF('WP PROGRESS'!$Y$10="X",'WP PROGRESS'!A10,"") | C13: =IF('WP PROGRESS'!$Y$10="X",'WP PROGRESS'!C10,"") | D13: =IF('WP PROGRESS'!$Y$10="X",'WP PROGRESS'!A10,"") | E13: =IF('WP PROGRESS'!$Y$10="X",IFERROR(INDEX('WORK PACKAGES'!$C$2:$C$100,MATCH('WP PROGRESS'!A10,'WORK PACKAGES'!$A$2:$A$100,0)),""),"") | H13: =IF('WP PROGRESS'!$Y$10="X","X","")
A14: =IF('WP PROGRESS'!$Y$11="X","WP PROGRESS","") | B14: =IF('WP PROGRESS'!$Y$11="X",'WP PROGRESS'!A11,"") | C14: =IF('WP PROGRESS'!$Y$11="X",'WP PROGRESS'!C11,"") | D14: =IF('WP PROGRESS'!$Y$11="X",'WP PROGRESS'!A11,"") | E14: =IF('WP PROGRESS'!$Y$11="X",IFERROR(INDEX('WORK PACKAGES'!$C$2:$C$100,MATCH('WP PROGRESS'!A11,'WORK PACKAGES'!$A$2:$A$100,0)),""),"") | H14: =IF('WP PROGRESS'!$Y$11="X","X","")
A15: =IF('WP PROGRESS'!$Y$12="X","WP PROGRESS","") | B15: =IF('WP PROGRESS'!$Y$12="X",'WP PROGRESS'!A12,"") | C15: =IF('WP PROGRESS'!$Y$12="X",'WP PROGRESS'!C12,"") | D15: =IF('WP PROGRESS'!$Y$12="X",'WP PROGRESS'!A12,"") | E15: =IF('WP PROGRESS'!$Y$12="X",IFERROR(INDEX('WORK PACKAGES'!$C$2:$C$100,MATCH('WP PROGRESS'!A12,'WORK PACKAGES'!$A$2:$A$100,0)),""),"") | H15: =IF('WP PROGRESS'!$Y$12="X","X","")
A16: =IF('WP PROGRESS'!$Y$13="X","WP PROGRESS","") | B16: =IF('WP PROGRESS'!$Y$13="X",'WP PROGRESS'!A13,"") | C16: =IF('WP PROGRESS'!$Y$13="X",'WP PROGRESS'!C13,"") | D16: =IF('WP PROGRESS'!$Y$13="X",'WP PROGRESS'!A13,"") | E16: =IF('WP PROGRESS'!$Y$13="X",IFERROR(INDEX('WORK PACKAGES'!$C$2:$C$100,MATCH('WP PROGRESS'!A13,'WORK PACKAGES'!$A$2:$A$100,0)),""),"") | H16: =IF('WP PROGRESS'!$Y$13="X","X","")
A17: =IF('WP PROGRESS'!$Y$14="X","WP PROGRESS","") | B17: =IF('WP PROGRESS'!$Y$14="X",'WP PROGRESS'!A14,"") | C17: =IF('WP PROGRESS'!$Y$14="X",'WP PROGRESS'!C14,"") | D17: =IF('WP PROGRESS'!$Y$14="X",'WP PROGRESS'!A14,"") | E17: =IF('WP PROGRESS'!$Y$14="X",IFERROR(INDEX('WORK PACKAGES'!$C$2:$C$100,MATCH('WP PROGRESS'!A14,'WORK PACKAGES'!$A$2:$A$100,0)),""),"") | H17: =IF('WP PROGRESS'!$Y$14="X","X","")
A18: =IF('WP PROGRESS'!$Y$15="X","WP PROGRESS","") | B18: =IF('WP PROGRESS'!$Y$15="X",'WP PROGRESS'!A15,"") | C18: =IF('WP PROGRESS'!$Y$15="X",'WP PROGRESS'!C15,"") | D18: =IF('WP PROGRESS'!$Y$15="X",'WP PROGRESS'!A15,"") | E18: =IF('WP PROGRESS'!$Y$15="X",IFERROR(INDEX('WORK PACKAGES'!$C$2:$C$100,MATCH('WP PROGRESS'!A15,'WORK PACKAGES'!$A$2:$A$100,0)),""),"") | H18: =IF('WP PROGRESS'!$Y$15="X","X","")
A19: =IF('WP PROGRESS'!$Y$16="X","WP PROGRESS","") | B19: =IF('WP PROGRESS'!$Y$16="X",'WP PROGRESS'!A16,"") | C19: =IF('WP PROGRESS'!$Y$16="X",'WP PROGRESS'!C16,"") | D19: =IF('WP PROGRESS'!$Y$16="X",'WP PROGRESS'!A16,"") | E19: =IF('WP PROGRESS'!$Y$16="X",IFERROR(INDEX('WORK PACKAGES'!$C$2:$C$100,MATCH('WP PROGRESS'!A16,'WORK PACKAGES'!$A$2:$A$100,0)),""),"") | H19: =IF('WP PROGRESS'!$Y$16="X","X","")
A20: =IF('WP PROGRESS'!$Y$17="X","WP PROGRESS","") | B20: =IF('WP PROGRESS'!$Y$17="X",'WP PROGRESS'!A17,"") | C20: =IF('WP PROGRESS'!$Y$17="X",'WP PROGRESS'!C17,"") | D20: =IF('WP PROGRESS'!$Y$17="X",'WP PROGRESS'!A17,"") | E20: =IF('WP PROGRESS'!$Y$17="X",IFERROR(INDEX('WORK PACKAGES'!$C$2:$C$100,MATCH('WP PROGRESS'!A17,'WORK PACKAGES'!$A$2:$A$100,0)),""),"") | H20: =IF('WP PROGRESS'!$Y$17="X","X","")
A21: =IF('WP PROGRESS'!$Y$18="X","WP PROGRESS","") | B21: =IF('WP PROGRESS'!$Y$18="X",'WP PROGRESS'!A18,"") | C21: =IF('WP PROGRESS'!$Y$18="X",'WP PROGRESS'!C18,"") | D21: =IF('WP PROGRESS'!$Y$18="X",'WP PROGRESS'!A18,"") | E21: =IF('WP PROGRESS'!$Y$18="X",IFERROR(INDEX('WORK PACKAGES'!$C$2:$C$100,MATCH('WP PROGRESS'!A18,'WORK PACKAGES'!$A$2:$A$100,0)),""),"") | H21: =IF('WP PROGRESS'!$Y$18="X","X","")
A22: =IF('WP PROGRESS'!$Y$19="X","WP PROGRESS","") | B22: =IF('WP PROGRESS'!$Y$19="X",'WP PROGRESS'!A19,"") | C22: =IF('WP PROGRESS'!$Y$19="X",'WP PROGRESS'!C19,"") | D22: =IF('WP PROGRESS'!$Y$19="X",'WP PROGRESS'!A19,"") | E22: =IF('WP PROGRESS'!$Y$19="X",IFERROR(INDEX('WORK PACKAGES'!$C$2:$C$100,MATCH('WP PROGRESS'!A19,'WORK PACKAGES'!$A$2:$A$100,0)),""),"") | H22: =IF('WP PROGRESS'!$Y$19="X","X","")
A23: =IF('WP PROGRESS'!$Y$20="X","WP PROGRESS","") | B23: =IF('WP PROGRESS'!$Y$20="X",'WP PROGRESS'!A20,"") | C23: =IF('WP PROGRESS'!$Y$20="X",'WP PROGRESS'!C20,"") | D23: =IF('WP PROGRESS'!$Y$20="X",'WP PROGRESS'!A20,"") | E23: =IF('WP PROGRESS'!$Y$20="X",IFERROR(INDEX('WORK PACKAGES'!$C$2:$C$100,MATCH('WP PROGRESS'!A20,'WORK PACKAGES'!$A$2:$A$100,0)),""),"") | H23: =IF('WP PROGRESS'!$Y$20="X","X","")
A24: =IF('WP PROGRESS'!$Y$21="X","WP PROGRESS","") | B24: =IF('WP PROGRESS'!$Y$21="X",'WP PROGRESS'!A21,"") | C24: =IF('WP PROGRESS'!$Y$21="X",'WP PROGRESS'!C21,"") | D24: =IF('WP PROGRESS'!$Y$21="X",'WP PROGRESS'!A21,"") | E24: =IF('WP PROGRESS'!$Y$21="X",IFERROR(INDEX('WORK PACKAGES'!$C$2:$C$100,MATCH('WP PROGRESS'!A21,'WORK PACKAGES'!$A$2:$A$100,0)),""),"") | H24: =IF('WP PROGRESS'!$Y$21="X","X","")
A25: =IF('WP PROGRESS'!$Y$22="X","WP PROGRESS","") | B25: =IF('WP PROGRESS'!$Y$22="X",'WP PROGRESS'!A22,"") | C25: =IF('WP PROGRESS'!$Y$22="X",'WP PROGRESS'!C22,"") | D25: =IF('WP PROGRESS'!$Y$22="X",'WP PROGRESS'!A22,"") | E25: =IF('WP PROGRESS'!$Y$22="X",IFERROR(INDEX('WORK PACKAGES'!$C$2:$C$100,MATCH('WP PROGRESS'!A22,'WORK PACKAGES'!$A$2:$A$100,0)),""),"") | H25: =IF('WP PROGRESS'!$Y$22="X","X","")
A26: =IF('WP PROGRESS'!$Y$23="X","WP PROGRESS","") | B26: =IF('WP PROGRESS'!$Y$23="X",'WP PROGRESS'!A23,"") | C26: =IF('WP PROGRESS'!$Y$23="X",'WP PROGRESS'!C23,"") | D26: =IF('WP PROGRESS'!$Y$23="X",'WP PROGRESS'!A23,"") | E26: =IF('WP PROGRESS'!$Y$23="X",IFERROR(INDEX('WORK PACKAGES'!$C$2:$C$100,MATCH('WP PROGRESS'!A23,'WORK PACKAGES'!$A$2:$A$100,0)),""),"") | H26: =IF('WP PROGRESS'!$Y$23="X","X","")
A27: =IF('WP PROGRESS'!$Y$24="X","WP PROGRESS","") | B27: =IF('WP PROGRESS'!$Y$24="X",'WP PROGRESS'!A24,"") | C27: =IF('WP PROGRESS'!$Y$24="X",'WP PROGRESS'!C24,"") | D27: =IF('WP PROGRESS'!$Y$24="X",'WP PROGRESS'!A24,"") | E27: =IF('WP PROGRESS'!$Y$24="X",IFERROR(INDEX('WORK PACKAGES'!$C$2:$C$100,MATCH('WP PROGRESS'!A24,'WORK PACKAGES'!$A$2:$A$100,0)),""),"") | H27: =IF('WP PROGRESS'!$Y$24="X","X","")
A28: =IF('WP PROGRESS'!$Y$25="X","WP PROGRESS","") | B28: =IF('WP PROGRESS'!$Y$25="X",'WP PROGRESS'!A25,"") | C28: =IF('WP PROGRESS'!$Y$25="X",'WP PROGRESS'!C25,"") | D28: =IF('WP PROGRESS'!$Y$25="X",'WP PROGRESS'!A25,"") | E28: =IF('WP PROGRESS'!$Y$25="X",IFERROR(INDEX('WORK PACKAGES'!$C$2:$C$100,MATCH('WP PROGRESS'!A25,'WORK PACKAGES'!$A$2:$A$100,0)),""),"") | H28: =IF('WP PROGRESS'!$Y$25="X","X","")
A29: =IF('WP PROGRESS'!$Y$26="X","WP PROGRESS","") | B29: =IF('WP PROGRESS'!$Y$26="X",'WP PROGRESS'!A26,"") | C29: =IF('WP PROGRESS'!$Y$26="X",'WP PROGRESS'!C26,"") | D29: =IF('WP PROGRESS'!$Y$26="X",'WP PROGRESS'!A26,"") | E29: =IF('WP PROGRESS'!$Y$26="X",IFERROR(INDEX('WORK PACKAGES'!$C$2:$C$100,MATCH('WP PROGRESS'!A26,'WORK PACKAGES'!$A$2:$A$100,0)),""),"") | H29: =IF('WP PROGRESS'!$Y$26="X","X","")
A30: =IF('WP PROGRESS'!$Y$27="X","WP PROGRESS","") | B30: =IF('WP PROGRESS'!$Y$27="X",'WP PROGRESS'!A27,"") | C30: =IF('WP PROGRESS'!$Y$27="X",'WP PROGRESS'!C27,"") | D30: =IF('WP PROGRESS'!$Y$27="X",'WP PROGRESS'!A27,"") | E30: =IF('WP PROGRESS'!$Y$27="X",IFERROR(INDEX('WORK PACKAGES'!$C$2:$C$100,MATCH('WP PROGRESS'!A27,'WORK PACKAGES'!$A$2:$A$100,0)),""),"") | H30: =IF('WP PROGRESS'!$Y$27="X","X","")
A31: =IF('WP PROGRESS'!$Y$28="X","WP PROGRESS","") | B31: =IF('WP PROGRESS'!$Y$28="X",'WP PROGRESS'!A28,"") | C31: =IF('WP PROGRESS'!$Y$28="X",'WP PROGRESS'!C28,"") | D31: =IF('WP PROGRESS'!$Y$28="X",'WP PROGRESS'!A28,"") | E31: =IF('WP PROGRESS'!$Y$28="X",IFERROR(INDEX('WORK PACKAGES'!$C$2:$C$100,MATCH('WP PROGRESS'!A28,'WORK PACKAGES'!$A$2:$A$100,0)),""),"") | H31: =IF('WP PROGRESS'!$Y$28="X","X","")
A32: =IF('WP PROGRESS'!$Y$29="X","WP PROGRESS","") | B32: =IF('WP PROGRESS'!$Y$29="X",'WP PROGRESS'!A29,"") | C32: =IF('WP PROGRESS'!$Y$29="X",'WP PROGRESS'!C29,"") | D32: =IF('WP PROGRESS'!$Y$29="X",'WP PROGRESS'!A29,"") | E32: =IF('WP PROGRESS'!$Y$29="X",IFERROR(INDEX('WORK PACKAGES'!$C$2:$C$100,MATCH('WP PROGRESS'!A29,'WORK PACKAGES'!$A$2:$A$100,0)),""),"") | H32: =IF('WP PROGRESS'!$Y$29="X","X","")
A33: =IF('WP PROGRESS'!$Y$30="X","WP PROGRESS","") | B33: =IF('WP PROGRESS'!$Y$30="X",'WP PROGRESS'!A30,"") | C33: =IF('WP PROGRESS'!$Y$30="X",'WP PROGRESS'!C30,"") | D33: =IF('WP PROGRESS'!$Y$30="X",'WP PROGRESS'!A30,"") | E33: =IF('WP PROGRESS'!$Y$30="X",IFERROR(INDEX('WORK PACKAGES'!$C$2:$C$100,MATCH('WP PROGRESS'!A30,'WORK PACKAGES'!$A$2:$A$100,0)),""),"") | H33: =IF('WP PROGRESS'!$Y$30="X","X","")
A34: =IF('WP PROGRESS'!$Y$31="X","WP PROGRESS","") | B34: =IF('WP PROGRESS'!$Y$31="X",'WP PROGRESS'!A31,"") | C34: =IF('WP PROGRESS'!$Y$31="X",'WP PROGRESS'!C31,"") | D34: =IF('WP PROGRESS'!$Y$31="X",'WP PROGRESS'!A31,"") | E34: =IF('WP PROGRESS'!$Y$31="X",IFERROR(INDEX('WORK PACKAGES'!$C$2:$C$100,MATCH('WP PROGRESS'!A31,'WORK PACKAGES'!$A$2:$A$100,0)),""),"") | H34: =IF('WP PROGRESS'!$Y$31="X","X","")
A35: =IF('WP PROGRESS'!$Y$32="X","WP PROGRESS","") | B35: =IF('WP PROGRESS'!$Y$32="X",'WP PROGRESS'!A32,"") | C35: =IF('WP PROGRESS'!$Y$32="X",'WP PROGRESS'!C32,"") | D35: =IF('WP PROGRESS'!$Y$32="X",'WP PROGRESS'!A32,"") | E35: =IF('WP PROGRESS'!$Y$32="X",IFERROR(INDEX('WORK PACKAGES'!$C$2:$C$100,MATCH('WP PROGRESS'!A32,'WORK PACKAGES'!$A$2:$A$100,0)),""),"") | H35: =IF('WP PROGRESS'!$Y$32="X","X","")
A36: =IF('WP PROGRESS'!$Y$33="X","WP PROGRESS","") | B36: =IF('WP PROGRESS'!$Y$33="X",'WP PROGRESS'!A33,"") | C36: =IF('WP PROGRESS'!$Y$33="X",'WP PROGRESS'!C33,"") | D36: =IF('WP PROGRESS'!$Y$33="X",'WP PROGRESS'!A33,"") | E36: =IF('WP PROGRESS'!$Y$33="X",IFERROR(INDEX('WORK PACKAGES'!$C$2:$C$100,MATCH('WP PROGRESS'!A33,'WORK PACKAGES'!$A$2:$A$100,0)),""),"") | H36: =IF('WP PROGRESS'!$Y$33="X","X","")
A37: =IF('WP PROGRESS'!$Y$34="X","WP PROGRESS","") | B37: =IF('WP PROGRESS'!$Y$34="X",'WP PROGRESS'!A34,"") | C37: =IF('WP PROGRESS'!$Y$34="X",'WP PROGRESS'!C34,"") | D37: =IF('WP PROGRESS'!$Y$34="X",'WP PROGRESS'!A34,"") | E37: =IF('WP PROGRESS'!$Y$34="X",IFERROR(INDEX('WORK PACKAGES'!$C$2:$C$100,MATCH('WP PROGRESS'!A34,'WORK PACKAGES'!$A$2:$A$100,0)),""),"") | H37: =IF('WP PROGRESS'!$Y$34="X","X","")
A38: =IF('WP PROGRESS'!$Y$35="X","WP PROGRESS","") | B38: =IF('WP PROGRESS'!$Y$35="X",'WP PROGRESS'!A35,"") | C38: =IF('WP PROGRESS'!$Y$35="X",'WP PROGRESS'!C35,"") | D38: =IF('WP PROGRESS'!$Y$35="X",'WP PROGRESS'!A35,"") | E38: =IF('WP PROGRESS'!$Y$35="X",IFERROR(INDEX('WORK PACKAGES'!$C$2:$C$100,MATCH('WP PROGRESS'!A35,'WORK PACKAGES'!$A$2:$A$100,0)),""),"") | H38: =IF('WP PROGRESS'!$Y$35="X","X","")
A39: =IF('WP PROGRESS'!$Y$36="X","WP PROGRESS","") | B39: =IF('WP PROGRESS'!$Y$36="X",'WP PROGRESS'!A36,"") | C39: =IF('WP PROGRESS'!$Y$36="X",'WP PROGRESS'!C36,"") | D39: =IF('WP PROGRESS'!$Y$36="X",'WP PROGRESS'!A36,"") | E39: =IF('WP PROGRESS'!$Y$36="X",IFERROR(INDEX('WORK PACKAGES'!$C$2:$C$100,MATCH('WP PROGRESS'!A36,'WORK PACKAGES'!$A$2:$A$100,0)),""),"") | H39: =IF('WP PROGRESS'!$Y$36="X","X","")
A40: =IF('WP PROGRESS'!$Y$37="X","WP PROGRESS","") | B40: =IF('WP PROGRESS'!$Y$37="X",'WP PROGRESS'!A37,"") | C40: =IF('WP PROGRESS'!$Y$37="X",'WP PROGRESS'!C37,"") | D40: =IF('WP PROGRESS'!$Y$37="X",'WP PROGRESS'!A37,"") | E40: =IF('WP PROGRESS'!$Y$37="X",IFERROR(INDEX('WORK PACKAGES'!$C$2:$C$100,MATCH('WP PROGRESS'!A37,'WORK PACKAGES'!$A$2:$A$100,0)),""),"") | H40: =IF('WP PROGRESS'!$Y$37="X","X","")
A41: =IF('WP PROGRESS'!$Y$38="X","WP PROGRESS","") | B41: =IF('WP PROGRESS'!$Y$38="X",'WP PROGRESS'!A38,"") | C41: =IF('WP PROGRESS'!$Y$38="X",'WP PROGRESS'!C38,"") | D41: =IF('WP PROGRESS'!$Y$38="X",'WP PROGRESS'!A38,"") | E41: =IF('WP PROGRESS'!$Y$38="X",IFERROR(INDEX('WORK PACKAGES'!$C$2:$C$100,MATCH('WP PROGRESS'!A38,'WORK PACKAGES'!$A$2:$A$100,0)),""),"") | H41: =IF('WP PROGRESS'!$Y$38="X","X","")
A42: =IF('WP PROGRESS'!$Y$39="X","WP PROGRESS","") | B42: =IF('WP PROGRESS'!$Y$39="X",'WP PROGRESS'!A39,"") | C42: =IF('WP PROGRESS'!$Y$39="X",'WP PROGRESS'!C39,"") | D42: =IF('WP PROGRESS'!$Y$39="X",'WP PROGRESS'!A39,"") | E42: =IF('WP PROGRESS'!$Y$39="X",IFERROR(INDEX('WORK PACKAGES'!$C$2:$C$100,MATCH('WP PROGRESS'!A39,'WORK PACKAGES'!$A$2:$A$100,0)),""),"") | H42: =IF('WP PROGRESS'!$Y$39="X","X","")
A43: =IF('WP PROGRESS'!$Y$40="X","WP PROGRESS","") | B43: =IF('WP PROGRESS'!$Y$40="X",'WP PROGRESS'!A40,"") | C43: =IF('WP PROGRESS'!$Y$40="X",'WP PROGRESS'!C40,"") | D43: =IF('WP PROGRESS'!$Y$40="X",'WP PROGRESS'!A40,"") | E43: =IF('WP PROGRESS'!$Y$40="X",IFERROR(INDEX('WORK PACKAGES'!$C$2:$C$100,MATCH('WP PROGRESS'!A40,'WORK PACKAGES'!$A$2:$A$100,0)),""),"") | H43: =IF('WP PROGRESS'!$Y$40="X","X","")
A44: =IF('WP PROGRESS'!$Y$41="X","WP PROGRESS","") | B44: =IF('WP PROGRESS'!$Y$41="X",'WP PROGRESS'!A41,"") | C44: =IF('WP PROGRESS'!$Y$41="X",'WP PROGRESS'!C41,"") | D44: =IF('WP PROGRESS'!$Y$41="X",'WP PROGRESS'!A41,"") | E44: =IF('WP PROGRESS'!$Y$41="X",IFERROR(INDEX('WORK PACKAGES'!$C$2:$C$100,MATCH('WP PROGRESS'!A41,'WORK PACKAGES'!$A$2:$A$100,0)),""),"") | H44: =IF('WP PROGRESS'!$Y$41="X","X","")
A45: =IF('WP PROGRESS'!$Y$42="X","WP PROGRESS","") | B45: =IF('WP PROGRESS'!$Y$42="X",'WP PROGRESS'!A42,"") | C45: =IF('WP PROGRESS'!$Y$42="X",'WP PROGRESS'!C42,"") | D45: =IF('WP PROGRESS'!$Y$42="X",'WP PROGRESS'!A42,"") | E45: =IF('WP PROGRESS'!$Y$42="X",IFERROR(INDEX('WORK PACKAGES'!$C$2:$C$100,MATCH('WP PROGRESS'!A42,'WORK PACKAGES'!$A$2:$A$100,0)),""),"") | H45: =IF('WP PROGRESS'!$Y$42="X","X","")
A46: =IF('WP PROGRESS'!$Y$43="X","WP PROGRESS","") | B46: =IF('WP PROGRESS'!$Y$43="X",'WP PROGRESS'!A43,"") | C46: =IF('WP PROGRESS'!$Y$43="X",'WP PROGRESS'!C43,"") | D46: =IF('WP PROGRESS'!$Y$43="X",'WP PROGRESS'!A43,"") | E46: =IF('WP PROGRESS'!$Y$43="X",IFERROR(INDEX('WORK PACKAGES'!$C$2:$C$100,MATCH('WP PROGRESS'!A43,'WORK PACKAGES'!$A$2:$A$100,0)),""),"") | H46: =IF('WP PROGRESS'!$Y$43="X","X","")
A47: =IF('WP PROGRESS'!$Y$44="X","WP PROGRESS","") | B47: =IF('WP PROGRESS'!$Y$44="X",'WP PROGRESS'!A44,"") | C47: =IF('WP PROGRESS'!$Y$44="X",'WP PROGRESS'!C44,"") | D47: =IF('WP PROGRESS'!$Y$44="X",'WP PROGRESS'!A44,"") | E47: =IF('WP PROGRESS'!$Y$44="X",IFERROR(INDEX('WORK PACKAGES'!$C$2:$C$100,MATCH('WP PROGRESS'!A44,'WORK PACKAGES'!$A$2:$A$100,0)),""),"") | H47: =IF('WP PROGRESS'!$Y$44="X","X","")
A48: =IF('WP PROGRESS'!$Y$45="X","WP PROGRESS","") | B48: =IF('WP PROGRESS'!$Y$45="X",'WP PROGRESS'!A45,"") | C48: =IF('WP PROGRESS'!$Y$45="X",'WP PROGRESS'!C45,"") | D48: =IF('WP PROGRESS'!$Y$45="X",'WP PROGRESS'!A45,"") | E48: =IF('WP PROGRESS'!$Y$45="X",IFERROR(INDEX('WORK PACKAGES'!$C$2:$C$100,MATCH('WP PROGRESS'!A45,'WORK PACKAGES'!$A$2:$A$100,0)),""),"") | H48: =IF('WP PROGRESS'!$Y$45="X","X","")
A49: =IF('WP PROGRESS'!$Y$46="X","WP PROGRESS","") | B49: =IF('WP PROGRESS'!$Y$46="X",'WP PROGRESS'!A46,"") | C49: =IF('WP PROGRESS'!$Y$46="X",'WP PROGRESS'!C46,"") | D49: =IF('WP PROGRESS'!$Y$46="X",'WP PROGRESS'!A46,"") | E49: =IF('WP PROGRESS'!$Y$46="X",IFERROR(INDEX('WORK PACKAGES'!$C$2:$C$100,MATCH('WP PROGRESS'!A46,'WORK PACKAGES'!$A$2:$A$100,0)),""),"") | H49: =IF('WP PROGRESS'!$Y$46="X","X","")
A50: =IF('WP PROGRESS'!$Y$47="X","WP PROGRESS","") | B50: =IF('WP PROGRESS'!$Y$47="X",'WP PROGRESS'!A47,"") | C50: =IF('WP PROGRESS'!$Y$47="X",'WP PROGRESS'!C47,"") | D50: =IF('WP PROGRESS'!$Y$47="X",'WP PROGRESS'!A47,"") | E50: =IF('WP PROGRESS'!$Y$47="X",IFERROR(INDEX('WORK PACKAGES'!$C$2:$C$100,MATCH('WP PROGRESS'!A47,'WORK PACKAGES'!$A$2:$A$100,0)),""),"") | H50: =IF('WP PROGRESS'!$Y$47="X","X","")
A51: =IF('WP PROGRESS'!$Y$48="X","WP PROGRESS","") | B51: =IF('WP PROGRESS'!$Y$48="X",'WP PROGRESS'!A48,"") | C51: =IF('WP PROGRESS'!$Y$48="X",'WP PROGRESS'!C48,"") | D51: =IF('WP PROGRESS'!$Y$48="X",'WP PROGRESS'!A48,"") | E51: =IF('WP PROGRESS'!$Y$48="X",IFERROR(INDEX('WORK PACKAGES'!$C$2:$C$100,MATCH('WP PROGRESS'!A48,'WORK PACKAGES'!$A$2:$A$100,0)),""),"") | H51: =IF('WP PROGRESS'!$Y$48="X","X","")
A52: =IF('WP PROGRESS'!$Y$49="X","WP PROGRESS","") | B52: =IF('WP PROGRESS'!$Y$49="X",'WP PROGRESS'!A49,"") | C52: =IF('WP PROGRESS'!$Y$49="X",'WP PROGRESS'!C49,"") | D52: =IF('WP PROGRESS'!$Y$49="X",'WP PROGRESS'!A49,"") | E52: =IF('WP PROGRESS'!$Y$49="X",IFERROR(INDEX('WORK PACKAGES'!$C$2:$C$100,MATCH('WP PROGRESS'!A49,'WORK PACKAGES'!$A$2:$A$100,0)),""),"") | H52: =IF('WP PROGRESS'!$Y$49="X","X","")
A53: =IF('WP PROGRESS'!$Y$50="X","WP PROGRESS","") | B53: =IF('WP PROGRESS'!$Y$50="X",'WP PROGRESS'!A50,"") | C53: =IF('WP PROGRESS'!$Y$50="X",'WP PROGRESS'!C50,"") | D53: =IF('WP PROGRESS'!$Y$50="X",'WP PROGRESS'!A50,"") | E53: =IF('WP PROGRESS'!$Y$50="X",IFERROR(INDEX('WORK PACKAGES'!$C$2:$C$100,MATCH('WP PROGRESS'!A50,'WORK PACKAGES'!$A$2:$A$100,0)),""),"") | H53: =IF('WP PROGRESS'!$Y$50="X","X","")
A54: =IF('WP PROGRESS'!$Y$51="X","WP PROGRESS","") | B54: =IF('WP PROGRESS'!$Y$51="X",'WP PROGRESS'!A51,"") | C54: =IF('WP PROGRESS'!$Y$51="X",'WP PROGRESS'!C51,"") | D54: =IF('WP PROGRESS'!$Y$51="X",'WP PROGRESS'!A51,"") | E54: =IF('WP PROGRESS'!$Y$51="X",IFERROR(INDEX('WORK PACKAGES'!$C$2:$C$100,MATCH('WP PROGRESS'!A51,'WORK PACKAGES'!$A$2:$A$100,0)),""),"") | H54: =IF('WP PROGRESS'!$Y$51="X","X","")
A55: =IF('WP PROGRESS'!$Y$52="X","WP PROGRESS","") | B55: =IF('WP PROGRESS'!$Y$52="X",'WP PROGRESS'!A52,"") | C55: =IF('WP PROGRESS'!$Y$52="X",'WP PROGRESS'!C52,"") | D55: =IF('WP PROGRESS'!$Y$52="X",'WP PROGRESS'!A52,"") | E55: =IF('WP PROGRESS'!$Y$52="X",IFERROR(INDEX('WORK PACKAGES'!$C$2:$C$100,MATCH('WP PROGRESS'!A52,'WORK PACKAGES'!$A$2:$A$100,0)),""),"") | H55: =IF('WP PROGRESS'!$Y$52="X","X","")
A56: =IF('WP PROGRESS'!$Y$53="X","WP PROGRESS","") | B56: =IF('WP PROGRESS'!$Y$53="X",'WP PROGRESS'!A53,"") | C56: =IF('WP PROGRESS'!$Y$53="X",'WP PROGRESS'!C53,"") | D56: =IF('WP PROGRESS'!$Y$53="X",'WP PROGRESS'!A53,"") | E56: =IF('WP PROGRESS'!$Y$53="X",IFERROR(INDEX('WORK PACKAGES'!$C$2:$C$100,MATCH('WP PROGRESS'!A53,'WORK PACKAGES'!$A$2:$A$100,0)),""),"") | H56: =IF('WP PROGRESS'!$Y$53="X","X","")
A57: =IF('WP PROGRESS'!$Y$54="X","WP PROGRESS","") | B57: =IF('WP PROGRESS'!$Y$54="X",'WP PROGRESS'!A54,"") | C57: =IF('WP PROGRESS'!$Y$54="X",'WP PROGRESS'!C54,"") | D57: =IF('WP PROGRESS'!$Y$54="X",'WP PROGRESS'!A54,"") | E57: =IF('WP PROGRESS'!$Y$54="X",IFERROR(INDEX('WORK PACKAGES'!$C$2:$C$100,MATCH('WP PROGRESS'!A54,'WORK PACKAGES'!$A$2:$A$100,0)),""),"") | H57: =IF('WP PROGRESS'!$Y$54="X","X","")
A58: =IF('WP PROGRESS'!$Y$55="X","WP PROGRESS","") | B58: =IF('WP PROGRESS'!$Y$55="X",'WP PROGRESS'!A55,"") | C58: =IF('WP PROGRESS'!$Y$55="X",'WP PROGRESS'!C55,"") | D58: =IF('WP PROGRESS'!$Y$55="X",'WP PROGRESS'!A55,"") | E58: =IF('WP PROGRESS'!$Y$55="X",IFERROR(INDEX('WORK PACKAGES'!$C$2:$C$100,MATCH('WP PROGRESS'!A55,'WORK PACKAGES'!$A$2:$A$100,0)),""),"") | H58: =IF('WP PROGRESS'!$Y$55="X","X","")
A59: =IF('WP PROGRESS'!$Y$56="X","WP PROGRESS","") | B59: =IF('WP PROGRESS'!$Y$56="X",'WP PROGRESS'!A56,"") | C59: =IF('WP PROGRESS'!$Y$56="X",'WP PROGRESS'!C56,"") | D59: =IF('WP PROGRESS'!$Y$56="X",'WP PROGRESS'!A56,"") | E59: =IF('WP PROGRESS'!$Y$56="X",IFERROR(INDEX('WORK PACKAGES'!$C$2:$C$100,MATCH('WP PROGRESS'!A56,'WORK PACKAGES'!$A$2:$A$100,0)),""),"") | H59: =IF('WP PROGRESS'!$Y$56="X","X","")
A60: =IF('WP PROGRESS'!$Y$57="X","WP PROGRESS","") | B60: =IF('WP PROGRESS'!$Y$57="X",'WP PROGRESS'!A57,"") | C60: =IF('WP PROGRESS'!$Y$57="X",'WP PROGRESS'!C57,"") | D60: =IF('WP PROGRESS'!$Y$57="X",'WP PROGRESS'!A57,"") | E60: =IF('WP PROGRESS'!$Y$57="X",IFERROR(INDEX('WORK PACKAGES'!$C$2:$C$100,MATCH('WP PROGRESS'!A57,'WORK PACKAGES'!$A$2:$A$100,0)),""),"") | H60: =IF('WP PROGRESS'!$Y$57="X","X","")
A61: =IF('WP PROGRESS'!$Y$58="X","WP PROGRESS","") | B61: =IF('WP PROGRESS'!$Y$58="X",'WP PROGRESS'!A58,"") | C61: =IF('WP PROGRESS'!$Y$58="X",'WP PROGRESS'!C58,"") | D61: =IF('WP PROGRESS'!$Y$58="X",'WP PROGRESS'!A58,"") | E61: =IF('WP PROGRESS'!$Y$58="X",IFERROR(INDEX('WORK PACKAGES'!$C$2:$C$100,MATCH('WP PROGRESS'!A58,'WORK PACKAGES'!$A$2:$A$100,0)),""),"") | H61: =IF('WP PROGRESS'!$Y$58="X","X","")
A62: =IF('WP PROGRESS'!$Y$59="X","WP PROGRESS","") | B62: =IF('WP PROGRESS'!$Y$59="X",'WP PROGRESS'!A59,"") | C62: =IF('WP PROGRESS'!$Y$59="X",'WP PROGRESS'!C59,"") | D62: =IF('WP PROGRESS'!$Y$59="X",'WP PROGRESS'!A59,"") | E62: =IF('WP PROGRESS'!$Y$59="X",IFERROR(INDEX('WORK PACKAGES'!$C$2:$C$100,MATCH('WP PROGRESS'!A59,'WORK PACKAGES'!$A$2:$A$100,0)),""),"") | H62: =IF('WP PROGRESS'!$Y$59="X","X","")
A63: =IF('WP PROGRESS'!$Y$60="X","WP PROGRESS","") | B63: =IF('WP PROGRESS'!$Y$60="X",'WP PROGRESS'!A60,"") | C63: =IF('WP PROGRESS'!$Y$60="X",'WP PROGRESS'!C60,"") | D63: =IF('WP PROGRESS'!$Y$60="X",'WP PROGRESS'!A60,"") | E63: =IF('WP PROGRESS'!$Y$60="X",IFERROR(INDEX('WORK PACKAGES'!$C$2:$C$100,MATCH('WP PROGRESS'!A60,'WORK PACKAGES'!$A$2:$A$100,0)),""),"") | H63: =IF('WP PROGRESS'!$Y$60="X","X","")
A64: =IF('WP PROGRESS'!$Y$61="X","WP PROGRESS","") | B64: =IF('WP PROGRESS'!$Y$61="X",'WP PROGRESS'!A61,"") | C64: =IF('WP PROGRESS'!$Y$61="X",'WP PROGRESS'!C61,"") | D64: =IF('WP PROGRESS'!$Y$61="X",'WP PROGRESS'!A61,"") | E64: =IF('WP PROGRESS'!$Y$61="X",IFERROR(INDEX('WORK PACKAGES'!$C$2:$C$100,MATCH('WP PROGRESS'!A61,'WORK PACKAGES'!$A$2:$A$100,0)),""),"") | H64: =IF('WP PROGRESS'!$Y$61="X","X","")
A65: =IF('WP PROGRESS'!$Y$62="X","WP PROGRESS","") | B65: =IF('WP PROGRESS'!$Y$62="X",'WP PROGRESS'!A62,"") | C65: =IF('WP PROGRESS'!$Y$62="X",'WP PROGRESS'!C62,"") | D65: =IF('WP PROGRESS'!$Y$62="X",'WP PROGRESS'!A62,"") | E65: =IF('WP PROGRESS'!$Y$62="X",IFERROR(INDEX('WORK PACKAGES'!$C$2:$C$100,MATCH('WP PROGRESS'!A62,'WORK PACKAGES'!$A$2:$A$100,0)),""),"") | H65: =IF('WP PROGRESS'!$Y$62="X","X","")
A66: =IF('WP PROGRESS'!$Y$63="X","WP PROGRESS","") | B66: =IF('WP PROGRESS'!$Y$63="X",'WP PROGRESS'!A63,"") | C66: =IF('WP PROGRESS'!$Y$63="X",'WP PROGRESS'!C63,"") | D66: =IF('WP PROGRESS'!$Y$63="X",'WP PROGRESS'!A63,"") | E66: =IF('WP PROGRESS'!$Y$63="X",IFERROR(INDEX('WORK PACKAGES'!$C$2:$C$100,MATCH('WP PROGRESS'!A63,'WORK PACKAGES'!$A$2:$A$100,0)),""),"") | H66: =IF('WP PROGRESS'!$Y$63="X","X","")
A67: =IF('WP PROGRESS'!$Y$64="X","WP PROGRESS","") | B67: =IF('WP PROGRESS'!$Y$64="X",'WP PROGRESS'!A64,"") | C67: =IF('WP PROGRESS'!$Y$64="X",'WP PROGRESS'!C64,"") | D67: =IF('WP PROGRESS'!$Y$64="X",'WP PROGRESS'!A64,"") | E67: =IF('WP PROGRESS'!$Y$64="X",IFERROR(INDEX('WORK PACKAGES'!$C$2:$C$100,MATCH('WP PROGRESS'!A64,'WORK PACKAGES'!$A$2:$A$100,0)),""),"") | H67: =IF('WP PROGRESS'!$Y$64="X","X","")
A68: =IF('WP PROGRESS'!$Y$65="X","WP PROGRESS","") | B68: =IF('WP PROGRESS'!$Y$65="X",'WP PROGRESS'!A65,"") | C68: =IF('WP PROGRESS'!$Y$65="X",'WP PROGRESS'!C65,"") | D68: =IF('WP PROGRESS'!$Y$65="X",'WP PROGRESS'!A65,"") | E68: =IF('WP PROGRESS'!$Y$65="X",IFERROR(INDEX('WORK PACKAGES'!$C$2:$C$100,MATCH('WP PROGRESS'!A65,'WORK PACKAGES'!$A$2:$A$100,0)),""),"") | H68: =IF('WP PROGRESS'!$Y$65="X","X","")
A69: =IF('WP PROGRESS'!$Y$66="X","WP PROGRESS","") | B69: =IF('WP PROGRESS'!$Y$66="X",'WP PROGRESS'!A66,"") | C69: =IF('WP PROGRESS'!$Y$66="X",'WP PROGRESS'!C66,"") | D69: =IF('WP PROGRESS'!$Y$66="X",'WP PROGRESS'!A66,"") | E69: =IF('WP PROGRESS'!$Y$66="X",IFERROR(INDEX('WORK PACKAGES'!$C$2:$C$100,MATCH('WP PROGRESS'!A66,'WORK PACKAGES'!$A$2:$A$100,0)),""),"") | H69: =IF('WP PROGRESS'!$Y$66="X","X","")
A70: =IF('WP PROGRESS'!$Y$67="X","WP PROGRESS","") | B70: =IF('WP PROGRESS'!$Y$67="X",'WP PROGRESS'!A67,"") | C70: =IF('WP PROGRESS'!$Y$67="X",'WP PROGRESS'!C67,"") | D70: =IF('WP PROGRESS'!$Y$67="X",'WP PROGRESS'!A67,"") | E70: =IF('WP PROGRESS'!$Y$67="X",IFERROR(INDEX('WORK PACKAGES'!$C$2:$C$100,MATCH('WP PROGRESS'!A67,'WORK PACKAGES'!$A$2:$A$100,0)),""),"") | H70: =IF('WP PROGRESS'!$Y$67="X","X","")
A71: =IF('WP PROGRESS'!$Y$68="X","WP PROGRESS","") | B71: =IF('WP PROGRESS'!$Y$68="X",'WP PROGRESS'!A68,"") | C71: =IF('WP PROGRESS'!$Y$68="X",'WP PROGRESS'!C68,"") | D71: =IF('WP PROGRESS'!$Y$68="X",'WP PROGRESS'!A68,"") | E71: =IF('WP PROGRESS'!$Y$68="X",IFERROR(INDEX('WORK PACKAGES'!$C$2:$C$100,MATCH('WP PROGRESS'!A68,'WORK PACKAGES'!$A$2:$A$100,0)),""),"") | H71: =IF('WP PROGRESS'!$Y$68="X","X","")
A72: =IF('WP PROGRESS'!$Y$69="X","WP PROGRESS","") | B72: =IF('WP PROGRESS'!$Y$69="X",'WP PROGRESS'!A69,"") | C72: =IF('WP PROGRESS'!$Y$69="X",'WP PROGRESS'!C69,"") | D72: =IF('WP PROGRESS'!$Y$69="X",'WP PROGRESS'!A69,"") | E72: =IF('WP PROGRESS'!$Y$69="X",IFERROR(INDEX('WORK PACKAGES'!$C$2:$C$100,MATCH('WP PROGRESS'!A69,'WORK PACKAGES'!$A$2:$A$100,0)),""),"") | H72: =IF('WP PROGRESS'!$Y$69="X","X","")
A73: =IF('WP PROGRESS'!$Y$70="X","WP PROGRESS","") | B73: =IF('WP PROGRESS'!$Y$70="X",'WP PROGRESS'!A70,"") | C73: =IF('WP PROGRESS'!$Y$70="X",'WP PROGRESS'!C70,"") | D73: =IF('WP PROGRESS'!$Y$70="X",'WP PROGRESS'!A70,"") | E73: =IF('WP PROGRESS'!$Y$70="X",IFERROR(INDEX('WORK PACKAGES'!$C$2:$C$100,MATCH('WP PROGRESS'!A70,'WORK PACKAGES'!$A$2:$A$100,0)),""),"") | H73: =IF('WP PROGRESS'!$Y$70="X","X","")
A74: =IF('WP PROGRESS'!$Y$71="X","WP PROGRESS","") | B74: =IF('WP PROGRESS'!$Y$71="X",'WP PROGRESS'!A71,"") | C74: =IF('WP PROGRESS'!$Y$71="X",'WP PROGRESS'!C71,"") | D74: =IF('WP PROGRESS'!$Y$71="X",'WP PROGRESS'!A71,"") | E74: =IF('WP PROGRESS'!$Y$71="X",IFERROR(INDEX('WORK PACKAGES'!$C$2:$C$100,MATCH('WP PROGRESS'!A71,'WORK PACKAGES'!$A$2:$A$100,0)),""),"") | H74: =IF('WP PROGRESS'!$Y$71="X","X","")
A75: =IF('WP PROGRESS'!$Y$72="X","WP PROGRESS","") | B75: =IF('WP PROGRESS'!$Y$72="X",'WP PROGRESS'!A72,"") | C75: =IF('WP PROGRESS'!$Y$72="X",'WP PROGRESS'!C72,"") | D75: =IF('WP PROGRESS'!$Y$72="X",'WP PROGRESS'!A72,"") | E75: =IF('WP PROGRESS'!$Y$72="X",IFERROR(INDEX('WORK PACKAGES'!$C$2:$C$100,MATCH('WP PROGRESS'!A72,'WORK PACKAGES'!$A$2:$A$100,0)),""),"") | H75: =IF('WP PROGRESS'!$Y$72="X","X","")
A76: =IF('WP PROGRESS'!$Y$73="X","WP PROGRESS","") | B76: =IF('WP PROGRESS'!$Y$73="X",'WP PROGRESS'!A73,"") | C76: =IF('WP PROGRESS'!$Y$73="X",'WP PROGRESS'!C73,"") | D76: =IF('WP PROGRESS'!$Y$73="X",'WP PROGRESS'!A73,"") | E76: =IF('WP PROGRESS'!$Y$73="X",IFERROR(INDEX('WORK PACKAGES'!$C$2:$C$100,MATCH('WP PROGRESS'!A73,'WORK PACKAGES'!$A$2:$A$100,0)),""),"") | H76: =IF('WP PROGRESS'!$Y$73="X","X","")
A77: =IF('WP PROGRESS'!$Y$74="X","WP PROGRESS","") | B77: =IF('WP PROGRESS'!$Y$74="X",'WP PROGRESS'!A74,"") | C77: =IF('WP PROGRESS'!$Y$74="X",'WP PROGRESS'!C74,"") | D77: =IF('WP PROGRESS'!$Y$74="X",'WP PROGRESS'!A74,"") | E77: =IF('WP PROGRESS'!$Y$74="X",IFERROR(INDEX('WORK PACKAGES'!$C$2:$C$100,MATCH('WP PROGRESS'!A74,'WORK PACKAGES'!$A$2:$A$100,0)),""),"") | H77: =IF('WP PROGRESS'!$Y$74="X","X","")
A78: =IF('WP PROGRESS'!$Y$75="X","WP PROGRESS","") | B78: =IF('WP PROGRESS'!$Y$75="X",'WP PROGRESS'!A75,"") | C78: =IF('WP PROGRESS'!$Y$75="X",'WP PROGRESS'!C75,"") | D78: =IF('WP PROGRESS'!$Y$75="X",'WP PROGRESS'!A75,"") | E78: =IF('WP PROGRESS'!$Y$75="X",IFERROR(INDEX('WORK PACKAGES'!$C$2:$C$100,MATCH('WP PROGRESS'!A75,'WORK PACKAGES'!$A$2:$A$100,0)),""),"") | H78: =IF('WP PROGRESS'!$Y$75="X","X","")
A79: =IF('WP PROGRESS'!$Y$76="X","WP PROGRESS","") | B79: =IF('WP PROGRESS'!$Y$76="X",'WP PROGRESS'!A76,"") | C79: =IF('WP PROGRESS'!$Y$76="X",'WP PROGRESS'!C76,"") | D79: =IF('WP PROGRESS'!$Y$76="X",'WP PROGRESS'!A76,"") | E79: =IF('WP PROGRESS'!$Y$76="X",IFERROR(INDEX('WORK PACKAGES'!$C$2:$C$100,MATCH('WP PROGRESS'!A76,'WORK PACKAGES'!$A$2:$A$100,0)),""),"") | H79: =IF('WP PROGRESS'!$Y$76="X","X","")
A80: =IF('WP PROGRESS'!$Y$77="X","WP PROGRESS","") | B80: =IF('WP PROGRESS'!$Y$77="X",'WP PROGRESS'!A77,"") | C80: =IF('WP PROGRESS'!$Y$77="X",'WP PROGRESS'!C77,"") | D80: =IF('WP PROGRESS'!$Y$77="X",'WP PROGRESS'!A77,"") | E80: =IF('WP PROGRESS'!$Y$77="X",IFERROR(INDEX('WORK PACKAGES'!$C$2:$C$100,MATCH('WP PROGRESS'!A77,'WORK PACKAGES'!$A$2:$A$100,0)),""),"") | H80: =IF('WP PROGRESS'!$Y$77="X","X","")
A81: =IF('WP PROGRESS'!$Y$78="X","WP PROGRESS","") | B81: =IF('WP PROGRESS'!$Y$78="X",'WP PROGRESS'!A78,"") | C81: =IF('WP PROGRESS'!$Y$78="X",'WP PROGRESS'!C78,"") | D81: =IF('WP PROGRESS'!$Y$78="X",'WP PROGRESS'!A78,"") | E81: =IF('WP PROGRESS'!$Y$78="X",IFERROR(INDEX('WORK PACKAGES'!$C$2:$C$100,MATCH('WP PROGRESS'!A78,'WORK PACKAGES'!$A$2:$A$100,0)),""),"") | H81: =IF('WP PROGRESS'!$Y$78="X","X","")
A82: =IF('WP PROGRESS'!$Y$79="X","WP PROGRESS","") | B82: =IF('WP PROGRESS'!$Y$79="X",'WP PROGRESS'!A79,"") | C82: =IF('WP PROGRESS'!$Y$79="X",'WP PROGRESS'!C79,"") | D82: =IF('WP PROGRESS'!$Y$79="X",'WP PROGRESS'!A79,"") | E82: =IF('WP PROGRESS'!$Y$79="X",IFERROR(INDEX('WORK PACKAGES'!$C$2:$C$100,MATCH('WP PROGRESS'!A79,'WORK PACKAGES'!$A$2:$A$100,0)),""),"") | H82: =IF('WP PROGRESS'!$Y$79="X","X","")
A83: =IF('WP PROGRESS'!$Y$80="X","WP PROGRESS","") | B83: =IF('WP PROGRESS'!$Y$80="X",'WP PROGRESS'!A80,"") | C83: =IF('WP PROGRESS'!$Y$80="X",'WP PROGRESS'!C80,"") | D83: =IF('WP PROGRESS'!$Y$80="X",'WP PROGRESS'!A80,"") | E83: =IF('WP PROGRESS'!$Y$80="X",IFERROR(INDEX('WORK PACKAGES'!$C$2:$C$100,MATCH('WP PROGRESS'!A80,'WORK PACKAGES'!$A$2:$A$100,0)),""),"") | H83: =IF('WP PROGRESS'!$Y$80="X","X","")
A84: =IF('WP PROGRESS'!$Y$81="X","WP PROGRESS","") | B84: =IF('WP PROGRESS'!$Y$81="X",'WP PROGRESS'!A81,"") | C84: =IF('WP PROGRESS'!$Y$81="X",'WP PROGRESS'!C81,"") | D84: =IF('WP PROGRESS'!$Y$81="X",'WP PROGRESS'!A81,"") | E84: =IF('WP PROGRESS'!$Y$81="X",IFERROR(INDEX('WORK PACKAGES'!$C$2:$C$100,MATCH('WP PROGRESS'!A81,'WORK PACKAGES'!$A$2:$A$100,0)),""),"") | H84: =IF('WP PROGRESS'!$Y$81="X","X","")
A85: =IF('WP PROGRESS'!$Y$82="X","WP PROGRESS","") | B85: =IF('WP PROGRESS'!$Y$82="X",'WP PROGRESS'!A82,"") | C85: =IF('WP PROGRESS'!$Y$82="X",'WP PROGRESS'!C82,"") | D85: =IF('WP PROGRESS'!$Y$82="X",'WP PROGRESS'!A82,"") | E85: =IF('WP PROGRESS'!$Y$82="X",IFERROR(INDEX('WORK PACKAGES'!$C$2:$C$100,MATCH('WP PROGRESS'!A82,'WORK PACKAGES'!$A$2:$A$100,0)),""),"") | H85: =IF('WP PROGRESS'!$Y$82="X","X","")
A86: =IF('WP PROGRESS'!$Y$83="X","WP PROGRESS","") | B86: =IF('WP PROGRESS'!$Y$83="X",'WP PROGRESS'!A83,"") | C86: =IF('WP PROGRESS'!$Y$83="X",'WP PROGRESS'!C83,"") | D86: =IF('WP PROGRESS'!$Y$83="X",'WP PROGRESS'!A83,"") | E86: =IF('WP PROGRESS'!$Y$83="X",IFERROR(INDEX('WORK PACKAGES'!$C$2:$C$100,MATCH('WP PROGRESS'!A83,'WORK PACKAGES'!$A$2:$A$100,0)),""),"") | H86: =IF('WP PROGRESS'!$Y$83="X","X","")
A87: =IF('WP PROGRESS'!$Y$84="X","WP PROGRESS","") | B87: =IF('WP PROGRESS'!$Y$84="X",'WP PROGRESS'!A84,"") | C87: =IF('WP PROGRESS'!$Y$84="X",'WP PROGRESS'!C84,"") | D87: =IF('WP PROGRESS'!$Y$84="X",'WP PROGRESS'!A84,"") | E87: =IF('WP PROGRESS'!$Y$84="X",IFERROR(INDEX('WORK PACKAGES'!$C$2:$C$100,MATCH('WP PROGRESS'!A84,'WORK PACKAGES'!$A$2:$A$100,0)),""),"") | H87: =IF('WP PROGRESS'!$Y$84="X","X","")
A88: =IF('WP PROGRESS'!$Y$85="X","WP PROGRESS","") | B88: =IF('WP PROGRESS'!$Y$85="X",'WP PROGRESS'!A85,"") | C88: =IF('WP PROGRESS'!$Y$85="X",'WP PROGRESS'!C85,"") | D88: =IF('WP PROGRESS'!$Y$85="X",'WP PROGRESS'!A85,"") | E88: =IF('WP PROGRESS'!$Y$85="X",IFERROR(INDEX('WORK PACKAGES'!$C$2:$C$100,MATCH('WP PROGRESS'!A85,'WORK PACKAGES'!$A$2:$A$100,0)),""),"") | H88: =IF('WP PROGRESS'!$Y$85="X","X","")
A89: =IF('WP PROGRESS'!$Y$86="X","WP PROGRESS","") | B89: =IF('WP PROGRESS'!$Y$86="X",'WP PROGRESS'!A86,"") | C89: =IF('WP PROGRESS'!$Y$86="X",'WP PROGRESS'!C86,"") | D89: =IF('WP PROGRESS'!$Y$86="X",'WP PROGRESS'!A86,"") | E89: =IF('WP PROGRESS'!$Y$86="X",IFERROR(INDEX('WORK PACKAGES'!$C$2:$C$100,MATCH('WP PROGRESS'!A86,'WORK PACKAGES'!$A$2:$A$100,0)),""),"") | H89: =IF('WP PROGRESS'!$Y$86="X","X","")
A90: =IF('WP PROGRESS'!$Y$87="X","WP PROGRESS","") | B90: =IF('WP PROGRESS'!$Y$87="X",'WP PROGRESS'!A87,"") | C90: =IF('WP PROGRESS'!$Y$87="X",'WP PROGRESS'!C87,"") | D90: =IF('WP PROGRESS'!$Y$87="X",'WP PROGRESS'!A87,"") | E90: =IF('WP PROGRESS'!$Y$87="X",IFERROR(INDEX('WORK PACKAGES'!$C$2:$C$100,MATCH('WP PROGRESS'!A87,'WORK PACKAGES'!$A$2:$A$100,0)),""),"") | H90: =IF('WP PROGRESS'!$Y$87="X","X","")
A91: =IF('WP PROGRESS'!$Y$88="X","WP PROGRESS","") | B91: =IF('WP PROGRESS'!$Y$88="X",'WP PROGRESS'!A88,"") | C91: =IF('WP PROGRESS'!$Y$88="X",'WP PROGRESS'!C88,"") | D91: =IF('WP PROGRESS'!$Y$88="X",'WP PROGRESS'!A88,"") | E91: =IF('WP PROGRESS'!$Y$88="X",IFERROR(INDEX('WORK PACKAGES'!$C$2:$C$100,MATCH('WP PROGRESS'!A88,'WORK PACKAGES'!$A$2:$A$100,0)),""),"") | H91: =IF('WP PROGRESS'!$Y$88="X","X","")
A92: =IF('WP PROGRESS'!$Y$89="X","WP PROGRESS","") | B92: =IF('WP PROGRESS'!$Y$89="X",'WP PROGRESS'!A89,"") | C92: =IF('WP PROGRESS'!$Y$89="X",'WP PROGRESS'!C89,"") | D92: =IF('WP PROGRESS'!$Y$89="X",'WP PROGRESS'!A89,"") | E92: =IF('WP PROGRESS'!$Y$89="X",IFERROR(INDEX('WORK PACKAGES'!$C$2:$C$100,MATCH('WP PROGRESS'!A89,'WORK PACKAGES'!$A$2:$A$100,0)),""),"") | H92: =IF('WP PROGRESS'!$Y$89="X","X","")
A93: =IF('WP PROGRESS'!$Y$90="X","WP PROGRESS","") | B93: =IF('WP PROGRESS'!$Y$90="X",'WP PROGRESS'!A90,"") | C93: =IF('WP PROGRESS'!$Y$90="X",'WP PROGRESS'!C90,"") | D93: =IF('WP PROGRESS'!$Y$90="X",'WP PROGRESS'!A90,"") | E93: =IF('WP PROGRESS'!$Y$90="X",IFERROR(INDEX('WORK PACKAGES'!$C$2:$C$100,MATCH('WP PROGRESS'!A90,'WORK PACKAGES'!$A$2:$A$100,0)),""),"") | H93: =IF('WP PROGRESS'!$Y$90="X","X","")
A94: =IF('WP PROGRESS'!$Y$91="X","WP PROGRESS","") | B94: =IF('WP PROGRESS'!$Y$91="X",'WP PROGRESS'!A91,"") | C94: =IF('WP PROGRESS'!$Y$91="X",'WP PROGRESS'!C91,"") | D94: =IF('WP PROGRESS'!$Y$91="X",'WP PROGRESS'!A91,"") | E94: =IF('WP PROGRESS'!$Y$91="X",IFERROR(INDEX('WORK PACKAGES'!$C$2:$C$100,MATCH('WP PROGRESS'!A91,'WORK PACKAGES'!$A$2:$A$100,0)),""),"") | H94: =IF('WP PROGRESS'!$Y$91="X","X","")
A95: =IF('WP PROGRESS'!$Y$92="X","WP PROGRESS","") | B95: =IF('WP PROGRESS'!$Y$92="X",'WP PROGRESS'!A92,"") | C95: =IF('WP PROGRESS'!$Y$92="X",'WP PROGRESS'!C92,"") | D95: =IF('WP PROGRESS'!$Y$92="X",'WP PROGRESS'!A92,"") | E95: =IF('WP PROGRESS'!$Y$92="X",IFERROR(INDEX('WORK PACKAGES'!$C$2:$C$100,MATCH('WP PROGRESS'!A92,'WORK PACKAGES'!$A$2:$A$100,0)),""),"") | H95: =IF('WP PROGRESS'!$Y$92="X","X","")
A96: =IF('WP PROGRESS'!$Y$93="X","WP PROGRESS","") | B96: =IF('WP PROGRESS'!$Y$93="X",'WP PROGRESS'!A93,"") | C96: =IF('WP PROGRESS'!$Y$93="X",'WP PROGRESS'!C93,"") | D96: =IF('WP PROGRESS'!$Y$93="X",'WP PROGRESS'!A93,"") | E96: =IF('WP PROGRESS'!$Y$93="X",IFERROR(INDEX('WORK PACKAGES'!$C$2:$C$100,MATCH('WP PROGRESS'!A93,'WORK PACKAGES'!$A$2:$A$100,0)),""),"") | H96: =IF('WP PROGRESS'!$Y$93="X","X","")
A97: =IF('WP PROGRESS'!$Y$94="X","WP PROGRESS","") | B97: =IF('WP PROGRESS'!$Y$94="X",'WP PROGRESS'!A94,"") | C97: =IF('WP PROGRESS'!$Y$94="X",'WP PROGRESS'!C94,"") | D97: =IF('WP PROGRESS'!$Y$94="X",'WP PROGRESS'!A94,"") | E97: =IF('WP PROGRESS'!$Y$94="X",IFERROR(INDEX('WORK PACKAGES'!$C$2:$C$100,MATCH('WP PROGRESS'!A94,'WORK PACKAGES'!$A$2:$A$100,0)),""),"") | H97: =IF('WP PROGRESS'!$Y$94="X","X","")
A98: =IF('WP PROGRESS'!$Y$95="X","WP PROGRESS","") | B98: =IF('WP PROGRESS'!$Y$95="X",'WP PROGRESS'!A95,"") | C98: =IF('WP PROGRESS'!$Y$95="X",'WP PROGRESS'!C95,"") | D98: =IF('WP PROGRESS'!$Y$95="X",'WP PROGRESS'!A95,"") | E98: =IF('WP PROGRESS'!$Y$95="X",IFERROR(INDEX('WORK PACKAGES'!$C$2:$C$100,MATCH('WP PROGRESS'!A95,'WORK PACKAGES'!$A$2:$A$100,0)),""),"") | H98: =IF('WP PROGRESS'!$Y$95="X","X","")
A99: =IF('WP PROGRESS'!$Y$96="X","WP PROGRESS","") | B99: =IF('WP PROGRESS'!$Y$96="X",'WP PROGRESS'!A96,"") | C99: =IF('WP PROGRESS'!$Y$96="X",'WP PROGRESS'!C96,"") | D99: =IF('WP PROGRESS'!$Y$96="X",'WP PROGRESS'!A96,"") | E99: =IF('WP PROGRESS'!$Y$96="X",IFERROR(INDEX('WORK PACKAGES'!$C$2:$C$100,MATCH('WP PROGRESS'!A96,'WORK PACKAGES'!$A$2:$A$100,0)),""),"") | H99: =IF('WP PROGRESS'!$Y$96="X","X","")
A100: =IF('WP PROGRESS'!$Y$97="X","WP PROGRESS","") | B100: =IF('WP PROGRESS'!$Y$97="X",'WP PROGRESS'!A97,"") | C100: =IF('WP PROGRESS'!$Y$97="X",'WP PROGRESS'!C97,"") | D100: =IF('WP PROGRESS'!$Y$97="X",'WP PROGRESS'!A97,"") | E100: =IF('WP PROGRESS'!$Y$97="X",IFERROR(INDEX('WORK PACKAGES'!$C$2:$C$100,MATCH('WP PROGRESS'!A97,'WORK PACKAGES'!$A$2:$A$100,0)),""),"") | H100: =IF('WP PROGRESS'!$Y$97="X","X","")
A101: =IF('WP PROGRESS'!$Y$98="X","WP PROGRESS","") | B101: =IF('WP PROGRESS'!$Y$98="X",'WP PROGRESS'!A98,"") | C101: =IF('WP PROGRESS'!$Y$98="X",'WP PROGRESS'!C98,"") | D101: =IF('WP PROGRESS'!$Y$98="X",'WP PROGRESS'!A98,"") | E101: =IF('WP PROGRESS'!$Y$98="X",IFERROR(INDEX('WORK PACKAGES'!$C$2:$C$100,MATCH('WP PROGRESS'!A98,'WORK PACKAGES'!$A$2:$A$100,0)),""),"") | H101: =IF('WP PROGRESS'!$Y$98="X","X","")
...

Sheet SCOPES
A1: SCOPES | Engineering System / Drawing / Logical Scope
A2: Engineering scopes organize multiple Work Packages into a coherent functional system or issued drawing/logic package. Scope members and requirements are traced by ID.
A3: Blue = editable • Green = imported prior work • Orange = needs review • Formulas = read only
A4: Scope ID | B4: Engineering Scope / System Description | C4: Functional / Drawing Boundary | D4: Lead Discipline / Responsible Party | E4: Primary System ID (optional) | F4: Related Work Package IDs (summary) | G4: Disposition | H4: Source / Requirement IDs | I4: Engineering Basis / Authority | J4: Review State | K4: Engineering State | L4: Engineering Progress % (if applicable) | M4: Owner | N4: Target Date | O4: Related IDs | P4: Notes | Q4: Updated | R4: Work Actions

Sheet WORK PACKAGES
A1: Work Package ID | B1: Package Code | C1: Work Boundary Description | D1: Legacy Selector Label (compatibility) | E1: Priority Sequence | F1: Parent Work Package ID (optional) | G1: Primary Scope ID | H1: Additional Scope IDs (optional) | I1: Responsible Team / Person | J1: Method / How | K1: Deliverable | L1: Depends On / Blocked By (IDs) | M1: Progress Columns In Use | N1: Tracking Basis | O1: Supplemental Boundary Notes | P1: Test Procedure Ref (optional) | Q1: Closeout Evidence Ref (optional) | R1: Relationship Review State | S1: Notes | T1: Progress Row Check (derived)
T2: =IF(A2="","",IF(COUNTIF('WP PROGRESS'!$A$2:$A$100,A2)=1,"OK",IF(COUNTIF('WP PROGRESS'!$A$2:$A$100,A2)=0,"NO PROGRESS ROW","DUPLICATE PROGRESS ROWS")))
T3: =IF(A3="","",IF(COUNTIF('WP PROGRESS'!$A$2:$A$100,A3)=1,"OK",IF(COUNTIF('WP PROGRESS'!$A$2:$A$100,A3)=0,"NO PROGRESS ROW","DUPLICATE PROGRESS ROWS")))
T4: =IF(A4="","",IF(COUNTIF('WP PROGRESS'!$A$2:$A$100,A4)=1,"OK",IF(COUNTIF('WP PROGRESS'!$A$2:$A$100,A4)=0,"NO PROGRESS ROW","DUPLICATE PROGRESS ROWS")))
T5: =IF(A5="","",IF(COUNTIF('WP PROGRESS'!$A$2:$A$100,A5)=1,"OK",IF(COUNTIF('WP PROGRESS'!$A$2:$A$100,A5)=0,"NO PROGRESS ROW","DUPLICATE PROGRESS ROWS")))
T6: =IF(A6="","",IF(COUNTIF('WP PROGRESS'!$A$2:$A$100,A6)=1,"OK",IF(COUNTIF('WP PROGRESS'!$A$2:$A$100,A6)=0,"NO PROGRESS ROW","DUPLICATE PROGRESS ROWS")))
T7: =IF(A7="","",IF(COUNTIF('WP PROGRESS'!$A$2:$A$100,A7)=1,"OK",IF(COUNTIF('WP PROGRESS'!$A$2:$A$100,A7)=0,"NO PROGRESS ROW","DUPLICATE PROGRESS ROWS")))
T8: =IF(A8="","",IF(COUNTIF('WP PROGRESS'!$A$2:$A$100,A8)=1,"OK",IF(COUNTIF('WP PROGRESS'!$A$2:$A$100,A8)=0,"NO PROGRESS ROW","DUPLICATE PROGRESS ROWS")))
T9: =IF(A9="","",IF(COUNTIF('WP PROGRESS'!$A$2:$A$100,A9)=1,"OK",IF(COUNTIF('WP PROGRESS'!$A$2:$A$100,A9)=0,"NO PROGRESS ROW","DUPLICATE PROGRESS ROWS")))
T10: =IF(A10="","",IF(COUNTIF('WP PROGRESS'!$A$2:$A$100,A10)=1,"OK",IF(COUNTIF('WP PROGRESS'!$A$2:$A$100,A10)=0,"NO PROGRESS ROW","DUPLICATE PROGRESS ROWS")))
T11: =IF(A11="","",IF(COUNTIF('WP PROGRESS'!$A$2:$A$100,A11)=1,"OK",IF(COUNTIF('WP PROGRESS'!$A$2:$A$100,A11)=0,"NO PROGRESS ROW","DUPLICATE PROGRESS ROWS")))
T12: =IF(A12="","",IF(COUNTIF('WP PROGRESS'!$A$2:$A$100,A12)=1,"OK",IF(COUNTIF('WP PROGRESS'!$A$2:$A$100,A12)=0,"NO PROGRESS ROW","DUPLICATE PROGRESS ROWS")))
T13: =IF(A13="","",IF(COUNTIF('WP PROGRESS'!$A$2:$A$100,A13)=1,"OK",IF(COUNTIF('WP PROGRESS'!$A$2:$A$100,A13)=0,"NO PROGRESS ROW","DUPLICATE PROGRESS ROWS")))
... T100: =IF(A100="","",IF(COUNTIF('WP PROGRESS'!$A$2:$A$100,A100)=1,"OK",IF(COUNTIF('WP PROGRESS'!$A$2:$A$100,A100)=0,"NO PROGRESS ROW","DUPLICATE PROGRESS ROWS")))

Sheet RFI LEGACY
B1: =SUBTOTAL(3,B3:B345) | C1: =SUBTOTAL(3,C3:C345) | D1: =SUBTOTAL(3,D3:D345) | E1: =SUBTOTAL(3,E3:E345) | F1: =SUBTOTAL(3,F3:F345) | H1: =SUBTOTAL(3,H3:H345) | I1: =SUBTOTAL(3,I3:I345) | J1: =SUBTOTAL(3,J3:J345) | K1: =SUBTOTAL(3,K3:K345) | L1: =SUBTOTAL(3,L3:L345) | M1: =SUBTOTAL(3,M3:M345) | N1: =SUBTOTAL(3,N3:N345) | O1: =COUNTIF(O3:O339,"Open")
B2: Punchlist | C2: Description | D2: Discipline | E2: Responsible Party | F2: Work Package | G2: Package Code | H2: Tag ID | I2: DWG # | J2: REF RFI # | K2: Comments | L2: Raised Date | M2: Cleared By | N2: Cleared Date | O2: Open / Close | P2: AGE | Q2: CLEAR TIME | R2: OLDER THAN 4WEEKS | S2: OLDER THAN 6 WEEKS | T2: OLDER THAN 8 WEEKS
G3: =IF($F3="","",INDEX('WORK PACKAGES'!$B$2:$B$47,MATCH($F3,'WORK PACKAGES'!$D$2:$D$47,0))) | P3: =IF(O3="","",IF(O3="Open",TODAY()-L3,"--")) | Q3: =IF(O3="","",IF(O3="Closed",N3-L3,"--"))
B4: =IF(C4="","",B3+1) | G4: =IF($F4="","",INDEX('WORK PACKAGES'!$B$2:$B$47,MATCH($F4,'WORK PACKAGES'!$D$2:$D$47,0))) | P4: =IF(O4="","",IF(O4="Open",TODAY()-L4,"--")) | Q4: =IF(O4="","",IF(O4="Closed",N4-L4,"--"))
B5: =IF(C5="","",B4+1) | G5: =IF($F5="","",INDEX('WORK PACKAGES'!$B$2:$B$47,MATCH($F5,'WORK PACKAGES'!$D$2:$D$47,0))) | P5: =IF(O5="","",IF(O5="Open",TODAY()-L5,"--")) | Q5: =IF(O5="","",IF(O5="Closed",N5-L5,"--"))
B6: =IF(C6="","",B5+1) | G6: =IF($F6="","",INDEX('WORK PACKAGES'!$B$2:$B$47,MATCH($F6,'WORK PACKAGES'!$D$2:$D$47,0))) | P6: =IF(O6="","",IF(O6="Open",TODAY()-L6,"--")) | Q6: =IF(O6="","",IF(O6="Closed",N6-L6,"--"))
B7: =IF(C7="","",B6+1) | G7: =IF($F7="","",INDEX('WORK PACKAGES'!$B$2:$B$47,MATCH($F7,'WORK PACKAGES'!$D$2:$D$47,0))) | P7: =IF(O7="","",IF(O7="Open",TODAY()-L7,"--")) | Q7: =IF(O7="","",IF(O7="Closed",N7-L7,"--"))
B8: =IF(C8="","",B7+1) | G8: =IF($F8="","",INDEX('WORK PACKAGES'!$B$2:$B$47,MATCH($F8,'WORK PACKAGES'!$D$2:$D$47,0))) | P8: =IF(O8="","",IF(O8="Open",TODAY()-L8,"--")) | Q8: =IF(O8="","",IF(O8="Closed",N8-L8,"--"))
B9: =IF(C9="","",B8+1) | G9: =IF($F9="","",INDEX('WORK PACKAGES'!$B$2:$B$47,MATCH($F9,'WORK PACKAGES'!$D$2:$D$47,0))) | P9: =IF(O9="","",IF(O9="Open",TODAY()-L9,"--")) | Q9: =IF(O9="","",IF(O9="Closed",N9-L9,"--"))
B10: =IF(C10="","",B9+1) | G10: =IF($F10="","",INDEX('WORK PACKAGES'!$B$2:$B$47,MATCH($F10,'WORK PACKAGES'!$D$2:$D$47,0))) | P10: =IF(O10="","",IF(O10="Open",TODAY()-L10,"--")) | Q10: =IF(O10="","",IF(O10="Closed",N10-L10,"--"))
B11: =IF(C11="","",B10+1) | G11: =IF($F11="","",INDEX('WORK PACKAGES'!$B$2:$B$47,MATCH($F11,'WORK PACKAGES'!$D$2:$D$47,0))) | P11: =IF(O11="","",IF(O11="Open",TODAY()-L11,"--")) | Q11: =IF(O11="","",IF(O11="Closed",N11-L11,"--"))
B12: =IF(C12="","",B11+1) | G12: =IF($F12="","",INDEX('WORK PACKAGES'!$B$2:$B$47,MATCH($F12,'WORK PACKAGES'!$D$2:$D$47,0))) | P12: =IF(O12="","",IF(O12="Open",TODAY()-L12,"--")) | Q12: =IF(O12="","",IF(O12="Closed",N12-L12,"--"))
B13: =IF(C13="","",B12+1) | G13: =IF($F13="","",INDEX('WORK PACKAGES'!$B$2:$B$47,MATCH($F13,'WORK PACKAGES'!$D$2:$D$47,0))) | P13: =IF(O13="","",IF(O13="Open",TODAY()-L13,"--")) | Q13: =IF(O13="","",IF(O13="Closed",N13-L13,"--"))
B14: =IF(C14="","",B13+1) | G14: =IF($F14="","",INDEX('WORK PACKAGES'!$B$2:$B$47,MATCH($F14,'WORK PACKAGES'!$D$2:$D$47,0))) | P14: =IF(O14="","",IF(O14="Open",TODAY()-L14,"--")) | Q14: =IF(O14="","",IF(O14="Closed",N14-L14,"--"))
B15: =IF(C15="","",B14+1) | G15: =IF($F15="","",INDEX('WORK PACKAGES'!$B$2:$B$47,MATCH($F15,'WORK PACKAGES'!$D$2:$D$47,0))) | P15: =IF(O15="","",IF(O15="Open",TODAY()-L15,"--")) | Q15: =IF(O15="","",IF(O15="Closed",N15-L15,"--"))
... B176: =IF(C176="","",B175+1) | G176: =IF($F176="","",INDEX('WORK PACKAGES'!$B$2:$B$47,MATCH($F176,'WORK PACKAGES'!$D$2:$D$47,0))) | P176: =IF(O176="","",IF(O176="Open",TODAY()-L176,"--")) | Q176: =IF(O176="","",IF(O176="Closed",N176-L176,"--"))
B177: =IF(C177="","",B176+1) | P177: =IF(O177="","",IF(O177="Open",TODAY()-L177,"--")) | Q177: =IF(O177="","",IF(O177="Closed",N177-L177,"--"))
B178: =IF(C178="","",B177+1) | P178: =IF(O178="","",IF(O178="Open",TODAY()-L178,"--")) | Q178: =IF(O178="","",IF(O178="Closed",N178-L178,"--"))
B179: =IF(C179="","",B178+1) | P179: =IF(O179="","",IF(O179="Open",TODAY()-L179,"--")) | Q179: =IF(O179="","",IF(O179="Closed",N179-L179,"--"))
B180: =IF(C180="","",B179+1) | P180: =IF(O180="","",IF(O180="Open",TODAY()-L180,"--")) | Q180: =IF(O180="","",IF(O180="Closed",N180-L180,"--"))
B181: =IF(C181="","",B180+1) | P181: =IF(O181="","",IF(O181="Open",TODAY()-L181,"--")) | Q181: =IF(O181="","",IF(O181="Closed",N181-L181,"--"))
B182: =IF(C182="","",B181+1) | P182: =IF(O182="","",IF(O182="Open",TODAY()-L182,"--")) | Q182: =IF(O182="","",IF(O182="Closed",N182-L182,"--"))
B183: =IF(C183="","",B182+1) | P183: =IF(O183="","",IF(O183="Open",TODAY()-L183,"--")) | Q183: =IF(O183="","",IF(O183="Closed",N183-L183,"--"))
B184: =IF(C184="","",B183+1) | P184: =IF(O184="","",IF(O184="Open",TODAY()-L184,"--")) | Q184: =IF(O184="","",IF(O184="Closed",N184-L184,"--"))
B185: =IF(C185="","",B184+1) | P185: =IF(O185="","",IF(O185="Open",TODAY()-L185,"--")) | Q185: =IF(O185="","",IF(O185="Closed",N185-L185,"--"))
B186: =IF(C186="","",B185+1) | P186: =IF(O186="","",IF(O186="Open",TODAY()-L186,"--")) | Q186: =IF(O186="","",IF(O186="Closed",N186-L186,"--"))
B187: =IF(C187="","",B186+1) | P187: =IF(O187="","",IF(O187="Open",TODAY()-L187,"--")) | Q187: =IF(O187="","",IF(O187="Closed",N187-L187,"--"))
B188: =IF(C188="","",B187+1) | P188: =IF(O188="","",IF(O188="Open",TODAY()-L188,"--")) | Q188: =IF(O188="","",IF(O188="Closed",N188-L188,"--"))
... B201: =IF(C201="","",B200+1) | P201: =IF(O201="","",IF(O201="Open",TODAY()-L201,"--")) | Q201: =IF(O201="","",IF(O201="Closed",N201-L201,"--"))
P202: =IF(O202="","",IF(O202="Open",TODAY()-L202,"--")) | Q202: =IF(O202="","",IF(O202="Closed",N202-L202,"--"))
B203: =IF(C203="","",B202+1) | P203: =IF(O203="","",IF(O203="Open",TODAY()-L203,"--")) | Q203: =IF(O203="","",IF(O203="Closed",N203-L203,"--"))
B204: =IF(C204="","",B203+1) | P204: =IF(O204="","",IF(O204="Open",TODAY()-L204,"--")) | Q204: =IF(O204="","",IF(O204="Closed",N204-L204,"--"))
B205: =IF(C205="","",B204+1) | P205: =IF(O205="","",IF(O205="Open",TODAY()-L205,"--")) | Q205: =IF(O205="","",IF(O205="Closed",N205-L205,"--"))
B206: =IF(C206="","",B205+1) | P206: =IF(O206="","",IF(O206="Open",TODAY()-L206,"--")) | Q206: =IF(O206="","",IF(O206="Closed",N206-L206,"--"))
B207: =IF(C207="","",B206+1) | P207: =IF(O207="","",IF(O207="Open",TODAY()-L207,"--")) | Q207: =IF(O207="","",IF(O207="Closed",N207-L207,"--"))
B208: =IF(C208="","",B207+1) | P208: =IF(O208="","",IF(O208="Open",TODAY()-L208,"--")) | Q208: =IF(O208="","",IF(O208="Closed",N208-L208,"--"))
B209: =IF(C209="","",B208+1) | P209: =IF(O209="","",IF(O209="Open",TODAY()-L209,"--")) | Q209: =IF(O209="","",IF(O209="Closed",N209-L209,"--"))
B210: =IF(C210="","",B209+1) | P210: =IF(O210="","",IF(O210="Open",TODAY()-L210,"--")) | Q210: =IF(O210="","",IF(O210="Closed",N210-L210,"--"))
B211: =IF(C211="","",B210+1) | P211: =IF(O211="","",IF(O211="Open",TODAY()-L211,"--")) | Q211: =IF(O211="","",IF(O211="Closed",N211-L211,"--"))
B212: =IF(C212="","",B211+1) | P212: =IF(O212="","",IF(O212="Open",TODAY()-L212,"--")) | Q212: =IF(O212="","",IF(O212="Closed",N212-L212,"--"))
B213: =IF(C213="","",B212+1) | P213: =IF(O213="","",IF(O213="Open",TODAY()-L213,"--")) | Q213: =IF(O213="","",IF(O213="Closed",N213-L213,"--"))
B214: =IF(C214="","",B213+1) | P214: =IF(O214="","",IF(O214="Open",TODAY()-L214,"--")) | Q214: =IF(O214="","",IF(O214="Closed",N214-L214,"--"))
... B450: =IF(C450="","",B449+1) | P450: =IF(O450="","",IF(O450="Open",TODAY()-L450,"--")) | Q450: =IF(O450="","",IF(O450="Closed",N450-L450,"--"))
O451: =IF(B451="","",IF(AND(M451="",N451=""),"Open","Closed")) | P451: =IF(O451="","",IF(O451="Open",TODAY()-L451,"--")) | Q451: =IF(O451="","",IF(O451="Closed",N451-L451,"--"))
O452: =IF(B452="","",IF(AND(M452="",N452=""),"Open","Closed")) | P452: =IF(O452="","",IF(O452="Open",TODAY()-L452,"--")) | Q452: =IF(O452="","",IF(O452="Closed",N452-L452,"--"))
O453: =IF(B453="","",IF(AND(M453="",N453=""),"Open","Closed")) | P453: =IF(O453="","",IF(O453="Open",TODAY()-L453,"--")) | Q453: =IF(O453="","",IF(O453="Closed",N453-L453,"--"))
O454: =IF(B454="","",IF(AND(M454="",N454=""),"Open","Closed")) | P454: =IF(O454="","",IF(O454="Open",TODAY()-L454,"--")) | Q454: =IF(O454="","",IF(O454="Closed",N454-L454,"--"))
O455: =IF(B455="","",IF(AND(M455="",N455=""),"Open","Closed")) | P455: =IF(O455="","",IF(O455="Open",TODAY()-L455,"--")) | Q455: =IF(O455="","",IF(O455="Closed",N455-L455,"--"))
O456: =IF(B456="","",IF(AND(M456="",N456=""),"Open","Closed")) | P456: =IF(O456="","",IF(O456="Open",TODAY()-L456,"--")) | Q456: =IF(O456="","",IF(O456="Closed",N456-L456,"--"))
O457: =IF(B457="","",IF(AND(M457="",N457=""),"Open","Closed")) | P457: =IF(O457="","",IF(O457="Open",TODAY()-L457,"--")) | Q457: =IF(O457="","",IF(O457="Closed",N457-L457,"--"))
O458: =IF(B458="","",IF(AND(M458="",N458=""),"Open","Closed")) | P458: =IF(O458="","",IF(O458="Open",TODAY()-L458,"--")) | Q458: =IF(O458="","",IF(O458="Closed",N458-L458,"--"))
O459: =IF(B459="","",IF(AND(M459="",N459=""),"Open","Closed")) | P459: =IF(O459="","",IF(O459="Open",TODAY()-L459,"--")) | Q459: =IF(O459="","",IF(O459="Closed",N459-L459,"--"))
O460: =IF(B460="","",IF(AND(M460="",N460=""),"Open","Closed")) | P460: =IF(O460="","",IF(O460="Open",TODAY()-L460,"--")) | Q460: =IF(O460="","",IF(O460="Closed",N460-L460,"--"))
O461: =IF(B461="","",IF(AND(M461="",N461=""),"Open","Closed")) | P461: =IF(O461="","",IF(O461="Open",TODAY()-L461,"--")) | Q461: =IF(O461="","",IF(O461="Closed",N461-L461,"--"))
O462: =IF(B462="","",IF(AND(M462="",N462=""),"Open","Closed")) | P462: =IF(O462="","",IF(O462="Open",TODAY()-L462,"--")) | Q462: =IF(O462="","",IF(O462="Closed",N462-L462,"--"))
... O464: =IF(B464="","",IF(AND(M464="",N464=""),"Open","Closed")) | P464: =IF(O464="","",IF(O464="Open",TODAY()-L464,"--")) | Q464: =IF(O464="","",IF(O464="Closed",N464-L464,"--"))

Sheet SYSTEM MODEL
A1: SYSTEM MODEL | Functional Systems
A2: True functional System of Interest records (not the operational WORK PACKAGES progress grouping).
A3: Blue = editable • Green = imported prior work • Orange = needs review • Formulas = read only
A4: System ID | B4: Source Code | C4: System Name | D4: System Type | E4: Scope Disposition | F4: Source IDs | G4: Location / Boundary | H4: Review State | I4: Notes

Sheet RFI REGISTER
A1: RFI REGISTER | Authoritative Working RFI Records
A2: Persistent RFI IDs; one row per question. Counts use Primary WP ID to avoid double counting. Historical data requires owner review.
A3: Statuses: Open / Submitted / Answered / Closed / Cancelled; all except Closed and Cancelled count as open. Blank WP remains Unassigned; do not infer.
A4: RFI ID | B4: Question / Clarification Requested | C4: Status | D4: Primary WP ID | E4: Related WP IDs | F4: Related Scope IDs | G4: Source / Document Reference | H4: Responsible Party | I4: Requested By | J4: Date Raised | K4: Required By | L4: Response / Decision | M4: Response Source | N4: Closed Date | O4: Review State | P4: Legacy Reference | Q4: Remarks | R4: Blocked? (X)

Sheet ISSUES
A1: ISSUES | Open Items and Findings
A2: Technical findings / gaps needing engineering disposition; operational unfinished-work tasks stay in PUNCH LIST; formal client questions stay in RFI REGISTER.
A3: Blue = editable • Green = imported prior work • Orange = needs review • Formulas = read only
A4: Item ID | B4: Kind | C4: Statement | D4: Affected IDs | E4: Source IDs | F4: Owner | G4: Resolve By | H4: Status | I4: Priority | J4: Opened Date | K4: Closed Date | L4: Resolution + Source | M4: Legacy Reference | N4: Notes | O4: Primary Scope ID | P4: Affected WP IDs | Q4: Blocked? (X)

Sheet PUNCH LIST
B1: =SUBTOTAL(3,B3:B345) | C1: =SUBTOTAL(3,C3:C345) | D1: =SUBTOTAL(3,D3:D345) | E1: =SUBTOTAL(3,E3:E345) | F1: =SUBTOTAL(3,F3:F345) | I1: =SUBTOTAL(3,I3:I345) | J1: =SUBTOTAL(3,J3:J345) | K1: =SUBTOTAL(3,K3:K345) | L1: =SUBTOTAL(3,L3:L345) | M1: =SUBTOTAL(3,M3:M345) | N1: =SUBTOTAL(3,N3:N345) | O1: =SUBTOTAL(3,O3:O345) | P1: =SUBTOTAL(3,P3:P345) | Q1: =COUNTIF(Q3:Q339,"Open")
B2: Punchlist | C2: Description | D2: Discipline | E2: Responsible Party | F2: Work Package | G2: Package Code (WP ID) | H2: Priority Cat | I2: Tag ID | J2: DWG # | K2: REF RFI # | L2: Comments | M2: Raised By | N2: Raised Date | O2: Cleared By | P2: Cleared Date | Q2: Open / Close | R2: AGE | S2: CLEAR TIME | T2: OLDER THAN 4WEEKS | U2: OLDER THAN 6 WEEKS | V2: OLDER THAN 8 WEEKS | W2: Blocked? (X)
G3: =IF($F3="","",IFERROR(INDEX('WORK PACKAGES'!$A$2:$A$100,MATCH($F3,'WORK PACKAGES'!$D$2:$D$100,0)),"")) | H3: =IF($F3="","",INDEX('WORK PACKAGES'!$E$2:$E$100,MATCH($F3,'WORK PACKAGES'!$D$2:$D$100,0))) | R3: =IF(Q3="","",IF(Q3="Open",TODAY()-N3,"--")) | S3: =IF(Q3="","",IF(Q3="Closed",P3-N3,"--"))
B4: =IF(C4="","",B3+1) | G4: =IF($F4="","",IFERROR(INDEX('WORK PACKAGES'!$A$2:$A$100,MATCH($F4,'WORK PACKAGES'!$D$2:$D$100,0)),"")) | H4: =IF($F4="","",INDEX('WORK PACKAGES'!$E$2:$E$100,MATCH($F4,'WORK PACKAGES'!$D$2:$D$100,0))) | R4: =IF(Q4="","",IF(Q4="Open",TODAY()-N4,"--")) | S4: =IF(Q4="","",IF(Q4="Closed",P4-N4,"--"))
B5: =IF(C5="","",B4+1) | G5: =IF($F5="","",IFERROR(INDEX('WORK PACKAGES'!$A$2:$A$100,MATCH($F5,'WORK PACKAGES'!$D$2:$D$100,0)),"")) | H5: =IF($F5="","",INDEX('WORK PACKAGES'!$E$2:$E$100,MATCH($F5,'WORK PACKAGES'!$D$2:$D$100,0))) | R5: =IF(Q5="","",IF(Q5="Open",TODAY()-N5,"--")) | S5: =IF(Q5="","",IF(Q5="Closed",P5-N5,"--"))
B6: =IF(C6="","",B5+1) | G6: =IF($F6="","",IFERROR(INDEX('WORK PACKAGES'!$A$2:$A$100,MATCH($F6,'WORK PACKAGES'!$D$2:$D$100,0)),"")) | H6: =IF($F6="","",INDEX('WORK PACKAGES'!$E$2:$E$100,MATCH($F6,'WORK PACKAGES'!$D$2:$D$100,0))) | R6: =IF(Q6="","",IF(Q6="Open",TODAY()-N6,"--")) | S6: =IF(Q6="","",IF(Q6="Closed",P6-N6,"--"))
B7: =IF(C7="","",B6+1) | G7: =IF($F7="","",IFERROR(INDEX('WORK PACKAGES'!$A$2:$A$100,MATCH($F7,'WORK PACKAGES'!$D$2:$D$100,0)),"")) | H7: =IF($F7="","",INDEX('WORK PACKAGES'!$E$2:$E$100,MATCH($F7,'WORK PACKAGES'!$D$2:$D$100,0))) | R7: =IF(Q7="","",IF(Q7="Open",TODAY()-N7,"--")) | S7: =IF(Q7="","",IF(Q7="Closed",P7-N7,"--"))
B8: =IF(C8="","",B7+1) | G8: =IF($F8="","",IFERROR(INDEX('WORK PACKAGES'!$A$2:$A$100,MATCH($F8,'WORK PACKAGES'!$D$2:$D$100,0)),"")) | H8: =IF($F8="","",INDEX('WORK PACKAGES'!$E$2:$E$100,MATCH($F8,'WORK PACKAGES'!$D$2:$D$100,0))) | R8: =IF(Q8="","",IF(Q8="Open",TODAY()-N8,"--")) | S8: =IF(Q8="","",IF(Q8="Closed",P8-N8,"--"))
B9: =IF(C9="","",B8+1) | G9: =IF($F9="","",IFERROR(INDEX('WORK PACKAGES'!$A$2:$A$100,MATCH($F9,'WORK PACKAGES'!$D$2:$D$100,0)),"")) | H9: =IF($F9="","",INDEX('WORK PACKAGES'!$E$2:$E$100,MATCH($F9,'WORK PACKAGES'!$D$2:$D$100,0))) | R9: =IF(Q9="","",IF(Q9="Open",TODAY()-N9,"--")) | S9: =IF(Q9="","",IF(Q9="Closed",P9-N9,"--"))
B10: =IF(C10="","",B9+1) | G10: =IF($F10="","",IFERROR(INDEX('WORK PACKAGES'!$A$2:$A$100,MATCH($F10,'WORK PACKAGES'!$D$2:$D$100,0)),"")) | H10: =IF($F10="","",INDEX('WORK PACKAGES'!$E$2:$E$100,MATCH($F10,'WORK PACKAGES'!$D$2:$D$100,0))) | R10: =IF(Q10="","",IF(Q10="Open",TODAY()-N10,"--")) | S10: =IF(Q10="","",IF(Q10="Closed",P10-N10,"--"))
B11: =IF(C11="","",B10+1) | G11: =IF($F11="","",IFERROR(INDEX('WORK PACKAGES'!$A$2:$A$100,MATCH($F11,'WORK PACKAGES'!$D$2:$D$100,0)),"")) | H11: =IF($F11="","",INDEX('WORK PACKAGES'!$E$2:$E$100,MATCH($F11,'WORK PACKAGES'!$D$2:$D$100,0))) | R11: =IF(Q11="","",IF(Q11="Open",TODAY()-N11,"--")) | S11: =IF(Q11="","",IF(Q11="Closed",P11-N11,"--"))
B12: =IF(C12="","",B11+1) | G12: =IF($F12="","",IFERROR(INDEX('WORK PACKAGES'!$A$2:$A$100,MATCH($F12,'WORK PACKAGES'!$D$2:$D$100,0)),"")) | H12: =IF($F12="","",INDEX('WORK PACKAGES'!$E$2:$E$100,MATCH($F12,'WORK PACKAGES'!$D$2:$D$100,0))) | R12: =IF(Q12="","",IF(Q12="Open",TODAY()-N12,"--")) | S12: =IF(Q12="","",IF(Q12="Closed",P12-N12,"--"))
B13: =IF(C13="","",B12+1) | G13: =IF($F13="","",IFERROR(INDEX('WORK PACKAGES'!$A$2:$A$100,MATCH($F13,'WORK PACKAGES'!$D$2:$D$100,0)),"")) | H13: =IF($F13="","",INDEX('WORK PACKAGES'!$E$2:$E$100,MATCH($F13,'WORK PACKAGES'!$D$2:$D$100,0))) | R13: =IF(Q13="","",IF(Q13="Open",TODAY()-N13,"--")) | S13: =IF(Q13="","",IF(Q13="Closed",P13-N13,"--"))
B14: =IF(C14="","",B13+1) | G14: =IF($F14="","",IFERROR(INDEX('WORK PACKAGES'!$A$2:$A$100,MATCH($F14,'WORK PACKAGES'!$D$2:$D$100,0)),"")) | H14: =IF($F14="","",INDEX('WORK PACKAGES'!$E$2:$E$100,MATCH($F14,'WORK PACKAGES'!$D$2:$D$100,0))) | R14: =IF(Q14="","",IF(Q14="Open",TODAY()-N14,"--")) | S14: =IF(Q14="","",IF(Q14="Closed",P14-N14,"--"))
B15: =IF(C15="","",B14+1) | G15: =IF($F15="","",IFERROR(INDEX('WORK PACKAGES'!$A$2:$A$100,MATCH($F15,'WORK PACKAGES'!$D$2:$D$100,0)),"")) | H15: =IF($F15="","",INDEX('WORK PACKAGES'!$E$2:$E$100,MATCH($F15,'WORK PACKAGES'!$D$2:$D$100,0))) | R15: =IF(Q15="","",IF(Q15="Open",TODAY()-N15,"--")) | S15: =IF(Q15="","",IF(Q15="Closed",P15-N15,"--"))
... B176: =IF(C176="","",B175+1) | G176: =IF($F176="","",IFERROR(INDEX('WORK PACKAGES'!$A$2:$A$100,MATCH($F176,'WORK PACKAGES'!$D$2:$D$100,0)),"")) | H176: =IF($F176="","",INDEX('WORK PACKAGES'!$E$2:$E$100,MATCH($F176,'WORK PACKAGES'!$D$2:$D$100,0))) | R176: =IF(Q176="","",IF(Q176="Open",TODAY()-N176,"--")) | S176: =IF(Q176="","",IF(Q176="Closed",P176-N176,"--"))
B177: =IF(C177="","",B176+1) | G177: =IF($F177="","",IFERROR(INDEX('WORK PACKAGES'!$A$2:$A$100,MATCH($F177,'WORK PACKAGES'!$D$2:$D$100,0)),"")) | R177: =IF(Q177="","",IF(Q177="Open",TODAY()-N177,"--")) | S177: =IF(Q177="","",IF(Q177="Closed",P177-N177,"--"))
B178: =IF(C178="","",B177+1) | G178: =IF($F178="","",IFERROR(INDEX('WORK PACKAGES'!$A$2:$A$100,MATCH($F178,'WORK PACKAGES'!$D$2:$D$100,0)),"")) | R178: =IF(Q178="","",IF(Q178="Open",TODAY()-N178,"--")) | S178: =IF(Q178="","",IF(Q178="Closed",P178-N178,"--"))
B179: =IF(C179="","",B178+1) | G179: =IF($F179="","",IFERROR(INDEX('WORK PACKAGES'!$A$2:$A$100,MATCH($F179,'WORK PACKAGES'!$D$2:$D$100,0)),"")) | R179: =IF(Q179="","",IF(Q179="Open",TODAY()-N179,"--")) | S179: =IF(Q179="","",IF(Q179="Closed",P179-N179,"--"))
B180: =IF(C180="","",B179+1) | G180: =IF($F180="","",IFERROR(INDEX('WORK PACKAGES'!$A$2:$A$100,MATCH($F180,'WORK PACKAGES'!$D$2:$D$100,0)),"")) | R180: =IF(Q180="","",IF(Q180="Open",TODAY()-N180,"--")) | S180: =IF(Q180="","",IF(Q180="Closed",P180-N180,"--"))
B181: =IF(C181="","",B180+1) | G181: =IF($F181="","",IFERROR(INDEX('WORK PACKAGES'!$A$2:$A$100,MATCH($F181,'WORK PACKAGES'!$D$2:$D$100,0)),"")) | R181: =IF(Q181="","",IF(Q181="Open",TODAY()-N181,"--")) | S181: =IF(Q181="","",IF(Q181="Closed",P181-N181,"--"))
B182: =IF(C182="","",B181+1) | G182: =IF($F182="","",IFERROR(INDEX('WORK PACKAGES'!$A$2:$A$100,MATCH($F182,'WORK PACKAGES'!$D$2:$D$100,0)),"")) | R182: =IF(Q182="","",IF(Q182="Open",TODAY()-N182,"--")) | S182: =IF(Q182="","",IF(Q182="Closed",P182-N182,"--"))
B183: =IF(C183="","",B182+1) | G183: =IF($F183="","",IFERROR(INDEX('WORK PACKAGES'!$A$2:$A$100,MATCH($F183,'WORK PACKAGES'!$D$2:$D$100,0)),"")) | R183: =IF(Q183="","",IF(Q183="Open",TODAY()-N183,"--")) | S183: =IF(Q183="","",IF(Q183="Closed",P183-N183,"--"))
B184: =IF(C184="","",B183+1) | G184: =IF($F184="","",IFERROR(INDEX('WORK PACKAGES'!$A$2:$A$100,MATCH($F184,'WORK PACKAGES'!$D$2:$D$100,0)),"")) | R184: =IF(Q184="","",IF(Q184="Open",TODAY()-N184,"--")) | S184: =IF(Q184="","",IF(Q184="Closed",P184-N184,"--"))
B185: =IF(C185="","",B184+1) | G185: =IF($F185="","",IFERROR(INDEX('WORK PACKAGES'!$A$2:$A$100,MATCH($F185,'WORK PACKAGES'!$D$2:$D$100,0)),"")) | R185: =IF(Q185="","",IF(Q185="Open",TODAY()-N185,"--")) | S185: =IF(Q185="","",IF(Q185="Closed",P185-N185,"--"))
B186: =IF(C186="","",B185+1) | G186: =IF($F186="","",IFERROR(INDEX('WORK PACKAGES'!$A$2:$A$100,MATCH($F186,'WORK PACKAGES'!$D$2:$D$100,0)),"")) | R186: =IF(Q186="","",IF(Q186="Open",TODAY()-N186,"--")) | S186: =IF(Q186="","",IF(Q186="Closed",P186-N186,"--"))
B187: =IF(C187="","",B186+1) | G187: =IF($F187="","",IFERROR(INDEX('WORK PACKAGES'!$A$2:$A$100,MATCH($F187,'WORK PACKAGES'!$D$2:$D$100,0)),"")) | R187: =IF(Q187="","",IF(Q187="Open",TODAY()-N187,"--")) | S187: =IF(Q187="","",IF(Q187="Closed",P187-N187,"--"))
B188: =IF(C188="","",B187+1) | G188: =IF($F188="","",IFERROR(INDEX('WORK PACKAGES'!$A$2:$A$100,MATCH($F188,'WORK PACKAGES'!$D$2:$D$100,0)),"")) | R188: =IF(Q188="","",IF(Q188="Open",TODAY()-N188,"--")) | S188: =IF(Q188="","",IF(Q188="Closed",P188-N188,"--"))
... B201: =IF(C201="","",B200+1) | G201: =IF($F201="","",IFERROR(INDEX('WORK PACKAGES'!$A$2:$A$100,MATCH($F201,'WORK PACKAGES'!$D$2:$D$100,0)),"")) | R201: =IF(Q201="","",IF(Q201="Open",TODAY()-N201,"--")) | S201: =IF(Q201="","",IF(Q201="Closed",P201-N201,"--"))
G202: =IF($F202="","",IFERROR(INDEX('WORK PACKAGES'!$A$2:$A$100,MATCH($F202,'WORK PACKAGES'!$D$2:$D$100,0)),"")) | R202: =IF(Q202="","",IF(Q202="Open",TODAY()-N202,"--")) | S202: =IF(Q202="","",IF(Q202="Closed",P202-N202,"--"))
B203: =IF(C203="","",B202+1) | G203: =IF($F203="","",IFERROR(INDEX('WORK PACKAGES'!$A$2:$A$100,MATCH($F203,'WORK PACKAGES'!$D$2:$D$100,0)),"")) | R203: =IF(Q203="","",IF(Q203="Open",TODAY()-N203,"--")) | S203: =IF(Q203="","",IF(Q203="Closed",P203-N203,"--"))
B204: =IF(C204="","",B203+1) | G204: =IF($F204="","",IFERROR(INDEX('WORK PACKAGES'!$A$2:$A$100,MATCH($F204,'WORK PACKAGES'!$D$2:$D$100,0)),"")) | R204: =IF(Q204="","",IF(Q204="Open",TODAY()-N204,"--")) | S204: =IF(Q204="","",IF(Q204="Closed",P204-N204,"--"))
B205: =IF(C205="","",B204+1) | G205: =IF($F205="","",IFERROR(INDEX('WORK PACKAGES'!$A$2:$A$100,MATCH($F205,'WORK PACKAGES'!$D$2:$D$100,0)),"")) | R205: =IF(Q205="","",IF(Q205="Open",TODAY()-N205,"--")) | S205: =IF(Q205="","",IF(Q205="Closed",P205-N205,"--"))
B206: =IF(C206="","",B205+1) | G206: =IF($F206="","",IFERROR(INDEX('WORK PACKAGES'!$A$2:$A$100,MATCH($F206,'WORK PACKAGES'!$D$2:$D$100,0)),"")) | R206: =IF(Q206="","",IF(Q206="Open",TODAY()-N206,"--")) | S206: =IF(Q206="","",IF(Q206="Closed",P206-N206,"--"))
B207: =IF(C207="","",B206+1) | G207: =IF($F207="","",IFERROR(INDEX('WORK PACKAGES'!$A$2:$A$100,MATCH($F207,'WORK PACKAGES'!$D$2:$D$100,0)),"")) | R207: =IF(Q207="","",IF(Q207="Open",TODAY()-N207,"--")) | S207: =IF(Q207="","",IF(Q207="Closed",P207-N207,"--"))
B208: =IF(C208="","",B207+1) | G208: =IF($F208="","",IFERROR(INDEX('WORK PACKAGES'!$A$2:$A$100,MATCH($F208,'WORK PACKAGES'!$D$2:$D$100,0)),"")) | R208: =IF(Q208="","",IF(Q208="Open",TODAY()-N208,"--")) | S208: =IF(Q208="","",IF(Q208="Closed",P208-N208,"--"))
B209: =IF(C209="","",B208+1) | G209: =IF($F209="","",IFERROR(INDEX('WORK PACKAGES'!$A$2:$A$100,MATCH($F209,'WORK PACKAGES'!$D$2:$D$100,0)),"")) | R209: =IF(Q209="","",IF(Q209="Open",TODAY()-N209,"--")) | S209: =IF(Q209="","",IF(Q209="Closed",P209-N209,"--"))
B210: =IF(C210="","",B209+1) | G210: =IF($F210="","",IFERROR(INDEX('WORK PACKAGES'!$A$2:$A$100,MATCH($F210,'WORK PACKAGES'!$D$2:$D$100,0)),"")) | R210: =IF(Q210="","",IF(Q210="Open",TODAY()-N210,"--")) | S210: =IF(Q210="","",IF(Q210="Closed",P210-N210,"--"))
B211: =IF(C211="","",B210+1) | G211: =IF($F211="","",IFERROR(INDEX('WORK PACKAGES'!$A$2:$A$100,MATCH($F211,'WORK PACKAGES'!$D$2:$D$100,0)),"")) | R211: =IF(Q211="","",IF(Q211="Open",TODAY()-N211,"--")) | S211: =IF(Q211="","",IF(Q211="Closed",P211-N211,"--"))
B212: =IF(C212="","",B211+1) | G212: =IF($F212="","",IFERROR(INDEX('WORK PACKAGES'!$A$2:$A$100,MATCH($F212,'WORK PACKAGES'!$D$2:$D$100,0)),"")) | R212: =IF(Q212="","",IF(Q212="Open",TODAY()-N212,"--")) | S212: =IF(Q212="","",IF(Q212="Closed",P212-N212,"--"))
B213: =IF(C213="","",B212+1) | G213: =IF($F213="","",IFERROR(INDEX('WORK PACKAGES'!$A$2:$A$100,MATCH($F213,'WORK PACKAGES'!$D$2:$D$100,0)),"")) | R213: =IF(Q213="","",IF(Q213="Open",TODAY()-N213,"--")) | S213: =IF(Q213="","",IF(Q213="Closed",P213-N213,"--"))
B214: =IF(C214="","",B213+1) | G214: =IF($F214="","",IFERROR(INDEX('WORK PACKAGES'!$A$2:$A$100,MATCH($F214,'WORK PACKAGES'!$D$2:$D$100,0)),"")) | R214: =IF(Q214="","",IF(Q214="Open",TODAY()-N214,"--")) | S214: =IF(Q214="","",IF(Q214="Closed",P214-N214,"--"))
... B450: =IF(C450="","",B449+1) | G450: =IF($F450="","",IFERROR(INDEX('WORK PACKAGES'!$A$2:$A$100,MATCH($F450,'WORK PACKAGES'!$D$2:$D$100,0)),"")) | R450: =IF(Q450="","",IF(Q450="Open",TODAY()-N450,"--")) | S450: =IF(Q450="","",IF(Q450="Closed",P450-N450,"--"))
G451: =IF($F451="","",IFERROR(INDEX('WORK PACKAGES'!$A$2:$A$100,MATCH($F451,'WORK PACKAGES'!$D$2:$D$100,0)),"")) | Q451: =IF(B451="","",IF(AND(O451="",P451=""),"Open","Closed")) | R451: =IF(Q451="","",IF(Q451="Open",TODAY()-N451,"--")) | S451: =IF(Q451="","",IF(Q451="Closed",P451-N451,"--"))
G452: =IF($F452="","",IFERROR(INDEX('WORK PACKAGES'!$A$2:$A$100,MATCH($F452,'WORK PACKAGES'!$D$2:$D$100,0)),"")) | Q452: =IF(B452="","",IF(AND(O452="",P452=""),"Open","Closed")) | R452: =IF(Q452="","",IF(Q452="Open",TODAY()-N452,"--")) | S452: =IF(Q452="","",IF(Q452="Closed",P452-N452,"--"))
G453: =IF($F453="","",IFERROR(INDEX('WORK PACKAGES'!$A$2:$A$100,MATCH($F453,'WORK PACKAGES'!$D$2:$D$100,0)),"")) | Q453: =IF(B453="","",IF(AND(O453="",P453=""),"Open","Closed")) | R453: =IF(Q453="","",IF(Q453="Open",TODAY()-N453,"--")) | S453: =IF(Q453="","",IF(Q453="Closed",P453-N453,"--"))
G454: =IF($F454="","",IFERROR(INDEX('WORK PACKAGES'!$A$2:$A$100,MATCH($F454,'WORK PACKAGES'!$D$2:$D$100,0)),"")) | Q454: =IF(B454="","",IF(AND(O454="",P454=""),"Open","Closed")) | R454: =IF(Q454="","",IF(Q454="Open",TODAY()-N454,"--")) | S454: =IF(Q454="","",IF(Q454="Closed",P454-N454,"--"))
G455: =IF($F455="","",IFERROR(INDEX('WORK PACKAGES'!$A$2:$A$100,MATCH($F455,'WORK PACKAGES'!$D$2:$D$100,0)),"")) | Q455: =IF(B455="","",IF(AND(O455="",P455=""),"Open","Closed")) | R455: =IF(Q455="","",IF(Q455="Open",TODAY()-N455,"--")) | S455: =IF(Q455="","",IF(Q455="Closed",P455-N455,"--"))
G456: =IF($F456="","",IFERROR(INDEX('WORK PACKAGES'!$A$2:$A$100,MATCH($F456,'WORK PACKAGES'!$D$2:$D$100,0)),"")) | Q456: =IF(B456="","",IF(AND(O456="",P456=""),"Open","Closed")) | R456: =IF(Q456="","",IF(Q456="Open",TODAY()-N456,"--")) | S456: =IF(Q456="","",IF(Q456="Closed",P456-N456,"--"))
G457: =IF($F457="","",IFERROR(INDEX('WORK PACKAGES'!$A$2:$A$100,MATCH($F457,'WORK PACKAGES'!$D$2:$D$100,0)),"")) | Q457: =IF(B457="","",IF(AND(O457="",P457=""),"Open","Closed")) | R457: =IF(Q457="","",IF(Q457="Open",TODAY()-N457,"--")) | S457: =IF(Q457="","",IF(Q457="Closed",P457-N457,"--"))
G458: =IF($F458="","",IFERROR(INDEX('WORK PACKAGES'!$A$2:$A$100,MATCH($F458,'WORK PACKAGES'!$D$2:$D$100,0)),"")) | Q458: =IF(B458="","",IF(AND(O458="",P458=""),"Open","Closed")) | R458: =IF(Q458="","",IF(Q458="Open",TODAY()-N458,"--")) | S458: =IF(Q458="","",IF(Q458="Closed",P458-N458,"--"))
G459: =IF($F459="","",IFERROR(INDEX('WORK PACKAGES'!$A$2:$A$100,MATCH($F459,'WORK PACKAGES'!$D$2:$D$100,0)),"")) | Q459: =IF(B459="","",IF(AND(O459="",P459=""),"Open","Closed")) | R459: =IF(Q459="","",IF(Q459="Open",TODAY()-N459,"--")) | S459: =IF(Q459="","",IF(Q459="Closed",P459-N459,"--"))
G460: =IF($F460="","",IFERROR(INDEX('WORK PACKAGES'!$A$2:$A$100,MATCH($F460,'WORK PACKAGES'!$D$2:$D$100,0)),"")) | Q460: =IF(B460="","",IF(AND(O460="",P460=""),"Open","Closed")) | R460: =IF(Q460="","",IF(Q460="Open",TODAY()-N460,"--")) | S460: =IF(Q460="","",IF(Q460="Closed",P460-N460,"--"))
G461: =IF($F461="","",IFERROR(INDEX('WORK PACKAGES'!$A$2:$A$100,MATCH($F461,'WORK PACKAGES'!$D$2:$D$100,0)),"")) | Q461: =IF(B461="","",IF(AND(O461="",P461=""),"Open","Closed")) | R461: =IF(Q461="","",IF(Q461="Open",TODAY()-N461,"--")) | S461: =IF(Q461="","",IF(Q461="Closed",P461-N461,"--"))
G462: =IF($F462="","",IFERROR(INDEX('WORK PACKAGES'!$A$2:$A$100,MATCH($F462,'WORK PACKAGES'!$D$2:$D$100,0)),"")) | Q462: =IF(B462="","",IF(AND(O462="",P462=""),"Open","Closed")) | R462: =IF(Q462="","",IF(Q462="Open",TODAY()-N462,"--")) | S462: =IF(Q462="","",IF(Q462="Closed",P462-N462,"--"))
... G464: =IF($F464="","",IFERROR(INDEX('WORK PACKAGES'!$A$2:$A$100,MATCH($F464,'WORK PACKAGES'!$D$2:$D$100,0)),"")) | Q464: =IF(B464="","",IF(AND(O464="",P464=""),"Open","Closed")) | R464: =IF(Q464="","",IF(Q464="Open",TODAY()-N464,"--")) | S464: =IF(Q464="","",IF(Q464="Closed",P464-N464,"--"))

Sheet REGISTRY GUIDE
A1: READ ME | Engineering Record & Work Package Contract
A2: WORK PACKAGES define project execution units (not Systems, Equipment, Scope obligations or SOV items). WP PROGRESS holds entered progress. DASHBOARD, SCOPE DASHBOARD and BLOCKED ITEMS REPORT are derived views.
A3: Blue = editable • Green = imported prior work • Orange = needs review • Formulas = read only
A4: Section | B4: Instruction | C4: Owner / status
A5: Template version | B5: PROJECT_PER v1.1 blank template (KIS controls-engineering). Copy it into authorized project storage, rename it for the project and record that copy in SOURCES / BASELINES. Never enter project data in the repository copy. | C5: Template
A6: Release designation | B6: v1.1 is a STRUCTURE revision of the blank template (work package definition / progress split, '--' progress convention, derived scope progress). It does not approve or accept any project's engineering content. | C6: Owner-accepted structure
A7: Dashboard | B7: DASHBOARD lists WP IDs entered manually in column A. Calculated columns look up WORK PACKAGES (definition) and WP PROGRESS (status); blank progress stays blank. Columns D, J:O and T are manual and travel with the row. | C7: View; formulas read only
A8: Safe sorting | B8: Filter/sort the entire full-width DASHBOARD list (A:U), never a single column. Calculated fields look up by WP ID. | C8: None
A9: Work Package contract | B9: A Work Package is a bounded, independently managed execution unit with progress and completion criteria, normally handed to one team or person. It can span multiple equipment items, scopes or test procedures. | C9: Framework-owned; instance uses WP-###
A10: Work Package definition | B10: WORK PACKAGES owns WP IDs. A:E = WP ID, Package Code, boundary description, hidden legacy selector (D, used by PUNCH LIST / RFI LEGACY forms) and priority. F:S = parent WP, primary and additional scopes, responsible team/person, method, deliverable, dependencies, progress columns in use, tracking basis, references, review state and notes. T checks that the WP has exactly one WP PROGRESS row. | C10: Definition only; no progress here
A11: WP progress | B11: WP PROGRESS has one row per WP ID, chosen from WORK PACKAGES (dropdown uses named range ValidWorkPackageIDs). Enter percentages (0-1), C&E, SAT, vendor checks, Blocked (X) and comments here. Package code, scope, priority, completion, gate and count columns are formulas. | C11: Entered progress
A12: Progress value convention | B12: Number 0-1 = progress. '--' = column not used for this WP (left out of completion, gates and roll-ups). Blank = not entered. Any other text shows CHECK. A WP's gate is complete when every column it uses is complete. | C12: None
A13: Scope progress | B13: SCOPE DASHBOARD derives scope progress per column as the average over WPs whose Primary Scope is that scope (equal weight). Blank and '--' are excluded; enter 0 for 'in use, not started'. WP Count, WPs Gate Complete and Blocked WPs are derived; the scope Blocked? (X) is human-managed. | C13: No SCOPE PROGRESS tab from v1.1
A14: Parent / child WPs | B14: Parent Work Package ID is a definition field only. v1.1 does not roll child progress into parents; parent progress must not double count children. | C14: None
A15: Splitting work packages | B15: Create a separate WP when the work goes to a different team or person, has its own blocking dependency (e.g. equipment by others), or is a deliverable handed off on its own. Do not create WPs per device or point; that detail belongs in the Equipment/Device/Points workbook. | C15: Guidance
... A41: Scope work actions | B41: SCOPES!R Work Actions records what is done in the scope using the M1 action vocabulary: furnish, install, remove, replace, modify, rewire, reprogram, integrate, monitor, test, document, coordinate. Several actions are entered separated by '; ' (the dropdown warns but accepts). Blank means not yet established, not none. | C41: M1 scope extraction

Sheet SOURCES
A1: SOURCES | Source Evidence
A2: Source IDs and exact document issue/revision are required before facts or scope obligations are promoted.
A3: Blue = editable • Green = imported prior work • Orange = needs review • Formulas = read only
A4: Source ID | B4: Document / File | C4: Source Class | D4: Issuer / Authority | E4: Revision | F4: Issue Date | G4: Exact Locator / URL | H4: Received Date | I4: Governs / Topic | J4: Review State | K4: Supersedes ID | L4: Notes

Sheet RECORDS
A1: RECORDS | Engineering Evidence and Requirements
A2: Typed durable Need/Fact/Requirement/Constraint/Criterion/Assumption/Directive/Decision/Finding records.
A3: Blue = editable • Green = imported prior work • Orange = needs review • Formulas = read only
A4: Record ID | B4: Record Type | C4: Atomic Statement | D4: Applies To IDs | E4: Source IDs | F4: Authority / Binding Basis | G4: Applicability | H4: Confidence | I4: Review State | J4: Owner | K4: Resolve By | L4: Related IDs | M4: Verification Method | N4: Supersedes | O4: Updated | P4: Notes

Sheet LINKS
A1: LINKS | Typed Relationships
A2: Typed cross-record links; WorkPackage tracks_scope Scope links connect progress to contractual obligations.
A3: Blue = editable • Green = imported prior work • Orange = needs review • Formulas = read only
A4: Link ID | B4: From Type | C4: From ID | D4: Relationship | E4: To Type | F4: To ID | G4: Source IDs | H4: Review State | I4: Notes | J4: Linked Scope State (derived)
J5: =IF(OR(B5<>"WorkPackage",D5<>"tracks_scope",E5<>"Scope",F5=""),"",IFERROR(INDEX(SCOPES!$K$5:$K$2000,MATCH(F5,SCOPES!$A$5:$A$2000,0)),"UNMATCHED"))
J6: =IF(OR(B6<>"WorkPackage",D6<>"tracks_scope",E6<>"Scope",F6=""),"",IFERROR(INDEX(SCOPES!$K$5:$K$2000,MATCH(F6,SCOPES!$A$5:$A$2000,0)),"UNMATCHED"))
J7: =IF(OR(B7<>"WorkPackage",D7<>"tracks_scope",E7<>"Scope",F7=""),"",IFERROR(INDEX(SCOPES!$K$5:$K$2000,MATCH(F7,SCOPES!$A$5:$A$2000,0)),"UNMATCHED"))
J8: =IF(OR(B8<>"WorkPackage",D8<>"tracks_scope",E8<>"Scope",F8=""),"",IFERROR(INDEX(SCOPES!$K$5:$K$2000,MATCH(F8,SCOPES!$A$5:$A$2000,0)),"UNMATCHED"))
J9: =IF(OR(B9<>"WorkPackage",D9<>"tracks_scope",E9<>"Scope",F9=""),"",IFERROR(INDEX(SCOPES!$K$5:$K$2000,MATCH(F9,SCOPES!$A$5:$A$2000,0)),"UNMATCHED"))
J10: =IF(OR(B10<>"WorkPackage",D10<>"tracks_scope",E10<>"Scope",F10=""),"",IFERROR(INDEX(SCOPES!$K$5:$K$2000,MATCH(F10,SCOPES!$A$5:$A$2000,0)),"UNMATCHED"))
J11: =IF(OR(B11<>"WorkPackage",D11<>"tracks_scope",E11<>"Scope",F11=""),"",IFERROR(INDEX(SCOPES!$K$5:$K$2000,MATCH(F11,SCOPES!$A$5:$A$2000,0)),"UNMATCHED"))
J12: =IF(OR(B12<>"WorkPackage",D12<>"tracks_scope",E12<>"Scope",F12=""),"",IFERROR(INDEX(SCOPES!$K$5:$K$2000,MATCH(F12,SCOPES!$A$5:$A$2000,0)),"UNMATCHED"))
J13: =IF(OR(B13<>"WorkPackage",D13<>"tracks_scope",E13<>"Scope",F13=""),"",IFERROR(INDEX(SCOPES!$K$5:$K$2000,MATCH(F13,SCOPES!$A$5:$A$2000,0)),"UNMATCHED"))
J14: =IF(OR(B14<>"WorkPackage",D14<>"tracks_scope",E14<>"Scope",F14=""),"",IFERROR(INDEX(SCOPES!$K$5:$K$2000,MATCH(F14,SCOPES!$A$5:$A$2000,0)),"UNMATCHED"))
J15: =IF(OR(B15<>"WorkPackage",D15<>"tracks_scope",E15<>"Scope",F15=""),"",IFERROR(INDEX(SCOPES!$K$5:$K$2000,MATCH(F15,SCOPES!$A$5:$A$2000,0)),"UNMATCHED"))
J16: =IF(OR(B16<>"WorkPackage",D16<>"tracks_scope",E16<>"Scope",F16=""),"",IFERROR(INDEX(SCOPES!$K$5:$K$2000,MATCH(F16,SCOPES!$A$5:$A$2000,0)),"UNMATCHED"))
... J2000: =IF(OR(B2000<>"WorkPackage",D2000<>"tracks_scope",E2000<>"Scope",F2000=""),"",IFERROR(INDEX(SCOPES!$K$5:$K$2000,MATCH(F2000,SCOPES!$A$5:$A$2000,0)),"UNMATCHED"))

Sheet CHANGE LOG
A1: CHANGE LOG | Record Revision Events
A2: Persistent change records must be written during an authorized process; this tab does not log edits automatically.
A3: Blue = editable • Green = imported prior work • Orange = needs review • Formulas = read only
A4: Change ID | B4: Timestamp | C4: Object Type | D4: Object ID | E4: Action | F4: Old Rev / Value | G4: New Rev / Value | H4: By / Approved By | I4: Source / Basis | J4: Affected IDs | K4: Notes

Sheet BASELINES
A1: BASELINES | Immutable Snapshots
A2: Register snapshot metadata only. Archive a separate immutable file and manifest; a baseline is not blanket approval.
A3: Blue = editable • Green = imported prior work • Orange = needs review • Formulas = read only
A4: Baseline ID | B4: Milestone | C4: Captured At | D4: Authorized By | E4: Register Revision | F4: Source Manifest | G4: SHA-256 / Hash | H4: Storage Path | I4: Status | J4: Open Items | K4: Notes

Sheet INTAKE QUEUE
A1: INTAKE QUEUE | Legacy Notes and RFIs
A2: Verbatim legacy prior-work content queued for M1/M2 comparison; neither verified nor promoted automatically.
A3: Blue = editable • Green = imported prior work • Orange = needs review • Formulas = read only
A4: Intake ID | B4: Origin Tab | C4: Origin Row | D4: Verbatim Original Text | E4: Legacy Status | F4: Legacy System | G4: Legacy Tag | H4: Legacy Drawing | I4: Legacy Comment | J4: Suggested Kind | K4: Review State | L4: Promoted Record ID | M4: Source ID | N4: Legacy Cell

Sheet WP CHECKS
A1: WP CHECKS
A3: Structure check | B3: Value | C3: Expected | D3: Result
A4: WP IDs defined in WORK PACKAGES | B4: =COUNTA('WORK PACKAGES'!$A$2:$A$100) | D4: =IF(B4=B5,"PASS","FAIL")
A5: WP rows in WP PROGRESS | B5: =COUNTA('WP PROGRESS'!$A$2:$A$100)
A6: WPs with no progress row | B6: =COUNTIF('WORK PACKAGES'!$T$2:$T$100,"NO PROGRESS ROW") | C6: 0 | D6: =IF(B6=C6,"PASS","FAIL")
A7: WPs with duplicate progress rows | B7: =COUNTIF('WORK PACKAGES'!$T$2:$T$100,"DUPLICATE PROGRESS ROWS") | C7: 0 | D7: =IF(B7=C7,"PASS","FAIL")
A8: Progress rows not in WORK PACKAGES | B8: =COUNTIF('WP PROGRESS'!$AC$2:$AC$100,"NOT IN WORK PACKAGES") | C8: 0 | D8: =IF(B8=C8,"PASS","FAIL")
A9: Progress values flagged CHECK | B9: =COUNTIF('WP PROGRESS'!$N$2:$S$100,"CHECK") | C9: 0 | D9: =IF(B9=C9,"PASS","FAIL")
A12: Roll-up test (sample data, not project data)
A13: Sample WP | B13: Scope | C13: Eng % | E13: Scope | F13: Derived Eng % | G13: Expected | H13: Result
A14: S1 | B14: SX | C14: 1 | E14: SX | F14: =IFERROR(AVERAGEIFS($C$14:$C$18,$B$14:$B$18,E14),"") | G14: 0.75 | H14: =IF(ROUND(F14,6)=ROUND(G14,6),"PASS","FAIL")
A15: S2 | B15: SX | C15: 0.5 | E15: SY | F15: =IFERROR(AVERAGEIFS($C$14:$C$18,$B$14:$B$18,E15),"") | G15: 0 | H15: =IF(ROUND(F15,6)=ROUND(G15,6),"PASS","FAIL")
A16: S3 | B16: SX | C16: --
A17: S4 | B17: SX
A18: S5 | B18: SY | C18: 0
A20: SX: 1 and 0.5 average to 0.75; '--' (not used) and blank (not entered) are left out. SY: 0 counts.
A22: Overall | B22: =IF(COUNTIF(D5:D9,"FAIL")+COUNTIF(H14:H15,"FAIL")+IF(D4="FAIL",1,0)=0,"ALL PASS","FAILURES")

Sheet WP FORMULA TESTS
A1: Case | B1: Eng (G) | C1: Prog (H) | D1: C&W (I) | E1: Dev (J) | F1: Loop (K) | G1: PreComm (L) | H1: Eng done? | I1: Prog done? | J1: C&W done? | K1: Dev done? | L1: Loop done? | M1: PreComm done? | N1: Gate | O1: Expected gate | P1: Expected Eng done? | Q1: PASS? | R1: What it tests
A2: T1 | B2: 1 | C2: 1 | D2: 1 | E2: 1 | F2: 1 | G2: 1 | H2: =IF($A2="","",IF(ISBLANK(B2),"",IF(TRIM(B2)="--","--",IF(ISNUMBER(B2),IF(B2>=1,"Yes",IF(B2=0,"No","PARTIAL")),"CHECK")))) | I2: =IF($A2="","",IF(ISBLANK(C2),"",IF(TRIM(C2)="--","--",IF(ISNUMBER(C2),IF(C2>=1,"Yes",IF(C2=0,"No","PARTIAL")),"CHECK")))) | J2: =IF($A2="","",IF(ISBLANK(D2),"",IF(TRIM(D2)="--","--",IF(ISNUMBER(D2),IF(D2>=1,"Yes",IF(D2=0,"No","PARTIAL")),"CHECK")))) | K2: =IF($A2="","",IF(ISBLANK(E2),"",IF(TRIM(E2)="--","--",IF(ISNUMBER(E2),IF(E2>=1,"Yes",IF(E2=0,"No","PARTIAL")),"CHECK")))) | L2: =IF($A2="","",IF(ISBLANK(F2),"",IF(TRIM(F2)="--","--",IF(ISNUMBER(F2),IF(F2>=1,"Yes",IF(F2=0,"No","PARTIAL")),"CHECK")))) | M2: =IF($A2="","",IF(ISBLANK(G2),"",IF(TRIM(G2)="--","--",IF(ISNUMBER(G2),IF(G2>=1,"Yes",IF(G2=0,"No","PARTIAL")),"CHECK")))) | N2: =IF(COUNTIF(H2:M2,"--")=6,"--",IF(COUNTIF(H2:M2,"Yes")+COUNTIF(H2:M2,"--")=6,"Yes","No")) | O2: Yes | P2: Yes | Q2: =IF(AND(N2=O2,H2=P2),"PASS","FAIL") | R2: all complete
A3: T2 | B3: 1 | C3: -- | D3: -- | E3: -- | F3: -- | G3: -- | H3: =IF($A3="","",IF(ISBLANK(B3),"",IF(TRIM(B3)="--","--",IF(ISNUMBER(B3),IF(B3>=1,"Yes",IF(B3=0,"No","PARTIAL")),"CHECK")))) | I3: =IF($A3="","",IF(ISBLANK(C3),"",IF(TRIM(C3)="--","--",IF(ISNUMBER(C3),IF(C3>=1,"Yes",IF(C3=0,"No","PARTIAL")),"CHECK")))) | J3: =IF($A3="","",IF(ISBLANK(D3),"",IF(TRIM(D3)="--","--",IF(ISNUMBER(D3),IF(D3>=1,"Yes",IF(D3=0,"No","PARTIAL")),"CHECK")))) | K3: =IF($A3="","",IF(ISBLANK(E3),"",IF(TRIM(E3)="--","--",IF(ISNUMBER(E3),IF(E3>=1,"Yes",IF(E3=0,"No","PARTIAL")),"CHECK")))) | L3: =IF($A3="","",IF(ISBLANK(F3),"",IF(TRIM(F3)="--","--",IF(ISNUMBER(F3),IF(F3>=1,"Yes",IF(F3=0,"No","PARTIAL")),"CHECK")))) | M3: =IF($A3="","",IF(ISBLANK(G3),"",IF(TRIM(G3)="--","--",IF(ISNUMBER(G3),IF(G3>=1,"Yes",IF(G3=0,"No","PARTIAL")),"CHECK")))) | N3: =IF(COUNTIF(H3:M3,"--")=6,"--",IF(COUNTIF(H3:M3,"Yes")+COUNTIF(H3:M3,"--")=6,"Yes","No")) | O3: Yes | P3: Yes | Q3: =IF(AND(N3=O3,H3=P3),"PASS","FAIL") | R3: Engineering-only WP (WP-ENG) complete
A4: T3 | B4: 0.5 | C4: -- | D4: -- | E4: -- | F4: -- | G4: -- | H4: =IF($A4="","",IF(ISBLANK(B4),"",IF(TRIM(B4)="--","--",IF(ISNUMBER(B4),IF(B4>=1,"Yes",IF(B4=0,"No","PARTIAL")),"CHECK")))) | I4: =IF($A4="","",IF(ISBLANK(C4),"",IF(TRIM(C4)="--","--",IF(ISNUMBER(C4),IF(C4>=1,"Yes",IF(C4=0,"No","PARTIAL")),"CHECK")))) | J4: =IF($A4="","",IF(ISBLANK(D4),"",IF(TRIM(D4)="--","--",IF(ISNUMBER(D4),IF(D4>=1,"Yes",IF(D4=0,"No","PARTIAL")),"CHECK")))) | K4: =IF($A4="","",IF(ISBLANK(E4),"",IF(TRIM(E4)="--","--",IF(ISNUMBER(E4),IF(E4>=1,"Yes",IF(E4=0,"No","PARTIAL")),"CHECK")))) | L4: =IF($A4="","",IF(ISBLANK(F4),"",IF(TRIM(F4)="--","--",IF(ISNUMBER(F4),IF(F4>=1,"Yes",IF(F4=0,"No","PARTIAL")),"CHECK")))) | M4: =IF($A4="","",IF(ISBLANK(G4),"",IF(TRIM(G4)="--","--",IF(ISNUMBER(G4),IF(G4>=1,"Yes",IF(G4=0,"No","PARTIAL")),"CHECK")))) | N4: =IF(COUNTIF(H4:M4,"--")=6,"--",IF(COUNTIF(H4:M4,"Yes")+COUNTIF(H4:M4,"--")=6,"Yes","No")) | O4: No | P4: PARTIAL | Q4: =IF(AND(N4=O4,H4=P4),"PASS","FAIL") | R4: Engineering-only WP in progress
A5: T4 | B5: -- | C5: -- | D5: -- | E5: -- | F5: -- | G5: -- | H5: =IF($A5="","",IF(ISBLANK(B5),"",IF(TRIM(B5)="--","--",IF(ISNUMBER(B5),IF(B5>=1,"Yes",IF(B5=0,"No","PARTIAL")),"CHECK")))) | I5: =IF($A5="","",IF(ISBLANK(C5),"",IF(TRIM(C5)="--","--",IF(ISNUMBER(C5),IF(C5>=1,"Yes",IF(C5=0,"No","PARTIAL")),"CHECK")))) | J5: =IF($A5="","",IF(ISBLANK(D5),"",IF(TRIM(D5)="--","--",IF(ISNUMBER(D5),IF(D5>=1,"Yes",IF(D5=0,"No","PARTIAL")),"CHECK")))) | K5: =IF($A5="","",IF(ISBLANK(E5),"",IF(TRIM(E5)="--","--",IF(ISNUMBER(E5),IF(E5>=1,"Yes",IF(E5=0,"No","PARTIAL")),"CHECK")))) | L5: =IF($A5="","",IF(ISBLANK(F5),"",IF(TRIM(F5)="--","--",IF(ISNUMBER(F5),IF(F5>=1,"Yes",IF(F5=0,"No","PARTIAL")),"CHECK")))) | M5: =IF($A5="","",IF(ISBLANK(G5),"",IF(TRIM(G5)="--","--",IF(ISNUMBER(G5),IF(G5>=1,"Yes",IF(G5=0,"No","PARTIAL")),"CHECK")))) | N5: =IF(COUNTIF(H5:M5,"--")=6,"--",IF(COUNTIF(H5:M5,"Yes")+COUNTIF(H5:M5,"--")=6,"Yes","No")) | O5: -- | P5: -- | Q5: =IF(AND(N5=O5,H5=P5),"PASS","FAIL") | R5: WP with nothing in use
A6: T5 | B6: 1 | C6: -- | D6: 1 | E6: -- | F6: -- | G6: -- | H6: =IF($A6="","",IF(ISBLANK(B6),"",IF(TRIM(B6)="--","--",IF(ISNUMBER(B6),IF(B6>=1,"Yes",IF(B6=0,"No","PARTIAL")),"CHECK")))) | I6: =IF($A6="","",IF(ISBLANK(C6),"",IF(TRIM(C6)="--","--",IF(ISNUMBER(C6),IF(C6>=1,"Yes",IF(C6=0,"No","PARTIAL")),"CHECK")))) | J6: =IF($A6="","",IF(ISBLANK(D6),"",IF(TRIM(D6)="--","--",IF(ISNUMBER(D6),IF(D6>=1,"Yes",IF(D6=0,"No","PARTIAL")),"CHECK")))) | K6: =IF($A6="","",IF(ISBLANK(E6),"",IF(TRIM(E6)="--","--",IF(ISNUMBER(E6),IF(E6>=1,"Yes",IF(E6=0,"No","PARTIAL")),"CHECK")))) | L6: =IF($A6="","",IF(ISBLANK(F6),"",IF(TRIM(F6)="--","--",IF(ISNUMBER(F6),IF(F6>=1,"Yes",IF(F6=0,"No","PARTIAL")),"CHECK")))) | M6: =IF($A6="","",IF(ISBLANK(G6),"",IF(TRIM(G6)="--","--",IF(ISNUMBER(G6),IF(G6>=1,"Yes",IF(G6=0,"No","PARTIAL")),"CHECK")))) | N6: =IF(COUNTIF(H6:M6,"--")=6,"--",IF(COUNTIF(H6:M6,"Yes")+COUNTIF(H6:M6,"--")=6,"Yes","No")) | O6: Yes | P6: Yes | Q6: =IF(AND(N6=O6,H6=P6),"PASS","FAIL") | R6: By-others WP (Eng + Cond & Wire) done
A7: T6 | B7: 1 | C7: -- | D7: 0 | E7: -- | F7: -- | G7: -- | H7: =IF($A7="","",IF(ISBLANK(B7),"",IF(TRIM(B7)="--","--",IF(ISNUMBER(B7),IF(B7>=1,"Yes",IF(B7=0,"No","PARTIAL")),"CHECK")))) | I7: =IF($A7="","",IF(ISBLANK(C7),"",IF(TRIM(C7)="--","--",IF(ISNUMBER(C7),IF(C7>=1,"Yes",IF(C7=0,"No","PARTIAL")),"CHECK")))) | J7: =IF($A7="","",IF(ISBLANK(D7),"",IF(TRIM(D7)="--","--",IF(ISNUMBER(D7),IF(D7>=1,"Yes",IF(D7=0,"No","PARTIAL")),"CHECK")))) | K7: =IF($A7="","",IF(ISBLANK(E7),"",IF(TRIM(E7)="--","--",IF(ISNUMBER(E7),IF(E7>=1,"Yes",IF(E7=0,"No","PARTIAL")),"CHECK")))) | L7: =IF($A7="","",IF(ISBLANK(F7),"",IF(TRIM(F7)="--","--",IF(ISNUMBER(F7),IF(F7>=1,"Yes",IF(F7=0,"No","PARTIAL")),"CHECK")))) | M7: =IF($A7="","",IF(ISBLANK(G7),"",IF(TRIM(G7)="--","--",IF(ISNUMBER(G7),IF(G7>=1,"Yes",IF(G7=0,"No","PARTIAL")),"CHECK")))) | N7: =IF(COUNTIF(H7:M7,"--")=6,"--",IF(COUNTIF(H7:M7,"Yes")+COUNTIF(H7:M7,"--")=6,"Yes","No")) | O7: No | P7: Yes | Q7: =IF(AND(N7=O7,H7=P7),"PASS","FAIL") | R7: By-others WP (Eng + Cond & Wire): submittal in, wiring not started
A8: T7 | C8: -- | D8: -- | E8: -- | F8: -- | G8: -- | H8: =IF($A8="","",IF(ISBLANK(B8),"",IF(TRIM(B8)="--","--",IF(ISNUMBER(B8),IF(B8>=1,"Yes",IF(B8=0,"No","PARTIAL")),"CHECK")))) | I8: =IF($A8="","",IF(ISBLANK(C8),"",IF(TRIM(C8)="--","--",IF(ISNUMBER(C8),IF(C8>=1,"Yes",IF(C8=0,"No","PARTIAL")),"CHECK")))) | J8: =IF($A8="","",IF(ISBLANK(D8),"",IF(TRIM(D8)="--","--",IF(ISNUMBER(D8),IF(D8>=1,"Yes",IF(D8=0,"No","PARTIAL")),"CHECK")))) | K8: =IF($A8="","",IF(ISBLANK(E8),"",IF(TRIM(E8)="--","--",IF(ISNUMBER(E8),IF(E8>=1,"Yes",IF(E8=0,"No","PARTIAL")),"CHECK")))) | L8: =IF($A8="","",IF(ISBLANK(F8),"",IF(TRIM(F8)="--","--",IF(ISNUMBER(F8),IF(F8>=1,"Yes",IF(F8=0,"No","PARTIAL")),"CHECK")))) | M8: =IF($A8="","",IF(ISBLANK(G8),"",IF(TRIM(G8)="--","--",IF(ISNUMBER(G8),IF(G8>=1,"Yes",IF(G8=0,"No","PARTIAL")),"CHECK")))) | N8: =IF(COUNTIF(H8:M8,"--")=6,"--",IF(COUNTIF(H8:M8,"Yes")+COUNTIF(H8:M8,"--")=6,"Yes","No")) | O8: No | Q8: =IF(AND(N8=O8,H8=P8),"PASS","FAIL") | R8: blank Eng is not done
A9: T8 | B9: 0 | C9: 0 | D9: 0 | E9: 0 | F9: 0 | G9: 0 | H9: =IF($A9="","",IF(ISBLANK(B9),"",IF(TRIM(B9)="--","--",IF(ISNUMBER(B9),IF(B9>=1,"Yes",IF(B9=0,"No","PARTIAL")),"CHECK")))) | I9: =IF($A9="","",IF(ISBLANK(C9),"",IF(TRIM(C9)="--","--",IF(ISNUMBER(C9),IF(C9>=1,"Yes",IF(C9=0,"No","PARTIAL")),"CHECK")))) | J9: =IF($A9="","",IF(ISBLANK(D9),"",IF(TRIM(D9)="--","--",IF(ISNUMBER(D9),IF(D9>=1,"Yes",IF(D9=0,"No","PARTIAL")),"CHECK")))) | K9: =IF($A9="","",IF(ISBLANK(E9),"",IF(TRIM(E9)="--","--",IF(ISNUMBER(E9),IF(E9>=1,"Yes",IF(E9=0,"No","PARTIAL")),"CHECK")))) | L9: =IF($A9="","",IF(ISBLANK(F9),"",IF(TRIM(F9)="--","--",IF(ISNUMBER(F9),IF(F9>=1,"Yes",IF(F9=0,"No","PARTIAL")),"CHECK")))) | M9: =IF($A9="","",IF(ISBLANK(G9),"",IF(TRIM(G9)="--","--",IF(ISNUMBER(G9),IF(G9>=1,"Yes",IF(G9=0,"No","PARTIAL")),"CHECK")))) | N9: =IF(COUNTIF(H9:M9,"--")=6,"--",IF(COUNTIF(H9:M9,"Yes")+COUNTIF(H9:M9,"--")=6,"Yes","No")) | O9: No | P9: No | Q9: =IF(AND(N9=O9,H9=P9),"PASS","FAIL") | R9: nothing started
A10: T9 | B10: n/a | C10: 1 | D10: 1 | E10: 1 | F10: 1 | G10: 1 | H10: =IF($A10="","",IF(ISBLANK(B10),"",IF(TRIM(B10)="--","--",IF(ISNUMBER(B10),IF(B10>=1,"Yes",IF(B10=0,"No","PARTIAL")),"CHECK")))) | I10: =IF($A10="","",IF(ISBLANK(C10),"",IF(TRIM(C10)="--","--",IF(ISNUMBER(C10),IF(C10>=1,"Yes",IF(C10=0,"No","PARTIAL")),"CHECK")))) | J10: =IF($A10="","",IF(ISBLANK(D10),"",IF(TRIM(D10)="--","--",IF(ISNUMBER(D10),IF(D10>=1,"Yes",IF(D10=0,"No","PARTIAL")),"CHECK")))) | K10: =IF($A10="","",IF(ISBLANK(E10),"",IF(TRIM(E10)="--","--",IF(ISNUMBER(E10),IF(E10>=1,"Yes",IF(E10=0,"No","PARTIAL")),"CHECK")))) | L10: =IF($A10="","",IF(ISBLANK(F10),"",IF(TRIM(F10)="--","--",IF(ISNUMBER(F10),IF(F10>=1,"Yes",IF(F10=0,"No","PARTIAL")),"CHECK")))) | M10: =IF($A10="","",IF(ISBLANK(G10),"",IF(TRIM(G10)="--","--",IF(ISNUMBER(G10),IF(G10>=1,"Yes",IF(G10=0,"No","PARTIAL")),"CHECK")))) | N10: =IF(COUNTIF(H10:M10,"--")=6,"--",IF(COUNTIF(H10:M10,"Yes")+COUNTIF(H10:M10,"--")=6,"Yes","No")) | O10: No | P10: CHECK | Q10: =IF(AND(N10=O10,H10=P10),"PASS","FAIL") | R10: stray text is flagged, not counted as done (old formula said Yes)
A11: T10 | B11: -- | C11: 1 | D11: 1 | E11: 1 | F11: 1 | G11: 1 | H11: =IF($A11="","",IF(ISBLANK(B11),"",IF(TRIM(B11)="--","--",IF(ISNUMBER(B11),IF(B11>=1,"Yes",IF(B11=0,"No","PARTIAL")),"CHECK")))) | I11: =IF($A11="","",IF(ISBLANK(C11),"",IF(TRIM(C11)="--","--",IF(ISNUMBER(C11),IF(C11>=1,"Yes",IF(C11=0,"No","PARTIAL")),"CHECK")))) | J11: =IF($A11="","",IF(ISBLANK(D11),"",IF(TRIM(D11)="--","--",IF(ISNUMBER(D11),IF(D11>=1,"Yes",IF(D11=0,"No","PARTIAL")),"CHECK")))) | K11: =IF($A11="","",IF(ISBLANK(E11),"",IF(TRIM(E11)="--","--",IF(ISNUMBER(E11),IF(E11>=1,"Yes",IF(E11=0,"No","PARTIAL")),"CHECK")))) | L11: =IF($A11="","",IF(ISBLANK(F11),"",IF(TRIM(F11)="--","--",IF(ISNUMBER(F11),IF(F11>=1,"Yes",IF(F11=0,"No","PARTIAL")),"CHECK")))) | M11: =IF($A11="","",IF(ISBLANK(G11),"",IF(TRIM(G11)="--","--",IF(ISNUMBER(G11),IF(G11>=1,"Yes",IF(G11=0,"No","PARTIAL")),"CHECK")))) | N11: =IF(COUNTIF(H11:M11,"--")=6,"--",IF(COUNTIF(H11:M11,"Yes")+COUNTIF(H11:M11,"--")=6,"Yes","No")) | O11: Yes | P11: -- | Q11: =IF(AND(N11=O11,H11=P11),"PASS","FAIL") | R11: dash with spaces still treated as not used
A13: Result | Q13: =IF(COUNTIF(Q2:Q11,"PASS")=10,"ALL PASS","FAILURES")
A15: Rules under test: '--' = column not used / by others, excluded from completion. A WP is complete when every column it uses is done. Blank = not done. Any other text = CHECK. Gate shows No (was '--') when not complete, because '--' now means not used.
